Workbook

Sheet Capa
A1: Ações | C1: Atualizado em | D1: =TODAY() -> 46073 | E1: Vídeo: Como usar a planilha | AP1: =$D$1-365 -> 45708 | AQ1: =$D$1-30 -> 46043
C4: Ações | D4: Vídeo: Como usar a planilha
A5: 5 | F5: INDICADORES FUNDAMENTALISTAS => | M5: Ideal é MAIOR que 4% | N5: Ideal é Entre 10 e 15 | O5: Ideal é Maior de 1,5 | T5: Menor melhor. Quer dizer gera caixa para enfrentar a crise | W5: Ideal <0,5 Aceitável <1
A6: TICKER | B6: Empresa | C6: Setor | D6: SubSetor | E6: Segmento | F6: PRECO ATUAL Graph 30 Dias | I6: Cotação Máxima 12 meses | L6: Queda do Máximo | M6: DY | N6: P/L | O6: P/VP | P6: P/ATIVOS | Q6: MARGEM BRUTA | R6: MARGEM EBIT | S6: MARG. LIQUIDA | T6: P/EBIT | U6: EV/EBIT | V6: DIVIDA LIQUIDA / EBIT | W6: DIV. LIQ. / PATRI. | X6: PSR | Y6: P/CAP. GIRO | Z6: P. AT CIR. LIQ. | AA6: LIQ. CORRENTE | AB6: ROE | AC6: ROA | AD6: ROIC | AE6: PATRIMONIO / ATIVOS | AF6: PASSIVOS / ATIVOS | AG6: GIRO ATIVOS | AH6: CAGR RECEITAS 5 ANOS | AI6: CAGR LUCROS 5 ANOS | AJ6: LIQUIDEZ MEDIA DIARIA | AK6: Alta | AL6: Baixa | AM6: Percentual de Curva | AN6: Volume | AO6: Preço Fechamento Anterior
A7: ='Dados StatusInvest'!A2:A621 -> AESB3 | B7: =IFERROR(__xludf.DUMMYFUNCTION("IFERROR((GOOGLEFINANCE(A7,""name"")),"""")"),"") | C7: =IFERROR((VLOOKUP(LEFT($A7,4),Setor!$A:$E,3,0)),"") | D7: =IFERROR((VLOOKUP(LEFT($A7,4),Setor!$A:$E,4,0)),"") | E7: =IFERROR((VLOOKUP(LEFT($A7,4),Setor!$A:$E,5,0)),"") | F7: =IFERROR(__xludf.DUMMYFUNCTION("IFERROR((GOOGLEFINANCE(A7)),"""")"),"") | G7: =IFERROR(__xludf.DUMMYFUNCTION("IFERROR((sparkline(GOOGLEFINANCE($A7,""price"",TODAY()-30,TODAY(),""DAILY""),{""charttype"",""line"";""linewidth"",1;""color"",""#5f88cc""})),"""")"),"") | H7: =IFERROR(__xludf.DUMMYFUNCTION("IFERROR((((GOOGLEFINANCE(A7))-(INDEX(GoogleFinance(A7,""PRICE"",$AQ$1),2,2)))/(INDEX(GoogleFinance(A7,""PRICE"",$AQ$1),2,2))),"""")"),"") | I7: =IFERROR(__xludf.DUMMYFUNCTION("IFERROR((GOOGLEFINANCE($A7,""high52"")),"""")"),"") | J7: =IFERROR(__xludf.DUMMYFUNCTION("IFERROR((sparkline(GOOGLEFINANCE($A7,""price"",TODAY()-365,TODAY(),""DAILY""),{""charttype"",""line"";""linewidth"",1;""color"",""#5f88cc""})),"""")"),"") | K7: =IFERROR(__xludf.DUMMYFUNCTION("IFERROR((((GOOGLEFINANCE(A7))-(INDEX(GoogleFinance(A7,""PRICE"",$AP$1),2,2)))/(INDEX(GoogleFinance(A7,""PRICE"",$AP$1),2,2))),"""")"),"") | L7: =IFERROR(((F7-I7)/I7),0) -> 0 | M7: =IFERROR((VLOOKUP($A7,'Dados StatusInvest'!$A:$AZ,COLUMN(M7)-$A$5,0)*VLOOKUP($A7,'Dados StatusInvest'!$A:$AZ,2,0)/$F7/100),0) -> 0 | N7: =IFERROR((VLOOKUP($A7,'Dados StatusInvest'!$A:$AZ,COLUMN(N7)-$A$5,0)/VLOOKUP($A7,'Dados StatusInvest'!$A:$AZ,2,0)*$F7),"") -> 0 | O7: =IFERROR((VLOOKUP($A7,'Dados StatusInvest'!$A:$AZ,COLUMN(O7)-$A$5,0)/VLOOKUP($A7,'Dados StatusInvest'!$A:$AZ,2,0)*$F7),0) -> 0 | P7: =IFERROR((VLOOKUP($A7,'Dados StatusInvest'!$A:$AZ,COLUMN(P7)-$A$5,0)/VLOOKUP($A7,'Dados StatusInvest'!$A:$AZ,2,0)*$F7),0) -> 0 | Q7: =IFERROR((VLOOKUP($A7,'Dados StatusInvest'!$A:$AZ,COLUMN(Q7)-$A$5,0)/100),0) -> 0.103 | R7: =VLOOKUP($A7,'Dados StatusInvest'!$A:$AZ,COLUMN(R7)-$A$5,0) -> 2.32 | S7: =IFERROR((VLOOKUP($A7,'Dados StatusInvest'!$A:$AZ,COLUMN(S7)-$A$5,0)),0) -> 1.89 | T7: =IFERROR((VLOOKUP($A7,'Dados StatusInvest'!$A:$AZ,COLUMN(T7)-$A$5,0)/VLOOKUP($A7,'Dados StatusInvest'!$A:$AZ,2,0)*$F7),0) -> 0 | U7: =IFERROR((VLOOKUP($A7,'Dados StatusInvest'!$A:$AZ,COLUMN(U7)-$A$5,0)-VLOOKUP($A7,'Dados StatusInvest'!$A:$AZ,COLUMN(U7)-$A$5-1,0)+T7),0) -> 50.08 | V7: =IFERROR((VLOOKUP($A7,'Dados StatusInvest'!$A:$AZ,COLUMN(V7)-$A$5,0)),0) -> 0.95 | W7: =IFERROR((VLOOKUP($A7,'Dados StatusInvest'!$A:$AZ,COLUMN(W7)-$A$5,0)),0) -> -12.23 | X7: =IFERROR((VLOOKUP($A7,'Dados StatusInvest'!$A:$AZ,COLUMN(X7)-$A$5,0)/VLOOKUP($A7,'Dados StatusInvest'!$A:$AZ,2,0)*$F7),0) -> 0 | Y7: =IFERROR((VLOOKUP($A7,'Dados StatusInvest'!$A:$AZ,COLUMN(Y7)-$A$5,0)/VLOOKUP($A7,'Dados StatusInvest'!$A:$AZ,2,0)*$F7),0) -> 0 | Z7: =IFERROR((VLOOKUP($A7,'Dados StatusInvest'!$A:$AZ,COLUMN(Z7)-$A$5,0)),0) -> 0.21 | AA7: =IFERROR((VLOOKUP($A7,'Dados StatusInvest'!$A:$AZ,COLUMN(AA7)-$A$5,0)),0) -> 0.73 | AB7: =IFERROR((VLOOKUP($A7,'Dados StatusInvest'!$A:$AZ,COLUMN(AB7)-$A$5,0)),0) -> 0.2 | AC7: =IFERROR((VLOOKUP($A7,'Dados StatusInvest'!$A:$AZ,COLUMN(AC7)-$A$5,0)),0) -> 0 | AD7: =IFERROR((VLOOKUP($A7,'Dados StatusInvest'!$A:$AZ,COLUMN(AD7)-$A$5,0)),0) -> 0 | AE7: =IFERROR((VLOOKUP($A7,'Dados StatusInvest'!$A:$AZ,COLUMN(AE7)-$A$5,0)),0) -> 13684494 | AF7: =IFERROR((VLOOKUP($A7,'Dados StatusInvest'!$A:$AZ,COLUMN(AF7)-$A$5,0)),0) -> 4.52 | AG7: =IFERROR((VLOOKUP($A7,'Dados StatusInvest'!$A:$AZ,COLUMN(AG7)-$A$5,0)),0) -> -0.55 | ... AJ7: =IFERROR((VLOOKUP($A7,'Dados StatusInvest'!$A:$AZ,COLUMN(AJ7)-$A$5,0)),0) | AK7: =IFERROR(__xludf.DUMMYFUNCTION("IFERROR(GOOGLEFINANCE($A7,""high""),"""")"),"") | AL7: =IFERROR(__xludf.DUMMYFUNCTION("IFERROR(GOOGLEFINANCE($A7,""low""),"""")"),"") | AM7: =IFERROR(((AK7-AL7)/AL7),0) -> 0 | AN7: =IFERROR(__xludf.DUMMYFUNCTION("IFERROR((GOOGLEFINANCE($A7,""volume"")),0)"),0.0) -> 0 | AO7: =IFERROR(__xludf.DUMMYFUNCTION("IFERROR((GOOGLEFINANCE($A7,""closeyest"")),"""")"),"") | AP7: =IFERROR(__xludf.DUMMYFUNCTION("IFERROR((GOOGLEFINANCE($A7,""shares"")),"""")"),"")
A8: ='Dados StatusInvest'!A3:A622 -> AFLT3 | B8: =IFERROR(__xludf.DUMMYFUNCTION("IFERROR((GOOGLEFINANCE(A8,""name"")),"""")"),"Afluente Transmissao de Energia Eltrc SA") -> Afluente Transmissao de Energia Eltrc SA | C8: =IFERROR((VLOOKUP(LEFT($A8,4),Setor!$A:$E,3,0)),"") -> Utilidade Pública | D8: =IFERROR((VLOOKUP(LEFT($A8,4),Setor!$A:$E,4,0)),"") -> Energia Elétrica | E8: =IFERROR((VLOOKUP(LEFT($A8,4),Setor!$A:$E,5,0)),"") -> Energia Elétrica | F8: =IFERROR(__xludf.DUMMYFUNCTION("IFERROR((GOOGLEFINANCE(A8)),"""")"),7.39) -> 7.39 | G8: =IFERROR(__xludf.DUMMYFUNCTION("IFERROR((sparkline(GOOGLEFINANCE($A8,""price"",TODAY()-30,TODAY(),""DAILY""),{""charttype"",""line"";""linewidth"",1;""color"",""#5f88cc""})),"""")"),"") | H8: =IFERROR(__xludf.DUMMYFUNCTION("IFERROR((((GOOGLEFINANCE(A8))-(INDEX(GoogleFinance(A8,""PRICE"",$AQ$1),2,2)))/(INDEX(GoogleFinance(A8,""PRICE"",$AQ$1),2,2))),"""")"),0.005442176870748304) -> 0.0054421769 | I8: =IFERROR(__xludf.DUMMYFUNCTION("IFERROR((GOOGLEFINANCE($A8,""high52"")),"""")"),7.84) -> 7.84 | J8: =IFERROR(__xludf.DUMMYFUNCTION("IFERROR((sparkline(GOOGLEFINANCE($A8,""price"",TODAY()-365,TODAY(),""DAILY""),{""charttype"",""line"";""linewidth"",1;""color"",""#5f88cc""})),"""")"),"") | K8: =IFERROR(__xludf.DUMMYFUNCTION("IFERROR((((GOOGLEFINANCE(A8))-(INDEX(GoogleFinance(A8,""PRICE"",$AP$1),2,2)))/(INDEX(GoogleFinance(A8,""PRICE"",$AP$1),2,2))),"""")"),0.042313117066290526) -> 0.042313117 | L8: =IFERROR(((F8-I8)/I8),0) -> -0.057397959 | M8: =IFERROR((VLOOKUP($A8,'Dados StatusInvest'!$A:$AZ,COLUMN(M8)-$A$5,0)*VLOOKUP($A8,'Dados StatusInvest'!$A:$AZ,2,0)/$F8/100),0) -> 0.6147 | N8: =IFERROR((VLOOKUP($A8,'Dados StatusInvest'!$A:$AZ,COLUMN(N8)-$A$5,0)/VLOOKUP($A8,'Dados StatusInvest'!$A:$AZ,2,0)*$F8),"") -> 42.8 | O8: =IFERROR((VLOOKUP($A8,'Dados StatusInvest'!$A:$AZ,COLUMN(O8)-$A$5,0)/VLOOKUP($A8,'Dados StatusInvest'!$A:$AZ,2,0)*$F8),0) -> 9.31 | P8: =IFERROR((VLOOKUP($A8,'Dados StatusInvest'!$A:$AZ,COLUMN(P8)-$A$5,0)/VLOOKUP($A8,'Dados StatusInvest'!$A:$AZ,2,0)*$F8),0) -> 9.1 | Q8: =IFERROR((VLOOKUP($A8,'Dados StatusInvest'!$A:$AZ,COLUMN(Q8)-$A$5,0)/100),0) -> -0.0021 | R8: =VLOOKUP($A8,'Dados StatusInvest'!$A:$AZ,COLUMN(R8)-$A$5,0) -> -0.04 | S8: =IFERROR((VLOOKUP($A8,'Dados StatusInvest'!$A:$AZ,COLUMN(S8)-$A$5,0)),0) -> 5.72 | T8: =IFERROR((VLOOKUP($A8,'Dados StatusInvest'!$A:$AZ,COLUMN(T8)-$A$5,0)/VLOOKUP($A8,'Dados StatusInvest'!$A:$AZ,2,0)*$F8),0) -> 5.92 | U8: =IFERROR((VLOOKUP($A8,'Dados StatusInvest'!$A:$AZ,COLUMN(U8)-$A$5,0)-VLOOKUP($A8,'Dados StatusInvest'!$A:$AZ,COLUMN(U8)-$A$5-1,0)+T8),0) -> -1.82 | V8: =IFERROR((VLOOKUP($A8,'Dados StatusInvest'!$A:$AZ,COLUMN(V8)-$A$5,0)),0) -> 2.9 | W8: =IFERROR((VLOOKUP($A8,'Dados StatusInvest'!$A:$AZ,COLUMN(W8)-$A$5,0)),0) -> 13.65 | X8: =IFERROR((VLOOKUP($A8,'Dados StatusInvest'!$A:$AZ,COLUMN(X8)-$A$5,0)/VLOOKUP($A8,'Dados StatusInvest'!$A:$AZ,2,0)*$F8),0) -> 9.25 | Y8: =IFERROR((VLOOKUP($A8,'Dados StatusInvest'!$A:$AZ,COLUMN(Y8)-$A$5,0)/VLOOKUP($A8,'Dados StatusInvest'!$A:$AZ,2,0)*$F8),0) -> 13.92 | Z8: =IFERROR((VLOOKUP($A8,'Dados StatusInvest'!$A:$AZ,COLUMN(Z8)-$A$5,0)),0) -> 0.68 | AA8: =IFERROR((VLOOKUP($A8,'Dados StatusInvest'!$A:$AZ,COLUMN(AA8)-$A$5,0)),0) -> 0.32 | AB8: =IFERROR((VLOOKUP($A8,'Dados StatusInvest'!$A:$AZ,COLUMN(AB8)-$A$5,0)),0) -> 0.22 | AC8: =IFERROR((VLOOKUP($A8,'Dados StatusInvest'!$A:$AZ,COLUMN(AC8)-$A$5,0)),0) -> 17.36 | AD8: =IFERROR((VLOOKUP($A8,'Dados StatusInvest'!$A:$AZ,COLUMN(AD8)-$A$5,0)),0) -> 6.66 | AE8: =IFERROR((VLOOKUP($A8,'Dados StatusInvest'!$A:$AZ,COLUMN(AE8)-$A$5,0)),0) -> 2146.31 | AF8: =IFERROR((VLOOKUP($A8,'Dados StatusInvest'!$A:$AZ,COLUMN(AF8)-$A$5,0)),0) -> 4.05 | AG8: =IFERROR((VLOOKUP($A8,'Dados StatusInvest'!$A:$AZ,COLUMN(AG8)-$A$5,0)),0) -> 0.55 | ... AJ8: =IFERROR((VLOOKUP($A8,'Dados StatusInvest'!$A:$AZ,COLUMN(AJ8)-$A$5,0)),0) | AK8: =IFERROR(__xludf.DUMMYFUNCTION("IFERROR(GOOGLEFINANCE($A8,""high""),"""")"),"") | AL8: =IFERROR(__xludf.DUMMYFUNCTION("IFERROR(GOOGLEFINANCE($A8,""low""),"""")"),"") | AM8: =IFERROR(((AK8-AL8)/AL8),0) -> 0 | AN8: =IFERROR(__xludf.DUMMYFUNCTION("IFERROR((GOOGLEFINANCE($A8,""volume"")),0)"),0.0) -> 0 | AO8: =IFERROR(__xludf.DUMMYFUNCTION("IFERROR((GOOGLEFINANCE($A8,""closeyest"")),"""")"),7.39) -> 7.39 | AP8: =IFERROR(__xludf.DUMMYFUNCTION("IFERROR((GOOGLEFINANCE($A8,""shares"")),"""")"),6.30847E7) -> 63084700
A9: ='Dados StatusInvest'!A4:A623 -> AGRO3 | B9: =IFERROR(__xludf.DUMMYFUNCTION("IFERROR((GOOGLEFINANCE(A9,""name"")),"""")"),"BrasilAgro - Companhia Brslr d Prprd Agr") -> BrasilAgro - Companhia Brslr d Prprd Agr | C9: =IFERROR((VLOOKUP(LEFT($A9,4),Setor!$A:$E,3,0)),"") -> Consumo não Cíclico | D9: =IFERROR((VLOOKUP(LEFT($A9,4),Setor!$A:$E,4,0)),"") -> Agropecuária | E9: =IFERROR((VLOOKUP(LEFT($A9,4),Setor!$A:$E,5,0)),"") -> Agricultura | F9: =IFERROR(__xludf.DUMMYFUNCTION("IFERROR((GOOGLEFINANCE(A9)),"""")"),20.24) -> 20.24 | G9: =IFERROR(__xludf.DUMMYFUNCTION("IFERROR((sparkline(GOOGLEFINANCE($A9,""price"",TODAY()-30,TODAY(),""DAILY""),{""charttype"",""line"";""linewidth"",1;""color"",""#5f88cc""})),"""")"),"") | H9: =IFERROR(__xludf.DUMMYFUNCTION("IFERROR((((GOOGLEFINANCE(A9))-(INDEX(GoogleFinance(A9,""PRICE"",$AQ$1),2,2)))/(INDEX(GoogleFinance(A9,""PRICE"",$AQ$1),2,2))),"""")"),-0.0434782608695653) -> -0.043478261 | I9: =IFERROR(__xludf.DUMMYFUNCTION("IFERROR((GOOGLEFINANCE($A9,""high52"")),"""")"),22.21) -> 22.21 | J9: =IFERROR(__xludf.DUMMYFUNCTION("IFERROR((sparkline(GOOGLEFINANCE($A9,""price"",TODAY()-365,TODAY(),""DAILY""),{""charttype"",""line"";""linewidth"",1;""color"",""#5f88cc""})),"""")"),"") | K9: =IFERROR(__xludf.DUMMYFUNCTION("IFERROR((((GOOGLEFINANCE(A9))-(INDEX(GoogleFinance(A9,""PRICE"",$AP$1),2,2)))/(INDEX(GoogleFinance(A9,""PRICE"",$AP$1),2,2))),"""")"),-0.043026004728132394) -> -0.043026005 | L9: =IFERROR(((F9-I9)/I9),0) -> -0.088698784 | M9: =IFERROR((VLOOKUP($A9,'Dados StatusInvest'!$A:$AZ,COLUMN(M9)-$A$5,0)*VLOOKUP($A9,'Dados StatusInvest'!$A:$AZ,2,0)/$F9/100),0) -> 0.019619368 | N9: =IFERROR((VLOOKUP($A9,'Dados StatusInvest'!$A:$AZ,COLUMN(N9)-$A$5,0)/VLOOKUP($A9,'Dados StatusInvest'!$A:$AZ,2,0)*$F9),"") -> -0.14985192 | O9: =IFERROR((VLOOKUP($A9,'Dados StatusInvest'!$A:$AZ,COLUMN(O9)-$A$5,0)/VLOOKUP($A9,'Dados StatusInvest'!$A:$AZ,2,0)*$F9),0) -> 103.9373 | P9: =IFERROR((VLOOKUP($A9,'Dados StatusInvest'!$A:$AZ,COLUMN(P9)-$A$5,0)/VLOOKUP($A9,'Dados StatusInvest'!$A:$AZ,2,0)*$F9),0) -> 167.30468 | Q9: =IFERROR((VLOOKUP($A9,'Dados StatusInvest'!$A:$AZ,COLUMN(Q9)-$A$5,0)/100),0) -> 0.6343 | R9: =VLOOKUP($A9,'Dados StatusInvest'!$A:$AZ,COLUMN(R9)-$A$5,0) -> 0.61 | S9: =IFERROR((VLOOKUP($A9,'Dados StatusInvest'!$A:$AZ,COLUMN(S9)-$A$5,0)),0) -> 2.04 | T9: =IFERROR((VLOOKUP($A9,'Dados StatusInvest'!$A:$AZ,COLUMN(T9)-$A$5,0)/VLOOKUP($A9,'Dados StatusInvest'!$A:$AZ,2,0)*$F9),0) -> 5.1149457 | U9: =IFERROR((VLOOKUP($A9,'Dados StatusInvest'!$A:$AZ,COLUMN(U9)-$A$5,0)-VLOOKUP($A9,'Dados StatusInvest'!$A:$AZ,COLUMN(U9)-$A$5-1,0)+T9),0) -> -0.78505429 | V9: =IFERROR((VLOOKUP($A9,'Dados StatusInvest'!$A:$AZ,COLUMN(V9)-$A$5,0)),0) -> 1.61 | W9: =IFERROR((VLOOKUP($A9,'Dados StatusInvest'!$A:$AZ,COLUMN(W9)-$A$5,0)),0) -> -0.08 | X9: =IFERROR((VLOOKUP($A9,'Dados StatusInvest'!$A:$AZ,COLUMN(X9)-$A$5,0)/VLOOKUP($A9,'Dados StatusInvest'!$A:$AZ,2,0)*$F9),0) -> -0.039960513 | Y9: =IFERROR((VLOOKUP($A9,'Dados StatusInvest'!$A:$AZ,COLUMN(Y9)-$A$5,0)/VLOOKUP($A9,'Dados StatusInvest'!$A:$AZ,2,0)*$F9),0) -> -1.0289832 | Z9: =IFERROR((VLOOKUP($A9,'Dados StatusInvest'!$A:$AZ,COLUMN(Z9)-$A$5,0)),0) -> 0.56 | AA9: =IFERROR((VLOOKUP($A9,'Dados StatusInvest'!$A:$AZ,COLUMN(AA9)-$A$5,0)),0) -> 0.44 | AB9: =IFERROR((VLOOKUP($A9,'Dados StatusInvest'!$A:$AZ,COLUMN(AB9)-$A$5,0)),0) -> 0.27 | AC9: =IFERROR((VLOOKUP($A9,'Dados StatusInvest'!$A:$AZ,COLUMN(AC9)-$A$5,0)),0) -> 10.7 | AD9: =IFERROR((VLOOKUP($A9,'Dados StatusInvest'!$A:$AZ,COLUMN(AD9)-$A$5,0)),0) -> 0 | AE9: =IFERROR((VLOOKUP($A9,'Dados StatusInvest'!$A:$AZ,COLUMN(AE9)-$A$5,0)),0) -> 4102180 | AF9: =IFERROR((VLOOKUP($A9,'Dados StatusInvest'!$A:$AZ,COLUMN(AF9)-$A$5,0)),0) -> 20.24 | AG9: =IFERROR((VLOOKUP($A9,'Dados StatusInvest'!$A:$AZ,COLUMN(AG9)-$A$5,0)),0) -> -0.02 | ... AJ9: =IFERROR((VLOOKUP($A9,'Dados StatusInvest'!$A:$AZ,COLUMN(AJ9)-$A$5,0)),0) | AK9: =IFERROR(__xludf.DUMMYFUNCTION("IFERROR(GOOGLEFINANCE($A9,""high""),"""")"),20.26) -> 20.26 | AL9: =IFERROR(__xludf.DUMMYFUNCTION("IFERROR(GOOGLEFINANCE($A9,""low""),"""")"),20.12) -> 20.12 | AM9: =IFERROR(((AK9-AL9)/AL9),0) -> 0.0069582505 | AN9: =IFERROR(__xludf.DUMMYFUNCTION("IFERROR((GOOGLEFINANCE($A9,""volume"")),0)"),8400.0) -> 8400 | AO9: =IFERROR(__xludf.DUMMYFUNCTION("IFERROR((GOOGLEFINANCE($A9,""closeyest"")),"""")"),20.26) -> 20.26 | AP9: =IFERROR(__xludf.DUMMYFUNCTION("IFERROR((GOOGLEFINANCE($A9,""shares"")),"""")"),1.02683444E8) -> 102683444
A10: ='Dados StatusInvest'!A5:A624 -> AGXY3 | B10: =IFERROR(__xludf.DUMMYFUNCTION("IFERROR((GOOGLEFINANCE(A10,""name"")),"""")"),"Agrogalaxy Participacoes SA em Recupera") -> Agrogalaxy Participacoes SA em Recupera | C10: =IFERROR((VLOOKUP(LEFT($A10,4),Setor!$A:$E,3,0)),"") | D10: =IFERROR((VLOOKUP(LEFT($A10,4),Setor!$A:$E,4,0)),"") | E10: =IFERROR((VLOOKUP(LEFT($A10,4),Setor!$A:$E,5,0)),"") | F10: =IFERROR(__xludf.DUMMYFUNCTION("IFERROR((GOOGLEFINANCE(A10)),"""")"),2.45) -> 2.45 | G10: =IFERROR(__xludf.DUMMYFUNCTION("IFERROR((sparkline(GOOGLEFINANCE($A10,""price"",TODAY()-30,TODAY(),""DAILY""),{""charttype"",""line"";""linewidth"",1;""color"",""#5f88cc""})),"""")"),"") | H10: =IFERROR(__xludf.DUMMYFUNCTION("IFERROR((((GOOGLEFINANCE(A10))-(INDEX(GoogleFinance(A10,""PRICE"",$AQ$1),2,2)))/(INDEX(GoogleFinance(A10,""PRICE"",$AQ$1),2,2))),"""")"),-0.38442211055276376) -> -0.38442211 | I10: =IFERROR(__xludf.DUMMYFUNCTION("IFERROR((GOOGLEFINANCE($A10,""high52"")),"""")"),9.9) -> 9.9 | J10: =IFERROR(__xludf.DUMMYFUNCTION("IFERROR((sparkline(GOOGLEFINANCE($A10,""price"",TODAY()-365,TODAY(),""DAILY""),{""charttype"",""line"";""linewidth"",1;""color"",""#5f88cc""})),"""")"),"") | K10: =IFERROR(__xludf.DUMMYFUNCTION("IFERROR((((GOOGLEFINANCE(A10))-(INDEX(GoogleFinance(A10,""PRICE"",$AP$1),2,2)))/(INDEX(GoogleFinance(A10,""PRICE"",$AP$1),2,2))),"""")"),-0.7447916666666666) -> -0.74479167 | L10: =IFERROR(((F10-I10)/I10),0) -> -0.75252525 | M10: =IFERROR((VLOOKUP($A10,'Dados StatusInvest'!$A:$AZ,COLUMN(M10)-$A$5,0)*VLOOKUP($A10,'Dados StatusInvest'!$A:$AZ,2,0)/$F10/100),0) -> 0.40713224 | N10: =IFERROR((VLOOKUP($A10,'Dados StatusInvest'!$A:$AZ,COLUMN(N10)-$A$5,0)/VLOOKUP($A10,'Dados StatusInvest'!$A:$AZ,2,0)*$F10),"") -> 68.385259 | O10: =IFERROR((VLOOKUP($A10,'Dados StatusInvest'!$A:$AZ,COLUMN(O10)-$A$5,0)/VLOOKUP($A10,'Dados StatusInvest'!$A:$AZ,2,0)*$F10),0) -> 0.058565737 | P10: =IFERROR((VLOOKUP($A10,'Dados StatusInvest'!$A:$AZ,COLUMN(P10)-$A$5,0)/VLOOKUP($A10,'Dados StatusInvest'!$A:$AZ,2,0)*$F10),0) -> 1.3860558 | Q10: =IFERROR((VLOOKUP($A10,'Dados StatusInvest'!$A:$AZ,COLUMN(Q10)-$A$5,0)/100),0) -> 0.0136 | R10: =VLOOKUP($A10,'Dados StatusInvest'!$A:$AZ,COLUMN(R10)-$A$5,0) -> 0 | S10: =IFERROR((VLOOKUP($A10,'Dados StatusInvest'!$A:$AZ,COLUMN(S10)-$A$5,0)),0) -> 0.02 | T10: =IFERROR((VLOOKUP($A10,'Dados StatusInvest'!$A:$AZ,COLUMN(T10)-$A$5,0)/VLOOKUP($A10,'Dados StatusInvest'!$A:$AZ,2,0)*$F10),0) -> 0.087848606 | U10: =IFERROR((VLOOKUP($A10,'Dados StatusInvest'!$A:$AZ,COLUMN(U10)-$A$5,0)-VLOOKUP($A10,'Dados StatusInvest'!$A:$AZ,COLUMN(U10)-$A$5-1,0)+T10),0) -> -0.032151394 | V10: =IFERROR((VLOOKUP($A10,'Dados StatusInvest'!$A:$AZ,COLUMN(V10)-$A$5,0)),0) -> 2.19 | W10: =IFERROR((VLOOKUP($A10,'Dados StatusInvest'!$A:$AZ,COLUMN(W10)-$A$5,0)),0) -> -661.54 | X10: =IFERROR((VLOOKUP($A10,'Dados StatusInvest'!$A:$AZ,COLUMN(X10)-$A$5,0)/VLOOKUP($A10,'Dados StatusInvest'!$A:$AZ,2,0)*$F10),0) -> 54.056175 | Y10: =IFERROR((VLOOKUP($A10,'Dados StatusInvest'!$A:$AZ,COLUMN(Y10)-$A$5,0)/VLOOKUP($A10,'Dados StatusInvest'!$A:$AZ,2,0)*$F10),0) -> 81.660159 | Z10: =IFERROR((VLOOKUP($A10,'Dados StatusInvest'!$A:$AZ,COLUMN(Z10)-$A$5,0)),0) -> -0.08 | AA10: =IFERROR((VLOOKUP($A10,'Dados StatusInvest'!$A:$AZ,COLUMN(AA10)-$A$5,0)),0) -> 1.08 | AB10: =IFERROR((VLOOKUP($A10,'Dados StatusInvest'!$A:$AZ,COLUMN(AB10)-$A$5,0)),0) -> 0.79 | AC10: =IFERROR((VLOOKUP($A10,'Dados StatusInvest'!$A:$AZ,COLUMN(AC10)-$A$5,0)),0) -> 24.29 | AD10: =IFERROR((VLOOKUP($A10,'Dados StatusInvest'!$A:$AZ,COLUMN(AD10)-$A$5,0)),0) -> 123.15 | AE10: =IFERROR((VLOOKUP($A10,'Dados StatusInvest'!$A:$AZ,COLUMN(AE10)-$A$5,0)),0) -> 118357.5 | AF10: =IFERROR((VLOOKUP($A10,'Dados StatusInvest'!$A:$AZ,COLUMN(AF10)-$A$5,0)),0) -> -10.93 | AG10: =IFERROR((VLOOKUP($A10,'Dados StatusInvest'!$A:$AZ,COLUMN(AG10)-$A$5,0)),0) -> 72.3 | ... AJ10: =IFERROR((VLOOKUP($A10,'Dados StatusInvest'!$A:$AZ,COLUMN(AJ10)-$A$5,0)),0) | AK10: =IFERROR(__xludf.DUMMYFUNCTION("IFERROR(GOOGLEFINANCE($A10,""high""),"""")"),2.51) -> 2.51 | AL10: =IFERROR(__xludf.DUMMYFUNCTION("IFERROR(GOOGLEFINANCE($A10,""low""),"""")"),2.43) -> 2.43 | AM10: =IFERROR(((AK10-AL10)/AL10),0) -> 0.032921811 | AN10: =IFERROR(__xludf.DUMMYFUNCTION("IFERROR((GOOGLEFINANCE($A10,""volume"")),0)"),10300.0) -> 10300 | AO10: =IFERROR(__xludf.DUMMYFUNCTION("IFERROR((GOOGLEFINANCE($A10,""closeyest"")),"""")"),2.51) -> 2.51 | AP10: =IFERROR(__xludf.DUMMYFUNCTION("IFERROR((GOOGLEFINANCE($A10,""shares"")),"""")"),1.6969571E7) -> 16969571
A11: ='Dados StatusInvest'!A6:A625 -> AHEB3 | B11: =IFERROR(__xludf.DUMMYFUNCTION("IFERROR((GOOGLEFINANCE(A11,""name"")),"""")"),"Sao Paulo Turismo SA") -> Sao Paulo Turismo SA | C11: =IFERROR((VLOOKUP(LEFT($A11,4),Setor!$A:$E,3,0)),"") -> Consumo Cíclico | D11: =IFERROR((VLOOKUP(LEFT($A11,4),Setor!$A:$E,4,0)),"") -> Viagens e Lazer | E11: =IFERROR((VLOOKUP(LEFT($A11,4),Setor!$A:$E,5,0)),"") -> Produção de Eventos e Shows | F11: =IFERROR(__xludf.DUMMYFUNCTION("IFERROR((GOOGLEFINANCE(A11)),"""")"),25.0) -> 25 | G11: =IFERROR(__xludf.DUMMYFUNCTION("IFERROR((sparkline(GOOGLEFINANCE($A11,""price"",TODAY()-30,TODAY(),""DAILY""),{""charttype"",""line"";""linewidth"",1;""color"",""#5f88cc""})),"""")"),"") | H11: =IFERROR(__xludf.DUMMYFUNCTION("IFERROR((((GOOGLEFINANCE(A11))-(INDEX(GoogleFinance(A11,""PRICE"",$AQ$1),2,2)))/(INDEX(GoogleFinance(A11,""PRICE"",$AQ$1),2,2))),"""")"),0.041666666666666664) -> 0.041666667 | I11: =IFERROR(__xludf.DUMMYFUNCTION("IFERROR((GOOGLEFINANCE($A11,""high52"")),"""")"),45.0) -> 45 | J11: =IFERROR(__xludf.DUMMYFUNCTION("IFERROR((sparkline(GOOGLEFINANCE($A11,""price"",TODAY()-365,TODAY(),""DAILY""),{""charttype"",""line"";""linewidth"",1;""color"",""#5f88cc""})),"""")"),"") | K11: =IFERROR(__xludf.DUMMYFUNCTION("IFERROR((((GOOGLEFINANCE(A11))-(INDEX(GoogleFinance(A11,""PRICE"",$AP$1),2,2)))/(INDEX(GoogleFinance(A11,""PRICE"",$AP$1),2,2))),"""")"),"") | L11: =IFERROR(((F11-I11)/I11),0) -> -0.44444444 | M11: =IFERROR((VLOOKUP($A11,'Dados StatusInvest'!$A:$AZ,COLUMN(M11)-$A$5,0)*VLOOKUP($A11,'Dados StatusInvest'!$A:$AZ,2,0)/$F11/100),0) -> 0.1104 | N11: =IFERROR((VLOOKUP($A11,'Dados StatusInvest'!$A:$AZ,COLUMN(N11)-$A$5,0)/VLOOKUP($A11,'Dados StatusInvest'!$A:$AZ,2,0)*$F11),"") -> 12.25 | O11: =IFERROR((VLOOKUP($A11,'Dados StatusInvest'!$A:$AZ,COLUMN(O11)-$A$5,0)/VLOOKUP($A11,'Dados StatusInvest'!$A:$AZ,2,0)*$F11),0) -> 2.87 | P11: =IFERROR((VLOOKUP($A11,'Dados StatusInvest'!$A:$AZ,COLUMN(P11)-$A$5,0)/VLOOKUP($A11,'Dados StatusInvest'!$A:$AZ,2,0)*$F11),0) -> 1.9 | Q11: =IFERROR((VLOOKUP($A11,'Dados StatusInvest'!$A:$AZ,COLUMN(Q11)-$A$5,0)/100),0) -> -0.0103 | R11: =VLOOKUP($A11,'Dados StatusInvest'!$A:$AZ,COLUMN(R11)-$A$5,0) -> -0.3 | S11: =IFERROR((VLOOKUP($A11,'Dados StatusInvest'!$A:$AZ,COLUMN(S11)-$A$5,0)),0) -> 0.32 | T11: =IFERROR((VLOOKUP($A11,'Dados StatusInvest'!$A:$AZ,COLUMN(T11)-$A$5,0)/VLOOKUP($A11,'Dados StatusInvest'!$A:$AZ,2,0)*$F11),0) -> 1.43 | U11: =IFERROR((VLOOKUP($A11,'Dados StatusInvest'!$A:$AZ,COLUMN(U11)-$A$5,0)-VLOOKUP($A11,'Dados StatusInvest'!$A:$AZ,COLUMN(U11)-$A$5-1,0)+T11),0) -> -0.63 | V11: =IFERROR((VLOOKUP($A11,'Dados StatusInvest'!$A:$AZ,COLUMN(V11)-$A$5,0)),0) -> 2.46 | W11: =IFERROR((VLOOKUP($A11,'Dados StatusInvest'!$A:$AZ,COLUMN(W11)-$A$5,0)),0) -> 32.19 | X11: =IFERROR((VLOOKUP($A11,'Dados StatusInvest'!$A:$AZ,COLUMN(X11)-$A$5,0)/VLOOKUP($A11,'Dados StatusInvest'!$A:$AZ,2,0)*$F11),0) -> 13.95 | Y11: =IFERROR((VLOOKUP($A11,'Dados StatusInvest'!$A:$AZ,COLUMN(Y11)-$A$5,0)/VLOOKUP($A11,'Dados StatusInvest'!$A:$AZ,2,0)*$F11),0) -> 27.08 | Z11: =IFERROR((VLOOKUP($A11,'Dados StatusInvest'!$A:$AZ,COLUMN(Z11)-$A$5,0)),0) -> 0.43 | AA11: =IFERROR((VLOOKUP($A11,'Dados StatusInvest'!$A:$AZ,COLUMN(AA11)-$A$5,0)),0) -> 0.57 | AB11: =IFERROR((VLOOKUP($A11,'Dados StatusInvest'!$A:$AZ,COLUMN(AB11)-$A$5,0)),0) -> 1.14 | AC11: =IFERROR((VLOOKUP($A11,'Dados StatusInvest'!$A:$AZ,COLUMN(AC11)-$A$5,0)),0) -> 44.62 | AD11: =IFERROR((VLOOKUP($A11,'Dados StatusInvest'!$A:$AZ,COLUMN(AD11)-$A$5,0)),0) -> 0 | AE11: =IFERROR((VLOOKUP($A11,'Dados StatusInvest'!$A:$AZ,COLUMN(AE11)-$A$5,0)),0) -> 2100 | AF11: =IFERROR((VLOOKUP($A11,'Dados StatusInvest'!$A:$AZ,COLUMN(AF11)-$A$5,0)),0) -> 30 | AG11: =IFERROR((VLOOKUP($A11,'Dados StatusInvest'!$A:$AZ,COLUMN(AG11)-$A$5,0)),0) -> 9.66 | ... AJ11: =IFERROR((VLOOKUP($A11,'Dados StatusInvest'!$A:$AZ,COLUMN(AJ11)-$A$5,0)),0) | AK11: =IFERROR(__xludf.DUMMYFUNCTION("IFERROR(GOOGLEFINANCE($A11,""high""),"""")"),"") | AL11: =IFERROR(__xludf.DUMMYFUNCTION("IFERROR(GOOGLEFINANCE($A11,""low""),"""")"),"") | AM11: =IFERROR(((AK11-AL11)/AL11),0) -> 0 | AN11: =IFERROR(__xludf.DUMMYFUNCTION("IFERROR((GOOGLEFINANCE($A11,""volume"")),0)"),0.0) -> 0 | AO11: =IFERROR(__xludf.DUMMYFUNCTION("IFERROR((GOOGLEFINANCE($A11,""closeyest"")),"""")"),25.0) -> 25 | AP11: =IFERROR(__xludf.DUMMYFUNCTION("IFERROR((GOOGLEFINANCE($A11,""shares"")),"""")"),8407877.0) -> 8407877
A12: ='Dados StatusInvest'!A7:A626 -> AHEB5 | B12: =IFERROR(__xludf.DUMMYFUNCTION("IFERROR((GOOGLEFINANCE(A12,""name"")),"""")"),"Sao Paulo Turismo Class Pref Shs Class A") -> Sao Paulo Turismo Class Pref Shs Class A | C12: =IFERROR((VLOOKUP(LEFT($A12,4),Setor!$A:$E,3,0)),"") -> Consumo Cíclico | D12: =IFERROR((VLOOKUP(LEFT($A12,4),Setor!$A:$E,4,0)),"") -> Viagens e Lazer | E12: =IFERROR((VLOOKUP(LEFT($A12,4),Setor!$A:$E,5,0)),"") -> Produção de Eventos e Shows | F12: =IFERROR(__xludf.DUMMYFUNCTION("IFERROR((GOOGLEFINANCE(A12)),"""")"),58.0) -> 58 | G12: =IFERROR(__xludf.DUMMYFUNCTION("IFERROR((sparkline(GOOGLEFINANCE($A12,""price"",TODAY()-30,TODAY(),""DAILY""),{""charttype"",""line"";""linewidth"",1;""color"",""#5f88cc""})),"""")"),"") | H12: =IFERROR(__xludf.DUMMYFUNCTION("IFERROR((((GOOGLEFINANCE(A12))-(INDEX(GoogleFinance(A12,""PRICE"",$AQ$1),2,2)))/(INDEX(GoogleFinance(A12,""PRICE"",$AQ$1),2,2))),"""")"),"") | I12: =IFERROR(__xludf.DUMMYFUNCTION("IFERROR((GOOGLEFINANCE($A12,""high52"")),"""")"),58.0) -> 58 | J12: =IFERROR(__xludf.DUMMYFUNCTION("IFERROR((sparkline(GOOGLEFINANCE($A12,""price"",TODAY()-365,TODAY(),""DAILY""),{""charttype"",""line"";""linewidth"",1;""color"",""#5f88cc""})),"""")"),"") | K12: =IFERROR(__xludf.DUMMYFUNCTION("IFERROR((((GOOGLEFINANCE(A12))-(INDEX(GoogleFinance(A12,""PRICE"",$AP$1),2,2)))/(INDEX(GoogleFinance(A12,""PRICE"",$AP$1),2,2))),"""")"),"") | L12: =IFERROR(((F12-I12)/I12),0) -> 0 | M12: =IFERROR((VLOOKUP($A12,'Dados StatusInvest'!$A:$AZ,COLUMN(M12)-$A$5,0)*VLOOKUP($A12,'Dados StatusInvest'!$A:$AZ,2,0)/$F12/100),0) -> 0.1104 | N12: =IFERROR((VLOOKUP($A12,'Dados StatusInvest'!$A:$AZ,COLUMN(N12)-$A$5,0)/VLOOKUP($A12,'Dados StatusInvest'!$A:$AZ,2,0)*$F12),"") -> 12.25 | O12: =IFERROR((VLOOKUP($A12,'Dados StatusInvest'!$A:$AZ,COLUMN(O12)-$A$5,0)/VLOOKUP($A12,'Dados StatusInvest'!$A:$AZ,2,0)*$F12),0) -> 6.67 | P12: =IFERROR((VLOOKUP($A12,'Dados StatusInvest'!$A:$AZ,COLUMN(P12)-$A$5,0)/VLOOKUP($A12,'Dados StatusInvest'!$A:$AZ,2,0)*$F12),0) -> 1.9 | Q12: =IFERROR((VLOOKUP($A12,'Dados StatusInvest'!$A:$AZ,COLUMN(Q12)-$A$5,0)/100),0) -> -0.0103 | R12: =VLOOKUP($A12,'Dados StatusInvest'!$A:$AZ,COLUMN(R12)-$A$5,0) -> -0.3 | S12: =IFERROR((VLOOKUP($A12,'Dados StatusInvest'!$A:$AZ,COLUMN(S12)-$A$5,0)),0) -> 0.74 | T12: =IFERROR((VLOOKUP($A12,'Dados StatusInvest'!$A:$AZ,COLUMN(T12)-$A$5,0)/VLOOKUP($A12,'Dados StatusInvest'!$A:$AZ,2,0)*$F12),0) -> 3.33 | U12: =IFERROR((VLOOKUP($A12,'Dados StatusInvest'!$A:$AZ,COLUMN(U12)-$A$5,0)-VLOOKUP($A12,'Dados StatusInvest'!$A:$AZ,COLUMN(U12)-$A$5-1,0)+T12),0) -> -1.45 | V12: =IFERROR((VLOOKUP($A12,'Dados StatusInvest'!$A:$AZ,COLUMN(V12)-$A$5,0)),0) -> 2.46 | W12: =IFERROR((VLOOKUP($A12,'Dados StatusInvest'!$A:$AZ,COLUMN(W12)-$A$5,0)),0) -> 32.19 | X12: =IFERROR((VLOOKUP($A12,'Dados StatusInvest'!$A:$AZ,COLUMN(X12)-$A$5,0)/VLOOKUP($A12,'Dados StatusInvest'!$A:$AZ,2,0)*$F12),0) -> 13.95 | Y12: =IFERROR((VLOOKUP($A12,'Dados StatusInvest'!$A:$AZ,COLUMN(Y12)-$A$5,0)/VLOOKUP($A12,'Dados StatusInvest'!$A:$AZ,2,0)*$F12),0) -> 27.08 | Z12: =IFERROR((VLOOKUP($A12,'Dados StatusInvest'!$A:$AZ,COLUMN(Z12)-$A$5,0)),0) -> 0.43 | AA12: =IFERROR((VLOOKUP($A12,'Dados StatusInvest'!$A:$AZ,COLUMN(AA12)-$A$5,0)),0) -> 0.57 | AB12: =IFERROR((VLOOKUP($A12,'Dados StatusInvest'!$A:$AZ,COLUMN(AB12)-$A$5,0)),0) -> 1.14 | AC12: =IFERROR((VLOOKUP($A12,'Dados StatusInvest'!$A:$AZ,COLUMN(AC12)-$A$5,0)),0) -> 44.62 | AD12: =IFERROR((VLOOKUP($A12,'Dados StatusInvest'!$A:$AZ,COLUMN(AD12)-$A$5,0)),0) -> 0 | AE12: =IFERROR((VLOOKUP($A12,'Dados StatusInvest'!$A:$AZ,COLUMN(AE12)-$A$5,0)),0) -> 0 | AF12: =IFERROR((VLOOKUP($A12,'Dados StatusInvest'!$A:$AZ,COLUMN(AF12)-$A$5,0)),0) -> 30 | AG12: =IFERROR((VLOOKUP($A12,'Dados StatusInvest'!$A:$AZ,COLUMN(AG12)-$A$5,0)),0) -> 9.66 | ... AJ12: =IFERROR((VLOOKUP($A12,'Dados StatusInvest'!$A:$AZ,COLUMN(AJ12)-$A$5,0)),0) | AK12: =IFERROR(__xludf.DUMMYFUNCTION("IFERROR(GOOGLEFINANCE($A12,""high""),"""")"),"") | AL12: =IFERROR(__xludf.DUMMYFUNCTION("IFERROR(GOOGLEFINANCE($A12,""low""),"""")"),"") | AM12: =IFERROR(((AK12-AL12)/AL12),0) -> 0 | AN12: =IFERROR(__xludf.DUMMYFUNCTION("IFERROR((GOOGLEFINANCE($A12,""volume"")),0)"),0.0) -> 0 | AO12: =IFERROR(__xludf.DUMMYFUNCTION("IFERROR((GOOGLEFINANCE($A12,""closeyest"")),"""")"),58.0) -> 58 | AP12: =IFERROR(__xludf.DUMMYFUNCTION("IFERROR((GOOGLEFINANCE($A12,""shares"")),"""")"),45022.0) -> 45022
A13: ='Dados StatusInvest'!A8:A627 -> AHEB6 | B13: =IFERROR(__xludf.DUMMYFUNCTION("IFERROR((GOOGLEFINANCE(A13,""name"")),"""")"),"Sao Paulo Turismo Class Pref Shs Class B") -> Sao Paulo Turismo Class Pref Shs Class B | C13: =IFERROR((VLOOKUP(LEFT($A13,4),Setor!$A:$E,3,0)),"") -> Consumo Cíclico | D13: =IFERROR((VLOOKUP(LEFT($A13,4),Setor!$A:$E,4,0)),"") -> Viagens e Lazer | E13: =IFERROR((VLOOKUP(LEFT($A13,4),Setor!$A:$E,5,0)),"") -> Produção de Eventos e Shows | F13: =IFERROR(__xludf.DUMMYFUNCTION("IFERROR((GOOGLEFINANCE(A13)),"""")"),55.0) -> 55 | G13: =IFERROR(__xludf.DUMMYFUNCTION("IFERROR((sparkline(GOOGLEFINANCE($A13,""price"",TODAY()-30,TODAY(),""DAILY""),{""charttype"",""line"";""linewidth"",1;""color"",""#5f88cc""})),"""")"),"") | H13: =IFERROR(__xludf.DUMMYFUNCTION("IFERROR((((GOOGLEFINANCE(A13))-(INDEX(GoogleFinance(A13,""PRICE"",$AQ$1),2,2)))/(INDEX(GoogleFinance(A13,""PRICE"",$AQ$1),2,2))),"""")"),"") | I13: =IFERROR(__xludf.DUMMYFUNCTION("IFERROR((GOOGLEFINANCE($A13,""high52"")),"""")"),55.0) -> 55 | J13: =IFERROR(__xludf.DUMMYFUNCTION("IFERROR((sparkline(GOOGLEFINANCE($A13,""price"",TODAY()-365,TODAY(),""DAILY""),{""charttype"",""line"";""linewidth"",1;""color"",""#5f88cc""})),"""")"),"") | K13: =IFERROR(__xludf.DUMMYFUNCTION("IFERROR((((GOOGLEFINANCE(A13))-(INDEX(GoogleFinance(A13,""PRICE"",$AP$1),2,2)))/(INDEX(GoogleFinance(A13,""PRICE"",$AP$1),2,2))),"""")"),"") | L13: =IFERROR(((F13-I13)/I13),0) -> 0 | M13: =IFERROR((VLOOKUP($A13,'Dados StatusInvest'!$A:$AZ,COLUMN(M13)-$A$5,0)*VLOOKUP($A13,'Dados StatusInvest'!$A:$AZ,2,0)/$F13/100),0) -> 0.1104 | N13: =IFERROR((VLOOKUP($A13,'Dados StatusInvest'!$A:$AZ,COLUMN(N13)-$A$5,0)/VLOOKUP($A13,'Dados StatusInvest'!$A:$AZ,2,0)*$F13),"") -> 12.25 | O13: =IFERROR((VLOOKUP($A13,'Dados StatusInvest'!$A:$AZ,COLUMN(O13)-$A$5,0)/VLOOKUP($A13,'Dados StatusInvest'!$A:$AZ,2,0)*$F13),0) -> 6.32 | P13: =IFERROR((VLOOKUP($A13,'Dados StatusInvest'!$A:$AZ,COLUMN(P13)-$A$5,0)/VLOOKUP($A13,'Dados StatusInvest'!$A:$AZ,2,0)*$F13),0) -> 1.9 | Q13: =IFERROR((VLOOKUP($A13,'Dados StatusInvest'!$A:$AZ,COLUMN(Q13)-$A$5,0)/100),0) -> -0.0103 | R13: =VLOOKUP($A13,'Dados StatusInvest'!$A:$AZ,COLUMN(R13)-$A$5,0) -> -0.3 | S13: =IFERROR((VLOOKUP($A13,'Dados StatusInvest'!$A:$AZ,COLUMN(S13)-$A$5,0)),0) -> 0.7 | T13: =IFERROR((VLOOKUP($A13,'Dados StatusInvest'!$A:$AZ,COLUMN(T13)-$A$5,0)/VLOOKUP($A13,'Dados StatusInvest'!$A:$AZ,2,0)*$F13),0) -> 3.15 | U13: =IFERROR((VLOOKUP($A13,'Dados StatusInvest'!$A:$AZ,COLUMN(U13)-$A$5,0)-VLOOKUP($A13,'Dados StatusInvest'!$A:$AZ,COLUMN(U13)-$A$5-1,0)+T13),0) -> -1.38 | V13: =IFERROR((VLOOKUP($A13,'Dados StatusInvest'!$A:$AZ,COLUMN(V13)-$A$5,0)),0) -> 2.46 | W13: =IFERROR((VLOOKUP($A13,'Dados StatusInvest'!$A:$AZ,COLUMN(W13)-$A$5,0)),0) -> 32.19 | X13: =IFERROR((VLOOKUP($A13,'Dados StatusInvest'!$A:$AZ,COLUMN(X13)-$A$5,0)/VLOOKUP($A13,'Dados StatusInvest'!$A:$AZ,2,0)*$F13),0) -> 13.95 | Y13: =IFERROR((VLOOKUP($A13,'Dados StatusInvest'!$A:$AZ,COLUMN(Y13)-$A$5,0)/VLOOKUP($A13,'Dados StatusInvest'!$A:$AZ,2,0)*$F13),0) -> 27.08 | Z13: =IFERROR((VLOOKUP($A13,'Dados StatusInvest'!$A:$AZ,COLUMN(Z13)-$A$5,0)),0) -> 0.43 | AA13: =IFERROR((VLOOKUP($A13,'Dados StatusInvest'!$A:$AZ,COLUMN(AA13)-$A$5,0)),0) -> 0.57 | AB13: =IFERROR((VLOOKUP($A13,'Dados StatusInvest'!$A:$AZ,COLUMN(AB13)-$A$5,0)),0) -> 1.14 | AC13: =IFERROR((VLOOKUP($A13,'Dados StatusInvest'!$A:$AZ,COLUMN(AC13)-$A$5,0)),0) -> 44.62 | AD13: =IFERROR((VLOOKUP($A13,'Dados StatusInvest'!$A:$AZ,COLUMN(AD13)-$A$5,0)),0) -> 0 | AE13: =IFERROR((VLOOKUP($A13,'Dados StatusInvest'!$A:$AZ,COLUMN(AE13)-$A$5,0)),0) -> 5500 | AF13: =IFERROR((VLOOKUP($A13,'Dados StatusInvest'!$A:$AZ,COLUMN(AF13)-$A$5,0)),0) -> 30 | AG13: =IFERROR((VLOOKUP($A13,'Dados StatusInvest'!$A:$AZ,COLUMN(AG13)-$A$5,0)),0) -> 9.66 | ... AJ13: =IFERROR((VLOOKUP($A13,'Dados StatusInvest'!$A:$AZ,COLUMN(AJ13)-$A$5,0)),0) | AK13: =IFERROR(__xludf.DUMMYFUNCTION("IFERROR(GOOGLEFINANCE($A13,""high""),"""")"),"") | AL13: =IFERROR(__xludf.DUMMYFUNCTION("IFERROR(GOOGLEFINANCE($A13,""low""),"""")"),"") | AM13: =IFERROR(((AK13-AL13)/AL13),0) -> 0 | AN13: =IFERROR(__xludf.DUMMYFUNCTION("IFERROR((GOOGLEFINANCE($A13,""volume"")),0)"),0.0) -> 0 | AO13: =IFERROR(__xludf.DUMMYFUNCTION("IFERROR((GOOGLEFINANCE($A13,""closeyest"")),"""")"),55.0) -> 55 | AP13: =IFERROR(__xludf.DUMMYFUNCTION("IFERROR((GOOGLEFINANCE($A13,""shares"")),"""")"),90995.0) -> 90995
A14: ='Dados StatusInvest'!A9:A628 -> ALLD3 | B14: =IFERROR(__xludf.DUMMYFUNCTION("IFERROR((GOOGLEFINANCE(A14,""name"")),"""")"),"Allied Tecnologia SA") -> Allied Tecnologia SA | C14: =IFERROR((VLOOKUP(LEFT($A14,4),Setor!$A:$E,3,0)),"") | D14: =IFERROR((VLOOKUP(LEFT($A14,4),Setor!$A:$E,4,0)),"") | E14: =IFERROR((VLOOKUP(LEFT($A14,4),Setor!$A:$E,5,0)),"") | F14: =IFERROR(__xludf.DUMMYFUNCTION("IFERROR((GOOGLEFINANCE(A14)),"""")"),7.48) -> 7.48 | G14: =IFERROR(__xludf.DUMMYFUNCTION("IFERROR((sparkline(GOOGLEFINANCE($A14,""price"",TODAY()-30,TODAY(),""DAILY""),{""charttype"",""line"";""linewidth"",1;""color"",""#5f88cc""})),"""")"),"") | H14: =IFERROR(__xludf.DUMMYFUNCTION("IFERROR((((GOOGLEFINANCE(A14))-(INDEX(GoogleFinance(A14,""PRICE"",$AQ$1),2,2)))/(INDEX(GoogleFinance(A14,""PRICE"",$AQ$1),2,2))),"""")"),-0.11269276393831545) -> -0.11269276 | I14: =IFERROR(__xludf.DUMMYFUNCTION("IFERROR((GOOGLEFINANCE($A14,""high52"")),"""")"),8.23) -> 8.23 | J14: =IFERROR(__xludf.DUMMYFUNCTION("IFERROR((sparkline(GOOGLEFINANCE($A14,""price"",TODAY()-365,TODAY(),""DAILY""),{""charttype"",""line"";""linewidth"",1;""color"",""#5f88cc""})),"""")"),"") | K14: =IFERROR(__xludf.DUMMYFUNCTION("IFERROR((((GOOGLEFINANCE(A14))-(INDEX(GoogleFinance(A14,""PRICE"",$AP$1),2,2)))/(INDEX(GoogleFinance(A14,""PRICE"",$AP$1),2,2))),"""")"),0.056497175141242986) -> 0.056497175 | L14: =IFERROR(((F14-I14)/I14),0) -> -0.091130012 | M14: =IFERROR((VLOOKUP($A14,'Dados StatusInvest'!$A:$AZ,COLUMN(M14)-$A$5,0)*VLOOKUP($A14,'Dados StatusInvest'!$A:$AZ,2,0)/$F14/100),0) -> 0.093396791 | N14: =IFERROR((VLOOKUP($A14,'Dados StatusInvest'!$A:$AZ,COLUMN(N14)-$A$5,0)/VLOOKUP($A14,'Dados StatusInvest'!$A:$AZ,2,0)*$F14),"") -> 6.5151596 | O14: =IFERROR((VLOOKUP($A14,'Dados StatusInvest'!$A:$AZ,COLUMN(O14)-$A$5,0)/VLOOKUP($A14,'Dados StatusInvest'!$A:$AZ,2,0)*$F14),0) -> 1.4323404 | P14: =IFERROR((VLOOKUP($A14,'Dados StatusInvest'!$A:$AZ,COLUMN(P14)-$A$5,0)/VLOOKUP($A14,'Dados StatusInvest'!$A:$AZ,2,0)*$F14),0) -> 1.1140426 | Q14: =IFERROR((VLOOKUP($A14,'Dados StatusInvest'!$A:$AZ,COLUMN(Q14)-$A$5,0)/100),0) -> -0.0032 | R14: =VLOOKUP($A14,'Dados StatusInvest'!$A:$AZ,COLUMN(R14)-$A$5,0) -> -0.09 | S14: =IFERROR((VLOOKUP($A14,'Dados StatusInvest'!$A:$AZ,COLUMN(S14)-$A$5,0)),0) -> 0.13 | T14: =IFERROR((VLOOKUP($A14,'Dados StatusInvest'!$A:$AZ,COLUMN(T14)-$A$5,0)/VLOOKUP($A14,'Dados StatusInvest'!$A:$AZ,2,0)*$F14),0) -> 0.56696809 | U14: =IFERROR((VLOOKUP($A14,'Dados StatusInvest'!$A:$AZ,COLUMN(U14)-$A$5,0)-VLOOKUP($A14,'Dados StatusInvest'!$A:$AZ,COLUMN(U14)-$A$5-1,0)+T14),0) -> -0.74303191 | V14: =IFERROR((VLOOKUP($A14,'Dados StatusInvest'!$A:$AZ,COLUMN(V14)-$A$5,0)),0) -> 1.81 | W14: =IFERROR((VLOOKUP($A14,'Dados StatusInvest'!$A:$AZ,COLUMN(W14)-$A$5,0)),0) -> 20.88 | X14: =IFERROR((VLOOKUP($A14,'Dados StatusInvest'!$A:$AZ,COLUMN(X14)-$A$5,0)/VLOOKUP($A14,'Dados StatusInvest'!$A:$AZ,2,0)*$F14),0) -> 9.3102128 | Y14: =IFERROR((VLOOKUP($A14,'Dados StatusInvest'!$A:$AZ,COLUMN(Y14)-$A$5,0)/VLOOKUP($A14,'Dados StatusInvest'!$A:$AZ,2,0)*$F14),0) -> 17.088617 | Z14: =IFERROR((VLOOKUP($A14,'Dados StatusInvest'!$A:$AZ,COLUMN(Z14)-$A$5,0)),0) -> 0.45 | AA14: =IFERROR((VLOOKUP($A14,'Dados StatusInvest'!$A:$AZ,COLUMN(AA14)-$A$5,0)),0) -> 0.55 | AB14: =IFERROR((VLOOKUP($A14,'Dados StatusInvest'!$A:$AZ,COLUMN(AB14)-$A$5,0)),0) -> 1.43 | AC14: =IFERROR((VLOOKUP($A14,'Dados StatusInvest'!$A:$AZ,COLUMN(AC14)-$A$5,0)),0) -> 8.27 | AD14: =IFERROR((VLOOKUP($A14,'Dados StatusInvest'!$A:$AZ,COLUMN(AD14)-$A$5,0)),0) -> 28.55 | AE14: =IFERROR((VLOOKUP($A14,'Dados StatusInvest'!$A:$AZ,COLUMN(AE14)-$A$5,0)),0) -> 5234240 | AF14: =IFERROR((VLOOKUP($A14,'Dados StatusInvest'!$A:$AZ,COLUMN(AF14)-$A$5,0)),0) -> 17.68 | AG14: =IFERROR((VLOOKUP($A14,'Dados StatusInvest'!$A:$AZ,COLUMN(AG14)-$A$5,0)),0) -> 3.69 | ... AJ14: =IFERROR((VLOOKUP($A14,'Dados StatusInvest'!$A:$AZ,COLUMN(AJ14)-$A$5,0)),0) | AK14: =IFERROR(__xludf.DUMMYFUNCTION("IFERROR(GOOGLEFINANCE($A14,""high""),"""")"),7.51) -> 7.51 | AL14: =IFERROR(__xludf.DUMMYFUNCTION("IFERROR(GOOGLEFINANCE($A14,""low""),"""")"),7.45) -> 7.45 | AM14: =IFERROR(((AK14-AL14)/AL14),0) -> 0.0080536913 | AN14: =IFERROR(__xludf.DUMMYFUNCTION("IFERROR((GOOGLEFINANCE($A14,""volume"")),0)"),19900.0) -> 19900 | AO14: =IFERROR(__xludf.DUMMYFUNCTION("IFERROR((GOOGLEFINANCE($A14,""closeyest"")),"""")"),7.52) -> 7.52 | AP14: =IFERROR(__xludf.DUMMYFUNCTION("IFERROR((GOOGLEFINANCE($A14,""shares"")),"""")"),9.5690787E7) -> 95690787
A15: ='Dados StatusInvest'!A10:A629 -> ALOS3 | B15: =IFERROR(__xludf.DUMMYFUNCTION("IFERROR((GOOGLEFINANCE(A15,""name"")),"""")"),"Allos SA") -> Allos SA | C15: =IFERROR((VLOOKUP(LEFT($A15,4),Setor!$A:$E,3,0)),"") -> Outros | D15: =IFERROR((VLOOKUP(LEFT($A15,4),Setor!$A:$E,4,0)),"") -> Comércio | E15: =IFERROR((VLOOKUP(LEFT($A15,4),Setor!$A:$E,5,0)),"") -> Comércio | F15: =IFERROR(__xludf.DUMMYFUNCTION("IFERROR((GOOGLEFINANCE(A15)),"""")"),31.13) -> 31.13 | G15: =IFERROR(__xludf.DUMMYFUNCTION("IFERROR((sparkline(GOOGLEFINANCE($A15,""price"",TODAY()-30,TODAY(),""DAILY""),{""charttype"",""line"";""linewidth"",1;""color"",""#5f88cc""})),"""")"),"") | H15: =IFERROR(__xludf.DUMMYFUNCTION("IFERROR((((GOOGLEFINANCE(A15))-(INDEX(GoogleFinance(A15,""PRICE"",$AQ$1),2,2)))/(INDEX(GoogleFinance(A15,""PRICE"",$AQ$1),2,2))),"""")"),0.06829100892244332) -> 0.068291009 | I15: =IFERROR(__xludf.DUMMYFUNCTION("IFERROR((GOOGLEFINANCE($A15,""high52"")),"""")"),31.66) -> 31.66 | J15: =IFERROR(__xludf.DUMMYFUNCTION("IFERROR((sparkline(GOOGLEFINANCE($A15,""price"",TODAY()-365,TODAY(),""DAILY""),{""charttype"",""line"";""linewidth"",1;""color"",""#5f88cc""})),"""")"),"") | K15: =IFERROR(__xludf.DUMMYFUNCTION("IFERROR((((GOOGLEFINANCE(A15))-(INDEX(GoogleFinance(A15,""PRICE"",$AP$1),2,2)))/(INDEX(GoogleFinance(A15,""PRICE"",$AP$1),2,2))),"""")"),0.6230448383733055) -> 0.62304484 | L15: =IFERROR(((F15-I15)/I15),0) -> -0.016740366 | M15: =IFERROR((VLOOKUP($A15,'Dados StatusInvest'!$A:$AZ,COLUMN(M15)-$A$5,0)*VLOOKUP($A15,'Dados StatusInvest'!$A:$AZ,2,0)/$F15/100),0) -> 0.57171539 | N15: =IFERROR((VLOOKUP($A15,'Dados StatusInvest'!$A:$AZ,COLUMN(N15)-$A$5,0)/VLOOKUP($A15,'Dados StatusInvest'!$A:$AZ,2,0)*$F15),"") -> 26.171239 | O15: =IFERROR((VLOOKUP($A15,'Dados StatusInvest'!$A:$AZ,COLUMN(O15)-$A$5,0)/VLOOKUP($A15,'Dados StatusInvest'!$A:$AZ,2,0)*$F15),0) -> 9.8880057 | P15: =IFERROR((VLOOKUP($A15,'Dados StatusInvest'!$A:$AZ,COLUMN(P15)-$A$5,0)/VLOOKUP($A15,'Dados StatusInvest'!$A:$AZ,2,0)*$F15),0) -> 8.0875032 | Q15: =IFERROR((VLOOKUP($A15,'Dados StatusInvest'!$A:$AZ,COLUMN(Q15)-$A$5,0)/100),0) -> -0.0183 | R15: =VLOOKUP($A15,'Dados StatusInvest'!$A:$AZ,COLUMN(R15)-$A$5,0) -> -0.22 | S15: =IFERROR((VLOOKUP($A15,'Dados StatusInvest'!$A:$AZ,COLUMN(S15)-$A$5,0)),0) -> 5.65 | T15: =IFERROR((VLOOKUP($A15,'Dados StatusInvest'!$A:$AZ,COLUMN(T15)-$A$5,0)/VLOOKUP($A15,'Dados StatusInvest'!$A:$AZ,2,0)*$F15),0) -> 6.1492573 | U15: =IFERROR((VLOOKUP($A15,'Dados StatusInvest'!$A:$AZ,COLUMN(U15)-$A$5,0)-VLOOKUP($A15,'Dados StatusInvest'!$A:$AZ,COLUMN(U15)-$A$5-1,0)+T15),0) -> -0.81074273 | V15: =IFERROR((VLOOKUP($A15,'Dados StatusInvest'!$A:$AZ,COLUMN(V15)-$A$5,0)),0) -> 3.06 | W15: =IFERROR((VLOOKUP($A15,'Dados StatusInvest'!$A:$AZ,COLUMN(W15)-$A$5,0)),0) -> 5.59 | X15: =IFERROR((VLOOKUP($A15,'Dados StatusInvest'!$A:$AZ,COLUMN(X15)-$A$5,0)/VLOOKUP($A15,'Dados StatusInvest'!$A:$AZ,2,0)*$F15),0) -> 2.8040613 | Y15: =IFERROR((VLOOKUP($A15,'Dados StatusInvest'!$A:$AZ,COLUMN(Y15)-$A$5,0)/VLOOKUP($A15,'Dados StatusInvest'!$A:$AZ,2,0)*$F15),0) -> 10.478334 | Z15: =IFERROR((VLOOKUP($A15,'Dados StatusInvest'!$A:$AZ,COLUMN(Z15)-$A$5,0)),0) -> 0.51 | AA15: =IFERROR((VLOOKUP($A15,'Dados StatusInvest'!$A:$AZ,COLUMN(AA15)-$A$5,0)),0) -> 0.46 | AB15: =IFERROR((VLOOKUP($A15,'Dados StatusInvest'!$A:$AZ,COLUMN(AB15)-$A$5,0)),0) -> 0.11 | AC15: =IFERROR((VLOOKUP($A15,'Dados StatusInvest'!$A:$AZ,COLUMN(AC15)-$A$5,0)),0) -> 29.82 | AD15: =IFERROR((VLOOKUP($A15,'Dados StatusInvest'!$A:$AZ,COLUMN(AD15)-$A$5,0)),0) -> 102.53 | AE15: =IFERROR((VLOOKUP($A15,'Dados StatusInvest'!$A:$AZ,COLUMN(AE15)-$A$5,0)),0) -> 178000000 | AF15: =IFERROR((VLOOKUP($A15,'Dados StatusInvest'!$A:$AZ,COLUMN(AF15)-$A$5,0)),0) -> 26.62 | AG15: =IFERROR((VLOOKUP($A15,'Dados StatusInvest'!$A:$AZ,COLUMN(AG15)-$A$5,0)),0) -> 1.49 | ... AJ15: =IFERROR((VLOOKUP($A15,'Dados StatusInvest'!$A:$AZ,COLUMN(AJ15)-$A$5,0)),0) | AK15: =IFERROR(__xludf.DUMMYFUNCTION("IFERROR(GOOGLEFINANCE($A15,""high""),"""")"),31.22) -> 31.22 | AL15: =IFERROR(__xludf.DUMMYFUNCTION("IFERROR(GOOGLEFINANCE($A15,""low""),"""")"),30.93) -> 30.93 | AM15: =IFERROR(((AK15-AL15)/AL15),0) -> 0.0093760103 | AN15: =IFERROR(__xludf.DUMMYFUNCTION("IFERROR((GOOGLEFINANCE($A15,""volume"")),0)"),88400.0) -> 88400 | AO15: =IFERROR(__xludf.DUMMYFUNCTION("IFERROR((GOOGLEFINANCE($A15,""closeyest"")),"""")"),31.35) -> 31.35 | AP15: =IFERROR(__xludf.DUMMYFUNCTION("IFERROR((GOOGLEFINANCE($A15,""shares"")),"""")"),5.04190947E8) -> 504190947
A16: ='Dados StatusInvest'!A11:A630 -> ALPA3 | B16: =IFERROR(__xludf.DUMMYFUNCTION("IFERROR((GOOGLEFINANCE(A16,""name"")),"""")"),"Alpargatas SA") -> Alpargatas SA | C16: =IFERROR((VLOOKUP(LEFT($A16,4),Setor!$A:$E,3,0)),"") -> Consumo Cíclico | D16: =IFERROR((VLOOKUP(LEFT($A16,4),Setor!$A:$E,4,0)),"") -> Tecidos, Vestuário e Calçados | E16: =IFERROR((VLOOKUP(LEFT($A16,4),Setor!$A:$E,5,0)),"") -> Calçados | F16: =IFERROR(__xludf.DUMMYFUNCTION("IFERROR((GOOGLEFINANCE(A16)),"""")"),12.35) -> 12.35 | G16: =IFERROR(__xludf.DUMMYFUNCTION("IFERROR((sparkline(GOOGLEFINANCE($A16,""price"",TODAY()-30,TODAY(),""DAILY""),{""charttype"",""line"";""linewidth"",1;""color"",""#5f88cc""})),"""")"),"") | H16: =IFERROR(__xludf.DUMMYFUNCTION("IFERROR((((GOOGLEFINANCE(A16))-(INDEX(GoogleFinance(A16,""PRICE"",$AQ$1),2,2)))/(INDEX(GoogleFinance(A16,""PRICE"",$AQ$1),2,2))),"""")"),0.21915103652517262) -> 0.21915104 | I16: =IFERROR(__xludf.DUMMYFUNCTION("IFERROR((GOOGLEFINANCE($A16,""high52"")),"""")"),13.49) -> 13.49 | J16: =IFERROR(__xludf.DUMMYFUNCTION("IFERROR((sparkline(GOOGLEFINANCE($A16,""price"",TODAY()-365,TODAY(),""DAILY""),{""charttype"",""line"";""linewidth"",1;""color"",""#5f88cc""})),"""")"),"") | K16: =IFERROR(__xludf.DUMMYFUNCTION("IFERROR((((GOOGLEFINANCE(A16))-(INDEX(GoogleFinance(A16,""PRICE"",$AP$1),2,2)))/(INDEX(GoogleFinance(A16,""PRICE"",$AP$1),2,2))),"""")"),0.9236760124610591) -> 0.92367601 | L16: =IFERROR(((F16-I16)/I16),0) -> -0.084507042 | M16: =IFERROR((VLOOKUP($A16,'Dados StatusInvest'!$A:$AZ,COLUMN(M16)-$A$5,0)*VLOOKUP($A16,'Dados StatusInvest'!$A:$AZ,2,0)/$F16/100),0) -> 0.0878 | N16: =IFERROR((VLOOKUP($A16,'Dados StatusInvest'!$A:$AZ,COLUMN(N16)-$A$5,0)/VLOOKUP($A16,'Dados StatusInvest'!$A:$AZ,2,0)*$F16),"") -> 8.43 | O16: =IFERROR((VLOOKUP($A16,'Dados StatusInvest'!$A:$AZ,COLUMN(O16)-$A$5,0)/VLOOKUP($A16,'Dados StatusInvest'!$A:$AZ,2,0)*$F16),0) -> 21.67 | P16: =IFERROR((VLOOKUP($A16,'Dados StatusInvest'!$A:$AZ,COLUMN(P16)-$A$5,0)/VLOOKUP($A16,'Dados StatusInvest'!$A:$AZ,2,0)*$F16),0) -> 22.81 | Q16: =IFERROR((VLOOKUP($A16,'Dados StatusInvest'!$A:$AZ,COLUMN(Q16)-$A$5,0)/100),0) -> -0.0099 | R16: =VLOOKUP($A16,'Dados StatusInvest'!$A:$AZ,COLUMN(R16)-$A$5,0) -> -0.09 | S16: =IFERROR((VLOOKUP($A16,'Dados StatusInvest'!$A:$AZ,COLUMN(S16)-$A$5,0)),0) -> 1.9 | T16: =IFERROR((VLOOKUP($A16,'Dados StatusInvest'!$A:$AZ,COLUMN(T16)-$A$5,0)/VLOOKUP($A16,'Dados StatusInvest'!$A:$AZ,2,0)*$F16),0) -> 4.62 | U16: =IFERROR((VLOOKUP($A16,'Dados StatusInvest'!$A:$AZ,COLUMN(U16)-$A$5,0)-VLOOKUP($A16,'Dados StatusInvest'!$A:$AZ,COLUMN(U16)-$A$5-1,0)+T16),0) -> -2.72 | V16: =IFERROR((VLOOKUP($A16,'Dados StatusInvest'!$A:$AZ,COLUMN(V16)-$A$5,0)),0) -> 2.4 | W16: =IFERROR((VLOOKUP($A16,'Dados StatusInvest'!$A:$AZ,COLUMN(W16)-$A$5,0)),0) -> 8.69 | X16: =IFERROR((VLOOKUP($A16,'Dados StatusInvest'!$A:$AZ,COLUMN(X16)-$A$5,0)/VLOOKUP($A16,'Dados StatusInvest'!$A:$AZ,2,0)*$F16),0) -> 5.99 | Y16: =IFERROR((VLOOKUP($A16,'Dados StatusInvest'!$A:$AZ,COLUMN(Y16)-$A$5,0)/VLOOKUP($A16,'Dados StatusInvest'!$A:$AZ,2,0)*$F16),0) -> 7.82 | Z16: =IFERROR((VLOOKUP($A16,'Dados StatusInvest'!$A:$AZ,COLUMN(Z16)-$A$5,0)),0) -> 0.69 | AA16: =IFERROR((VLOOKUP($A16,'Dados StatusInvest'!$A:$AZ,COLUMN(AA16)-$A$5,0)),0) -> 0.31 | AB16: =IFERROR((VLOOKUP($A16,'Dados StatusInvest'!$A:$AZ,COLUMN(AB16)-$A$5,0)),0) -> 0.71 | AC16: =IFERROR((VLOOKUP($A16,'Dados StatusInvest'!$A:$AZ,COLUMN(AC16)-$A$5,0)),0) -> 2.05 | AD16: =IFERROR((VLOOKUP($A16,'Dados StatusInvest'!$A:$AZ,COLUMN(AD16)-$A$5,0)),0) -> 6.4 | AE16: =IFERROR((VLOOKUP($A16,'Dados StatusInvest'!$A:$AZ,COLUMN(AE16)-$A$5,0)),0) -> 270396 | AF16: =IFERROR((VLOOKUP($A16,'Dados StatusInvest'!$A:$AZ,COLUMN(AF16)-$A$5,0)),0) -> 6.3 | AG16: =IFERROR((VLOOKUP($A16,'Dados StatusInvest'!$A:$AZ,COLUMN(AG16)-$A$5,0)),0) -> 0.55 | ... AJ16: =IFERROR((VLOOKUP($A16,'Dados StatusInvest'!$A:$AZ,COLUMN(AJ16)-$A$5,0)),0) | AK16: =IFERROR(__xludf.DUMMYFUNCTION("IFERROR(GOOGLEFINANCE($A16,""high""),"""")"),12.35) -> 12.35 | AL16: =IFERROR(__xludf.DUMMYFUNCTION("IFERROR(GOOGLEFINANCE($A16,""low""),"""")"),12.35) -> 12.35 | AM16: =IFERROR(((AK16-AL16)/AL16),0) -> 0 | AN16: =IFERROR(__xludf.DUMMYFUNCTION("IFERROR((GOOGLEFINANCE($A16,""volume"")),0)"),200.0) -> 200 | AO16: =IFERROR(__xludf.DUMMYFUNCTION("IFERROR((GOOGLEFINANCE($A16,""closeyest"")),"""")"),12.35) -> 12.35 | AP16: =IFERROR(__xludf.DUMMYFUNCTION("IFERROR((GOOGLEFINANCE($A16,""shares"")),"""")"),3.39510689E8) -> 339510689
A17: ='Dados StatusInvest'!A12:A631 -> ALPA4 | B17: =IFERROR(__xludf.DUMMYFUNCTION("IFERROR((GOOGLEFINANCE(A17,""name"")),"""")"),"Alpargatas SA Preference Shares") -> Alpargatas SA Preference Shares | C17: =IFERROR((VLOOKUP(LEFT($A17,4),Setor!$A:$E,3,0)),"") -> Consumo Cíclico | D17: =IFERROR((VLOOKUP(LEFT($A17,4),Setor!$A:$E,4,0)),"") -> Tecidos, Vestuário e Calçados | E17: =IFERROR((VLOOKUP(LEFT($A17,4),Setor!$A:$E,5,0)),"") -> Calçados | F17: =IFERROR(__xludf.DUMMYFUNCTION("IFERROR((GOOGLEFINANCE(A17)),"""")"),14.51) -> 14.51 | G17: =IFERROR(__xludf.DUMMYFUNCTION("IFERROR((sparkline(GOOGLEFINANCE($A17,""price"",TODAY()-30,TODAY(),""DAILY""),{""charttype"",""line"";""linewidth"",1;""color"",""#5f88cc""})),"""")"),"") | H17: =IFERROR(__xludf.DUMMYFUNCTION("IFERROR((((GOOGLEFINANCE(A17))-(INDEX(GoogleFinance(A17,""PRICE"",$AQ$1),2,2)))/(INDEX(GoogleFinance(A17,""PRICE"",$AQ$1),2,2))),"""")"),0.12219644238205724) -> 0.12219644 | I17: =IFERROR(__xludf.DUMMYFUNCTION("IFERROR((GOOGLEFINANCE($A17,""high52"")),"""")"),16.22) -> 16.22 | J17: =IFERROR(__xludf.DUMMYFUNCTION("IFERROR((sparkline(GOOGLEFINANCE($A17,""price"",TODAY()-365,TODAY(),""DAILY""),{""charttype"",""line"";""linewidth"",1;""color"",""#5f88cc""})),"""")"),"") | K17: =IFERROR(__xludf.DUMMYFUNCTION("IFERROR((((GOOGLEFINANCE(A17))-(INDEX(GoogleFinance(A17,""PRICE"",$AP$1),2,2)))/(INDEX(GoogleFinance(A17,""PRICE"",$AP$1),2,2))),"""")"),1.1151603498542273) -> 1.1151604 | L17: =IFERROR(((F17-I17)/I17),0) -> -0.1054254 | M17: =IFERROR((VLOOKUP($A17,'Dados StatusInvest'!$A:$AZ,COLUMN(M17)-$A$5,0)*VLOOKUP($A17,'Dados StatusInvest'!$A:$AZ,2,0)/$F17/100),0) -> 0.08925224 | N17: =IFERROR((VLOOKUP($A17,'Dados StatusInvest'!$A:$AZ,COLUMN(N17)-$A$5,0)/VLOOKUP($A17,'Dados StatusInvest'!$A:$AZ,2,0)*$F17),"") -> 8.2928339 | O17: =IFERROR((VLOOKUP($A17,'Dados StatusInvest'!$A:$AZ,COLUMN(O17)-$A$5,0)/VLOOKUP($A17,'Dados StatusInvest'!$A:$AZ,2,0)*$F17),0) -> 25.468739 | P17: =IFERROR((VLOOKUP($A17,'Dados StatusInvest'!$A:$AZ,COLUMN(P17)-$A$5,0)/VLOOKUP($A17,'Dados StatusInvest'!$A:$AZ,2,0)*$F17),0) -> 22.438854 | Q17: =IFERROR((VLOOKUP($A17,'Dados StatusInvest'!$A:$AZ,COLUMN(Q17)-$A$5,0)/100),0) -> -0.0099 | R17: =VLOOKUP($A17,'Dados StatusInvest'!$A:$AZ,COLUMN(R17)-$A$5,0) -> -0.09 | S17: =IFERROR((VLOOKUP($A17,'Dados StatusInvest'!$A:$AZ,COLUMN(S17)-$A$5,0)),0) -> 2.27 | T17: =IFERROR((VLOOKUP($A17,'Dados StatusInvest'!$A:$AZ,COLUMN(T17)-$A$5,0)/VLOOKUP($A17,'Dados StatusInvest'!$A:$AZ,2,0)*$F17),0) -> 5.4301831 | U17: =IFERROR((VLOOKUP($A17,'Dados StatusInvest'!$A:$AZ,COLUMN(U17)-$A$5,0)-VLOOKUP($A17,'Dados StatusInvest'!$A:$AZ,COLUMN(U17)-$A$5-1,0)+T17),0) -> -3.3298169 | V17: =IFERROR((VLOOKUP($A17,'Dados StatusInvest'!$A:$AZ,COLUMN(V17)-$A$5,0)),0) -> 2.4 | W17: =IFERROR((VLOOKUP($A17,'Dados StatusInvest'!$A:$AZ,COLUMN(W17)-$A$5,0)),0) -> 8.69 | X17: =IFERROR((VLOOKUP($A17,'Dados StatusInvest'!$A:$AZ,COLUMN(X17)-$A$5,0)/VLOOKUP($A17,'Dados StatusInvest'!$A:$AZ,2,0)*$F17),0) -> 5.8925356 | Y17: =IFERROR((VLOOKUP($A17,'Dados StatusInvest'!$A:$AZ,COLUMN(Y17)-$A$5,0)/VLOOKUP($A17,'Dados StatusInvest'!$A:$AZ,2,0)*$F17),0) -> 7.6927593 | Z17: =IFERROR((VLOOKUP($A17,'Dados StatusInvest'!$A:$AZ,COLUMN(Z17)-$A$5,0)),0) -> 0.69 | AA17: =IFERROR((VLOOKUP($A17,'Dados StatusInvest'!$A:$AZ,COLUMN(AA17)-$A$5,0)),0) -> 0.31 | AB17: =IFERROR((VLOOKUP($A17,'Dados StatusInvest'!$A:$AZ,COLUMN(AB17)-$A$5,0)),0) -> 0.71 | AC17: =IFERROR((VLOOKUP($A17,'Dados StatusInvest'!$A:$AZ,COLUMN(AC17)-$A$5,0)),0) -> 2.05 | AD17: =IFERROR((VLOOKUP($A17,'Dados StatusInvest'!$A:$AZ,COLUMN(AD17)-$A$5,0)),0) -> 6.4 | AE17: =IFERROR((VLOOKUP($A17,'Dados StatusInvest'!$A:$AZ,COLUMN(AE17)-$A$5,0)),0) -> 36061574 | AF17: =IFERROR((VLOOKUP($A17,'Dados StatusInvest'!$A:$AZ,COLUMN(AF17)-$A$5,0)),0) -> 6.3 | AG17: =IFERROR((VLOOKUP($A17,'Dados StatusInvest'!$A:$AZ,COLUMN(AG17)-$A$5,0)),0) -> 0.55 | ... AJ17: =IFERROR((VLOOKUP($A17,'Dados StatusInvest'!$A:$AZ,COLUMN(AJ17)-$A$5,0)),0) | AK17: =IFERROR(__xludf.DUMMYFUNCTION("IFERROR(GOOGLEFINANCE($A17,""high""),"""")"),14.74) -> 14.74 | AL17: =IFERROR(__xludf.DUMMYFUNCTION("IFERROR(GOOGLEFINANCE($A17,""low""),"""")"),14.36) -> 14.36 | AM17: =IFERROR(((AK17-AL17)/AL17),0) -> 0.026462396 | AN17: =IFERROR(__xludf.DUMMYFUNCTION("IFERROR((GOOGLEFINANCE($A17,""volume"")),0)"),100300.0) -> 100300 | AO17: =IFERROR(__xludf.DUMMYFUNCTION("IFERROR((GOOGLEFINANCE($A17,""closeyest"")),"""")"),14.75) -> 14.75 | AP17: =IFERROR(__xludf.DUMMYFUNCTION("IFERROR((GOOGLEFINANCE($A17,""shares"")),"""")"),"")
A18: ='Dados StatusInvest'!A13:A632 -> ALPK3 | B18: =IFERROR(__xludf.DUMMYFUNCTION("IFERROR((GOOGLEFINANCE(A18,""name"")),"""")"),"Allpark Empreendimentos Prtcpcs Srvcs SA") -> Allpark Empreendimentos Prtcpcs Srvcs SA | C18: =IFERROR((VLOOKUP(LEFT($A18,4),Setor!$A:$E,3,0)),"") -> Bens Industriais | D18: =IFERROR((VLOOKUP(LEFT($A18,4),Setor!$A:$E,4,0)),"") -> Serviços Diversos | E18: =IFERROR((VLOOKUP(LEFT($A18,4),Setor!$A:$E,5,0)),"") -> Serviços Diversos | F18: =IFERROR(__xludf.DUMMYFUNCTION("IFERROR((GOOGLEFINANCE(A18)),"""")"),5.36) -> 5.36 | G18: =IFERROR(__xludf.DUMMYFUNCTION("IFERROR((sparkline(GOOGLEFINANCE($A18,""price"",TODAY()-30,TODAY(),""DAILY""),{""charttype"",""line"";""linewidth"",1;""color"",""#5f88cc""})),"""")"),"") | H18: =IFERROR(__xludf.DUMMYFUNCTION("IFERROR((((GOOGLEFINANCE(A18))-(INDEX(GoogleFinance(A18,""PRICE"",$AQ$1),2,2)))/(INDEX(GoogleFinance(A18,""PRICE"",$AQ$1),2,2))),"""")"),0.16268980477223427) -> 0.1626898 | I18: =IFERROR(__xludf.DUMMYFUNCTION("IFERROR((GOOGLEFINANCE($A18,""high52"")),"""")"),5.37) -> 5.37 | J18: =IFERROR(__xludf.DUMMYFUNCTION("IFERROR((sparkline(GOOGLEFINANCE($A18,""price"",TODAY()-365,TODAY(),""DAILY""),{""charttype"",""line"";""linewidth"",1;""color"",""#5f88cc""})),"""")"),"") | K18: =IFERROR(__xludf.DUMMYFUNCTION("IFERROR((((GOOGLEFINANCE(A18))-(INDEX(GoogleFinance(A18,""PRICE"",$AP$1),2,2)))/(INDEX(GoogleFinance(A18,""PRICE"",$AP$1),2,2))),"""")"),0.7866666666666667) -> 0.78666667 | L18: =IFERROR(((F18-I18)/I18),0) -> -0.0018621974 | M18: =IFERROR((VLOOKUP($A18,'Dados StatusInvest'!$A:$AZ,COLUMN(M18)-$A$5,0)*VLOOKUP($A18,'Dados StatusInvest'!$A:$AZ,2,0)/$F18/100),0) -> 0.13698731 | N18: =IFERROR((VLOOKUP($A18,'Dados StatusInvest'!$A:$AZ,COLUMN(N18)-$A$5,0)/VLOOKUP($A18,'Dados StatusInvest'!$A:$AZ,2,0)*$F18),"") -> 0.081058601 | O18: =IFERROR((VLOOKUP($A18,'Dados StatusInvest'!$A:$AZ,COLUMN(O18)-$A$5,0)/VLOOKUP($A18,'Dados StatusInvest'!$A:$AZ,2,0)*$F18),0) -> 4.7013989 | P18: =IFERROR((VLOOKUP($A18,'Dados StatusInvest'!$A:$AZ,COLUMN(P18)-$A$5,0)/VLOOKUP($A18,'Dados StatusInvest'!$A:$AZ,2,0)*$F18),0) -> 9.443327 | Q18: =IFERROR((VLOOKUP($A18,'Dados StatusInvest'!$A:$AZ,COLUMN(Q18)-$A$5,0)/100),0) -> 0.0469 | R18: =VLOOKUP($A18,'Dados StatusInvest'!$A:$AZ,COLUMN(R18)-$A$5,0) -> 3.29 | S18: =IFERROR((VLOOKUP($A18,'Dados StatusInvest'!$A:$AZ,COLUMN(S18)-$A$5,0)),0) -> 0.64 | T18: =IFERROR((VLOOKUP($A18,'Dados StatusInvest'!$A:$AZ,COLUMN(T18)-$A$5,0)/VLOOKUP($A18,'Dados StatusInvest'!$A:$AZ,2,0)*$F18),0) -> -9.9600756 | U18: =IFERROR((VLOOKUP($A18,'Dados StatusInvest'!$A:$AZ,COLUMN(U18)-$A$5,0)-VLOOKUP($A18,'Dados StatusInvest'!$A:$AZ,COLUMN(U18)-$A$5-1,0)+T18),0) -> -0.70007561 | V18: =IFERROR((VLOOKUP($A18,'Dados StatusInvest'!$A:$AZ,COLUMN(V18)-$A$5,0)),0) -> 0.82 | W18: =IFERROR((VLOOKUP($A18,'Dados StatusInvest'!$A:$AZ,COLUMN(W18)-$A$5,0)),0) -> 0.4 | X18: =IFERROR((VLOOKUP($A18,'Dados StatusInvest'!$A:$AZ,COLUMN(X18)-$A$5,0)/VLOOKUP($A18,'Dados StatusInvest'!$A:$AZ,2,0)*$F18),0) -> 0.050661626 | Y18: =IFERROR((VLOOKUP($A18,'Dados StatusInvest'!$A:$AZ,COLUMN(Y18)-$A$5,0)/VLOOKUP($A18,'Dados StatusInvest'!$A:$AZ,2,0)*$F18),0) -> 12.908582 | Z18: =IFERROR((VLOOKUP($A18,'Dados StatusInvest'!$A:$AZ,COLUMN(Z18)-$A$5,0)),0) -> 0.14 | AA18: =IFERROR((VLOOKUP($A18,'Dados StatusInvest'!$A:$AZ,COLUMN(AA18)-$A$5,0)),0) -> 0.86 | AB18: =IFERROR((VLOOKUP($A18,'Dados StatusInvest'!$A:$AZ,COLUMN(AB18)-$A$5,0)),0) -> 0.7 | AC18: =IFERROR((VLOOKUP($A18,'Dados StatusInvest'!$A:$AZ,COLUMN(AC18)-$A$5,0)),0) -> 7.96 | AD18: =IFERROR((VLOOKUP($A18,'Dados StatusInvest'!$A:$AZ,COLUMN(AD18)-$A$5,0)),0) -> 0 | AE18: =IFERROR((VLOOKUP($A18,'Dados StatusInvest'!$A:$AZ,COLUMN(AE18)-$A$5,0)),0) -> 997644.2 | AF18: =IFERROR((VLOOKUP($A18,'Dados StatusInvest'!$A:$AZ,COLUMN(AF18)-$A$5,0)),0) -> 1.63 | AG18: =IFERROR((VLOOKUP($A18,'Dados StatusInvest'!$A:$AZ,COLUMN(AG18)-$A$5,0)),0) -> 0.01 | ... AJ18: =IFERROR((VLOOKUP($A18,'Dados StatusInvest'!$A:$AZ,COLUMN(AJ18)-$A$5,0)),0) | AK18: =IFERROR(__xludf.DUMMYFUNCTION("IFERROR(GOOGLEFINANCE($A18,""high""),"""")"),5.36) -> 5.36 | AL18: =IFERROR(__xludf.DUMMYFUNCTION("IFERROR(GOOGLEFINANCE($A18,""low""),"""")"),5.24) -> 5.24 | AM18: =IFERROR(((AK18-AL18)/AL18),0) -> 0.022900763 | AN18: =IFERROR(__xludf.DUMMYFUNCTION("IFERROR((GOOGLEFINANCE($A18,""volume"")),0)"),61800.0) -> 61800 | AO18: =IFERROR(__xludf.DUMMYFUNCTION("IFERROR((GOOGLEFINANCE($A18,""closeyest"")),"""")"),5.29) -> 5.29 | AP18: =IFERROR(__xludf.DUMMYFUNCTION("IFERROR((GOOGLEFINANCE($A18,""shares"")),"""")"),2.19305733E8) -> 219305733
A19: ='Dados StatusInvest'!A14:A633 -> ALUP11 | B19: =IFERROR(__xludf.DUMMYFUNCTION("IFERROR((GOOGLEFINANCE(A19,""name"")),"""")"),"Alupar Investimento SA Unit") -> Alupar Investimento SA Unit | C19: =IFERROR((VLOOKUP(LEFT($A19,4),Setor!$A:$E,3,0)),"") -> Utilidade Pública | D19: =IFERROR((VLOOKUP(LEFT($A19,4),Setor!$A:$E,4,0)),"") -> Energia Elétrica | E19: =IFERROR((VLOOKUP(LEFT($A19,4),Setor!$A:$E,5,0)),"") -> Energia Elétrica | F19: =IFERROR(__xludf.DUMMYFUNCTION("IFERROR((GOOGLEFINANCE(A19)),"""")"),35.92) -> 35.92 | G19: =IFERROR(__xludf.DUMMYFUNCTION("IFERROR((sparkline(GOOGLEFINANCE($A19,""price"",TODAY()-30,TODAY(),""DAILY""),{""charttype"",""line"";""linewidth"",1;""color"",""#5f88cc""})),"""")"),"") | H19: =IFERROR(__xludf.DUMMYFUNCTION("IFERROR((((GOOGLEFINANCE(A19))-(INDEX(GoogleFinance(A19,""PRICE"",$AQ$1),2,2)))/(INDEX(GoogleFinance(A19,""PRICE"",$AQ$1),2,2))),"""")"),0.05958702064896765) -> 0.059587021 | I19: =IFERROR(__xludf.DUMMYFUNCTION("IFERROR((GOOGLEFINANCE($A19,""high52"")),"""")"),36.44) -> 36.44 | J19: =IFERROR(__xludf.DUMMYFUNCTION("IFERROR((sparkline(GOOGLEFINANCE($A19,""price"",TODAY()-365,TODAY(),""DAILY""),{""charttype"",""line"";""linewidth"",1;""color"",""#5f88cc""})),"""")"),"") | K19: =IFERROR(__xludf.DUMMYFUNCTION("IFERROR((((GOOGLEFINANCE(A19))-(INDEX(GoogleFinance(A19,""PRICE"",$AP$1),2,2)))/(INDEX(GoogleFinance(A19,""PRICE"",$AP$1),2,2))),"""")"),0.3171983865053173) -> 0.31719839 | L19: =IFERROR(((F19-I19)/I19),0) -> -0.014270033 | M19: =IFERROR((VLOOKUP($A19,'Dados StatusInvest'!$A:$AZ,COLUMN(M19)-$A$5,0)*VLOOKUP($A19,'Dados StatusInvest'!$A:$AZ,2,0)/$F19/100),0) -> 0.71898675 | N19: =IFERROR((VLOOKUP($A19,'Dados StatusInvest'!$A:$AZ,COLUMN(N19)-$A$5,0)/VLOOKUP($A19,'Dados StatusInvest'!$A:$AZ,2,0)*$F19),"") -> 26.574231 | O19: =IFERROR((VLOOKUP($A19,'Dados StatusInvest'!$A:$AZ,COLUMN(O19)-$A$5,0)/VLOOKUP($A19,'Dados StatusInvest'!$A:$AZ,2,0)*$F19),0) -> 3.7920532 | P19: =IFERROR((VLOOKUP($A19,'Dados StatusInvest'!$A:$AZ,COLUMN(P19)-$A$5,0)/VLOOKUP($A19,'Dados StatusInvest'!$A:$AZ,2,0)*$F19),0) -> 6.7480632 | Q19: =IFERROR((VLOOKUP($A19,'Dados StatusInvest'!$A:$AZ,COLUMN(Q19)-$A$5,0)/100),0) -> 0.0297 | R19: =VLOOKUP($A19,'Dados StatusInvest'!$A:$AZ,COLUMN(R19)-$A$5,0) -> 1.03 | S19: =IFERROR((VLOOKUP($A19,'Dados StatusInvest'!$A:$AZ,COLUMN(S19)-$A$5,0)),0) -> 2.73 | T19: =IFERROR((VLOOKUP($A19,'Dados StatusInvest'!$A:$AZ,COLUMN(T19)-$A$5,0)/VLOOKUP($A19,'Dados StatusInvest'!$A:$AZ,2,0)*$F19),0) -> 3.2048324 | U19: =IFERROR((VLOOKUP($A19,'Dados StatusInvest'!$A:$AZ,COLUMN(U19)-$A$5,0)-VLOOKUP($A19,'Dados StatusInvest'!$A:$AZ,COLUMN(U19)-$A$5-1,0)+T19),0) -> -0.48516764 | V19: =IFERROR((VLOOKUP($A19,'Dados StatusInvest'!$A:$AZ,COLUMN(V19)-$A$5,0)),0) -> 2.55 | W19: =IFERROR((VLOOKUP($A19,'Dados StatusInvest'!$A:$AZ,COLUMN(W19)-$A$5,0)),0) -> 12.93 | X19: =IFERROR((VLOOKUP($A19,'Dados StatusInvest'!$A:$AZ,COLUMN(X19)-$A$5,0)/VLOOKUP($A19,'Dados StatusInvest'!$A:$AZ,2,0)*$F19),0) -> 3.6825713 | Y19: =IFERROR((VLOOKUP($A19,'Dados StatusInvest'!$A:$AZ,COLUMN(Y19)-$A$5,0)/VLOOKUP($A19,'Dados StatusInvest'!$A:$AZ,2,0)*$F19),0) -> 10.75908 | Z19: =IFERROR((VLOOKUP($A19,'Dados StatusInvest'!$A:$AZ,COLUMN(Z19)-$A$5,0)),0) -> 0.29 | AA19: =IFERROR((VLOOKUP($A19,'Dados StatusInvest'!$A:$AZ,COLUMN(AA19)-$A$5,0)),0) -> 0.61 | AB19: =IFERROR((VLOOKUP($A19,'Dados StatusInvest'!$A:$AZ,COLUMN(AB19)-$A$5,0)),0) -> 0.14 | AC19: =IFERROR((VLOOKUP($A19,'Dados StatusInvest'!$A:$AZ,COLUMN(AC19)-$A$5,0)),0) -> -2.71 | AD19: =IFERROR((VLOOKUP($A19,'Dados StatusInvest'!$A:$AZ,COLUMN(AD19)-$A$5,0)),0) -> 5.5 | AE19: =IFERROR((VLOOKUP($A19,'Dados StatusInvest'!$A:$AZ,COLUMN(AE19)-$A$5,0)),0) -> 32185667 | AF19: =IFERROR((VLOOKUP($A19,'Dados StatusInvest'!$A:$AZ,COLUMN(AF19)-$A$5,0)),0) -> 27.3 | AG19: =IFERROR((VLOOKUP($A19,'Dados StatusInvest'!$A:$AZ,COLUMN(AG19)-$A$5,0)),0) -> 3.53 | ... AJ19: =IFERROR((VLOOKUP($A19,'Dados StatusInvest'!$A:$AZ,COLUMN(AJ19)-$A$5,0)),0) | AK19: =IFERROR(__xludf.DUMMYFUNCTION("IFERROR(GOOGLEFINANCE($A19,""high""),"""")"),36.11) -> 36.11 | AL19: =IFERROR(__xludf.DUMMYFUNCTION("IFERROR(GOOGLEFINANCE($A19,""low""),"""")"),35.81) -> 35.81 | AM19: =IFERROR(((AK19-AL19)/AL19),0) -> 0.0083775482 | AN19: =IFERROR(__xludf.DUMMYFUNCTION("IFERROR((GOOGLEFINANCE($A19,""volume"")),0)"),9900.0) -> 9900 | AO19: =IFERROR(__xludf.DUMMYFUNCTION("IFERROR((GOOGLEFINANCE($A19,""closeyest"")),"""")"),36.09) -> 36.09 | AP19: =IFERROR(__xludf.DUMMYFUNCTION("IFERROR((GOOGLEFINANCE($A19,""shares"")),"""")"),0.0) -> 0
A20: ='Dados StatusInvest'!A15:A634 -> ALUP3 | B20: =IFERROR(__xludf.DUMMYFUNCTION("IFERROR((GOOGLEFINANCE(A20,""name"")),"""")"),"Alupar Investimento SA") -> Alupar Investimento SA | C20: =IFERROR((VLOOKUP(LEFT($A20,4),Setor!$A:$E,3,0)),"") -> Utilidade Pública | D20: =IFERROR((VLOOKUP(LEFT($A20,4),Setor!$A:$E,4,0)),"") -> Energia Elétrica | E20: =IFERROR((VLOOKUP(LEFT($A20,4),Setor!$A:$E,5,0)),"") -> Energia Elétrica | F20: =IFERROR(__xludf.DUMMYFUNCTION("IFERROR((GOOGLEFINANCE(A20)),"""")"),13.28) -> 13.28 | G20: =IFERROR(__xludf.DUMMYFUNCTION("IFERROR((sparkline(GOOGLEFINANCE($A20,""price"",TODAY()-30,TODAY(),""DAILY""),{""charttype"",""line"";""linewidth"",1;""color"",""#5f88cc""})),"""")"),"") | H20: =IFERROR(__xludf.DUMMYFUNCTION("IFERROR((((GOOGLEFINANCE(A20))-(INDEX(GoogleFinance(A20,""PRICE"",$AQ$1),2,2)))/(INDEX(GoogleFinance(A20,""PRICE"",$AQ$1),2,2))),"""")"),0.09031198686371097) -> 0.090311987 | I20: =IFERROR(__xludf.DUMMYFUNCTION("IFERROR((GOOGLEFINANCE($A20,""high52"")),"""")"),13.8) -> 13.8 | J20: =IFERROR(__xludf.DUMMYFUNCTION("IFERROR((sparkline(GOOGLEFINANCE($A20,""price"",TODAY()-365,TODAY(),""DAILY""),{""charttype"",""line"";""linewidth"",1;""color"",""#5f88cc""})),"""")"),"") | K20: =IFERROR(__xludf.DUMMYFUNCTION("IFERROR((((GOOGLEFINANCE(A20))-(INDEX(GoogleFinance(A20,""PRICE"",$AP$1),2,2)))/(INDEX(GoogleFinance(A20,""PRICE"",$AP$1),2,2))),"""")"),0.41577825159914694) -> 0.41577825 | L20: =IFERROR(((F20-I20)/I20),0) -> -0.037681159 | M20: =IFERROR((VLOOKUP($A20,'Dados StatusInvest'!$A:$AZ,COLUMN(M20)-$A$5,0)*VLOOKUP($A20,'Dados StatusInvest'!$A:$AZ,2,0)/$F20/100),0) -> 0.70428404 | N20: =IFERROR((VLOOKUP($A20,'Dados StatusInvest'!$A:$AZ,COLUMN(N20)-$A$5,0)/VLOOKUP($A20,'Dados StatusInvest'!$A:$AZ,2,0)*$F20),"") -> 27.128998 | O20: =IFERROR((VLOOKUP($A20,'Dados StatusInvest'!$A:$AZ,COLUMN(O20)-$A$5,0)/VLOOKUP($A20,'Dados StatusInvest'!$A:$AZ,2,0)*$F20),0) -> 4.2065187 | P20: =IFERROR((VLOOKUP($A20,'Dados StatusInvest'!$A:$AZ,COLUMN(P20)-$A$5,0)/VLOOKUP($A20,'Dados StatusInvest'!$A:$AZ,2,0)*$F20),0) -> 6.8889365 | Q20: =IFERROR((VLOOKUP($A20,'Dados StatusInvest'!$A:$AZ,COLUMN(Q20)-$A$5,0)/100),0) -> 0.0297 | R20: =VLOOKUP($A20,'Dados StatusInvest'!$A:$AZ,COLUMN(R20)-$A$5,0) -> 1.03 | S20: =IFERROR((VLOOKUP($A20,'Dados StatusInvest'!$A:$AZ,COLUMN(S20)-$A$5,0)),0) -> 2.97 | T20: =IFERROR((VLOOKUP($A20,'Dados StatusInvest'!$A:$AZ,COLUMN(T20)-$A$5,0)/VLOOKUP($A20,'Dados StatusInvest'!$A:$AZ,2,0)*$F20),0) -> 3.5562357 | U20: =IFERROR((VLOOKUP($A20,'Dados StatusInvest'!$A:$AZ,COLUMN(U20)-$A$5,0)-VLOOKUP($A20,'Dados StatusInvest'!$A:$AZ,COLUMN(U20)-$A$5-1,0)+T20),0) -> -0.45376435 | V20: =IFERROR((VLOOKUP($A20,'Dados StatusInvest'!$A:$AZ,COLUMN(V20)-$A$5,0)),0) -> 2.55 | W20: =IFERROR((VLOOKUP($A20,'Dados StatusInvest'!$A:$AZ,COLUMN(W20)-$A$5,0)),0) -> 12.93 | X20: =IFERROR((VLOOKUP($A20,'Dados StatusInvest'!$A:$AZ,COLUMN(X20)-$A$5,0)/VLOOKUP($A20,'Dados StatusInvest'!$A:$AZ,2,0)*$F20),0) -> 3.7594491 | Y20: =IFERROR((VLOOKUP($A20,'Dados StatusInvest'!$A:$AZ,COLUMN(Y20)-$A$5,0)/VLOOKUP($A20,'Dados StatusInvest'!$A:$AZ,2,0)*$F20),0) -> 10.983688 | Z20: =IFERROR((VLOOKUP($A20,'Dados StatusInvest'!$A:$AZ,COLUMN(Z20)-$A$5,0)),0) -> 0.29 | AA20: =IFERROR((VLOOKUP($A20,'Dados StatusInvest'!$A:$AZ,COLUMN(AA20)-$A$5,0)),0) -> 0.61 | AB20: =IFERROR((VLOOKUP($A20,'Dados StatusInvest'!$A:$AZ,COLUMN(AB20)-$A$5,0)),0) -> 0.14 | AC20: =IFERROR((VLOOKUP($A20,'Dados StatusInvest'!$A:$AZ,COLUMN(AC20)-$A$5,0)),0) -> -2.71 | AD20: =IFERROR((VLOOKUP($A20,'Dados StatusInvest'!$A:$AZ,COLUMN(AD20)-$A$5,0)),0) -> 5.5 | AE20: =IFERROR((VLOOKUP($A20,'Dados StatusInvest'!$A:$AZ,COLUMN(AE20)-$A$5,0)),0) -> 120061.5 | AF20: =IFERROR((VLOOKUP($A20,'Dados StatusInvest'!$A:$AZ,COLUMN(AF20)-$A$5,0)),0) -> 9.1 | AG20: =IFERROR((VLOOKUP($A20,'Dados StatusInvest'!$A:$AZ,COLUMN(AG20)-$A$5,0)),0) -> 1.18 | ... AJ20: =IFERROR((VLOOKUP($A20,'Dados StatusInvest'!$A:$AZ,COLUMN(AJ20)-$A$5,0)),0) | AK20: =IFERROR(__xludf.DUMMYFUNCTION("IFERROR(GOOGLEFINANCE($A20,""high""),"""")"),13.28) -> 13.28 | AL20: =IFERROR(__xludf.DUMMYFUNCTION("IFERROR(GOOGLEFINANCE($A20,""low""),"""")"),13.02) -> 13.02 | AM20: =IFERROR(((AK20-AL20)/AL20),0) -> 0.019969278 | AN20: =IFERROR(__xludf.DUMMYFUNCTION("IFERROR((GOOGLEFINANCE($A20,""volume"")),0)"),300.0) -> 300 | AO20: =IFERROR(__xludf.DUMMYFUNCTION("IFERROR((GOOGLEFINANCE($A20,""closeyest"")),"""")"),13.07) -> 13.07 | AP20: =IFERROR(__xludf.DUMMYFUNCTION("IFERROR((GOOGLEFINANCE($A20,""shares"")),"""")"),6.71494278E8) -> 671494278
A21: ='Dados StatusInvest'!A16:A635 -> ALUP4 | B21: =IFERROR(__xludf.DUMMYFUNCTION("IFERROR((GOOGLEFINANCE(A21,""name"")),"""")"),"Alupar Investimento SA Preference Shares") -> Alupar Investimento SA Preference Shares | C21: =IFERROR((VLOOKUP(LEFT($A21,4),Setor!$A:$E,3,0)),"") -> Utilidade Pública | D21: =IFERROR((VLOOKUP(LEFT($A21,4),Setor!$A:$E,4,0)),"") -> Energia Elétrica | E21: =IFERROR((VLOOKUP(LEFT($A21,4),Setor!$A:$E,5,0)),"") -> Energia Elétrica | F21: =IFERROR(__xludf.DUMMYFUNCTION("IFERROR((GOOGLEFINANCE(A21)),"""")"),11.39) -> 11.39 | G21: =IFERROR(__xludf.DUMMYFUNCTION("IFERROR((sparkline(GOOGLEFINANCE($A21,""price"",TODAY()-30,TODAY(),""DAILY""),{""charttype"",""line"";""linewidth"",1;""color"",""#5f88cc""})),"""")"),"") | H21: =IFERROR(__xludf.DUMMYFUNCTION("IFERROR((((GOOGLEFINANCE(A21))-(INDEX(GoogleFinance(A21,""PRICE"",$AQ$1),2,2)))/(INDEX(GoogleFinance(A21,""PRICE"",$AQ$1),2,2))),"""")"),0.04113345521023776) -> 0.041133455 | I21: =IFERROR(__xludf.DUMMYFUNCTION("IFERROR((GOOGLEFINANCE($A21,""high52"")),"""")"),11.56) -> 11.56 | J21: =IFERROR(__xludf.DUMMYFUNCTION("IFERROR((sparkline(GOOGLEFINANCE($A21,""price"",TODAY()-365,TODAY(),""DAILY""),{""charttype"",""line"";""linewidth"",1;""color"",""#5f88cc""})),"""")"),"") | K21: =IFERROR(__xludf.DUMMYFUNCTION("IFERROR((((GOOGLEFINANCE(A21))-(INDEX(GoogleFinance(A21,""PRICE"",$AP$1),2,2)))/(INDEX(GoogleFinance(A21,""PRICE"",$AP$1),2,2))),"""")"),0.27833894500561174) -> 0.27833895 | L21: =IFERROR(((F21-I21)/I21),0) -> -0.014705882 | M21: =IFERROR((VLOOKUP($A21,'Dados StatusInvest'!$A:$AZ,COLUMN(M21)-$A$5,0)*VLOOKUP($A21,'Dados StatusInvest'!$A:$AZ,2,0)/$F21/100),0) -> 0.70680421 | N21: =IFERROR((VLOOKUP($A21,'Dados StatusInvest'!$A:$AZ,COLUMN(N21)-$A$5,0)/VLOOKUP($A21,'Dados StatusInvest'!$A:$AZ,2,0)*$F21),"") -> 27.032267 | O21: =IFERROR((VLOOKUP($A21,'Dados StatusInvest'!$A:$AZ,COLUMN(O21)-$A$5,0)/VLOOKUP($A21,'Dados StatusInvest'!$A:$AZ,2,0)*$F21),0) -> 3.6144267 | P21: =IFERROR((VLOOKUP($A21,'Dados StatusInvest'!$A:$AZ,COLUMN(P21)-$A$5,0)/VLOOKUP($A21,'Dados StatusInvest'!$A:$AZ,2,0)*$F21),0) -> 6.8643733 | Q21: =IFERROR((VLOOKUP($A21,'Dados StatusInvest'!$A:$AZ,COLUMN(Q21)-$A$5,0)/100),0) -> 0.0297 | R21: =VLOOKUP($A21,'Dados StatusInvest'!$A:$AZ,COLUMN(R21)-$A$5,0) -> 1.03 | S21: =IFERROR((VLOOKUP($A21,'Dados StatusInvest'!$A:$AZ,COLUMN(S21)-$A$5,0)),0) -> 2.55 | T21: =IFERROR((VLOOKUP($A21,'Dados StatusInvest'!$A:$AZ,COLUMN(T21)-$A$5,0)/VLOOKUP($A21,'Dados StatusInvest'!$A:$AZ,2,0)*$F21),0) -> 3.0474578 | U21: =IFERROR((VLOOKUP($A21,'Dados StatusInvest'!$A:$AZ,COLUMN(U21)-$A$5,0)-VLOOKUP($A21,'Dados StatusInvest'!$A:$AZ,COLUMN(U21)-$A$5-1,0)+T21),0) -> -0.40254222 | V21: =IFERROR((VLOOKUP($A21,'Dados StatusInvest'!$A:$AZ,COLUMN(V21)-$A$5,0)),0) -> 2.55 | W21: =IFERROR((VLOOKUP($A21,'Dados StatusInvest'!$A:$AZ,COLUMN(W21)-$A$5,0)),0) -> 12.93 | X21: =IFERROR((VLOOKUP($A21,'Dados StatusInvest'!$A:$AZ,COLUMN(X21)-$A$5,0)/VLOOKUP($A21,'Dados StatusInvest'!$A:$AZ,2,0)*$F21),0) -> 3.7460444 | Y21: =IFERROR((VLOOKUP($A21,'Dados StatusInvest'!$A:$AZ,COLUMN(Y21)-$A$5,0)/VLOOKUP($A21,'Dados StatusInvest'!$A:$AZ,2,0)*$F21),0) -> 10.944524 | Z21: =IFERROR((VLOOKUP($A21,'Dados StatusInvest'!$A:$AZ,COLUMN(Z21)-$A$5,0)),0) -> 0.29 | AA21: =IFERROR((VLOOKUP($A21,'Dados StatusInvest'!$A:$AZ,COLUMN(AA21)-$A$5,0)),0) -> 0.61 | AB21: =IFERROR((VLOOKUP($A21,'Dados StatusInvest'!$A:$AZ,COLUMN(AB21)-$A$5,0)),0) -> 0.14 | AC21: =IFERROR((VLOOKUP($A21,'Dados StatusInvest'!$A:$AZ,COLUMN(AC21)-$A$5,0)),0) -> -2.71 | AD21: =IFERROR((VLOOKUP($A21,'Dados StatusInvest'!$A:$AZ,COLUMN(AD21)-$A$5,0)),0) -> 5.5 | AE21: =IFERROR((VLOOKUP($A21,'Dados StatusInvest'!$A:$AZ,COLUMN(AE21)-$A$5,0)),0) -> 164248.6 | AF21: =IFERROR((VLOOKUP($A21,'Dados StatusInvest'!$A:$AZ,COLUMN(AF21)-$A$5,0)),0) -> 9.1 | AG21: =IFERROR((VLOOKUP($A21,'Dados StatusInvest'!$A:$AZ,COLUMN(AG21)-$A$5,0)),0) -> 1.18 | ... AJ21: =IFERROR((VLOOKUP($A21,'Dados StatusInvest'!$A:$AZ,COLUMN(AJ21)-$A$5,0)),0) | AK21: =IFERROR(__xludf.DUMMYFUNCTION("IFERROR(GOOGLEFINANCE($A21,""high""),"""")"),11.48) -> 11.48 | AL21: =IFERROR(__xludf.DUMMYFUNCTION("IFERROR(GOOGLEFINANCE($A21,""low""),"""")"),11.3) -> 11.3 | AM21: =IFERROR(((AK21-AL21)/AL21),0) -> 0.015929204 | AN21: =IFERROR(__xludf.DUMMYFUNCTION("IFERROR((GOOGLEFINANCE($A21,""volume"")),0)"),4800.0) -> 4800 | AO21: =IFERROR(__xludf.DUMMYFUNCTION("IFERROR((GOOGLEFINANCE($A21,""closeyest"")),"""")"),11.25) -> 11.25 | AP21: =IFERROR(__xludf.DUMMYFUNCTION("IFERROR((GOOGLEFINANCE($A21,""shares"")),"""")"),3.17386323E8) -> 317386323
A22: ='Dados StatusInvest'!A17:A636 -> AMAR3 | B22: =IFERROR(__xludf.DUMMYFUNCTION("IFERROR((GOOGLEFINANCE(A22,""name"")),"""")"),"Marisa Lojas SA") -> Marisa Lojas SA | C22: =IFERROR((VLOOKUP(LEFT($A22,4),Setor!$A:$E,3,0)),"") -> Consumo Cíclico | D22: =IFERROR((VLOOKUP(LEFT($A22,4),Setor!$A:$E,4,0)),"") -> Comércio | E22: =IFERROR((VLOOKUP(LEFT($A22,4),Setor!$A:$E,5,0)),"") -> Tecidos, Vestuário e Calçados | F22: =IFERROR(__xludf.DUMMYFUNCTION("IFERROR((GOOGLEFINANCE(A22)),"""")"),0.95) -> 0.95 | G22: =IFERROR(__xludf.DUMMYFUNCTION("IFERROR((sparkline(GOOGLEFINANCE($A22,""price"",TODAY()-30,TODAY(),""DAILY""),{""charttype"",""line"";""linewidth"",1;""color"",""#5f88cc""})),"""")"),"") | H22: =IFERROR(__xludf.DUMMYFUNCTION("IFERROR((((GOOGLEFINANCE(A22))-(INDEX(GoogleFinance(A22,""PRICE"",$AQ$1),2,2)))/(INDEX(GoogleFinance(A22,""PRICE"",$AQ$1),2,2))),"""")"),-0.04040404040404044) -> -0.04040404 | I22: =IFERROR(__xludf.DUMMYFUNCTION("IFERROR((GOOGLEFINANCE($A22,""high52"")),"""")"),1.75) -> 1.75 | J22: =IFERROR(__xludf.DUMMYFUNCTION("IFERROR((sparkline(GOOGLEFINANCE($A22,""price"",TODAY()-365,TODAY(),""DAILY""),{""charttype"",""line"";""linewidth"",1;""color"",""#5f88cc""})),"""")"),"") | K22: =IFERROR(__xludf.DUMMYFUNCTION("IFERROR((((GOOGLEFINANCE(A22))-(INDEX(GoogleFinance(A22,""PRICE"",$AP$1),2,2)))/(INDEX(GoogleFinance(A22,""PRICE"",$AP$1),2,2))),"""")"),-0.24603174603174607) -> -0.24603175 | L22: =IFERROR(((F22-I22)/I22),0) -> -0.45714286 | M22: =IFERROR((VLOOKUP($A22,'Dados StatusInvest'!$A:$AZ,COLUMN(M22)-$A$5,0)*VLOOKUP($A22,'Dados StatusInvest'!$A:$AZ,2,0)/$F22/100),0) -> 0.16514842 | N22: =IFERROR((VLOOKUP($A22,'Dados StatusInvest'!$A:$AZ,COLUMN(N22)-$A$5,0)/VLOOKUP($A22,'Dados StatusInvest'!$A:$AZ,2,0)*$F22),"") -> 1.1032258 | O22: =IFERROR((VLOOKUP($A22,'Dados StatusInvest'!$A:$AZ,COLUMN(O22)-$A$5,0)/VLOOKUP($A22,'Dados StatusInvest'!$A:$AZ,2,0)*$F22),0) -> 1.9408602 | P22: =IFERROR((VLOOKUP($A22,'Dados StatusInvest'!$A:$AZ,COLUMN(P22)-$A$5,0)/VLOOKUP($A22,'Dados StatusInvest'!$A:$AZ,2,0)*$F22),0) -> 5.1892473 | Q22: =IFERROR((VLOOKUP($A22,'Dados StatusInvest'!$A:$AZ,COLUMN(Q22)-$A$5,0)/100),0) -> 0.0319 | R22: =VLOOKUP($A22,'Dados StatusInvest'!$A:$AZ,COLUMN(R22)-$A$5,0) -> 2.72 | S22: =IFERROR((VLOOKUP($A22,'Dados StatusInvest'!$A:$AZ,COLUMN(S22)-$A$5,0)),0) -> 0.32 | T22: =IFERROR((VLOOKUP($A22,'Dados StatusInvest'!$A:$AZ,COLUMN(T22)-$A$5,0)/VLOOKUP($A22,'Dados StatusInvest'!$A:$AZ,2,0)*$F22),0) -> -1.8387097 | U22: =IFERROR((VLOOKUP($A22,'Dados StatusInvest'!$A:$AZ,COLUMN(U22)-$A$5,0)-VLOOKUP($A22,'Dados StatusInvest'!$A:$AZ,COLUMN(U22)-$A$5-1,0)+T22),0) -> -0.35870968 | V22: =IFERROR((VLOOKUP($A22,'Dados StatusInvest'!$A:$AZ,COLUMN(V22)-$A$5,0)),0) -> 0.7 | W22: =IFERROR((VLOOKUP($A22,'Dados StatusInvest'!$A:$AZ,COLUMN(W22)-$A$5,0)),0) -> 5.45 | X22: =IFERROR((VLOOKUP($A22,'Dados StatusInvest'!$A:$AZ,COLUMN(X22)-$A$5,0)/VLOOKUP($A22,'Dados StatusInvest'!$A:$AZ,2,0)*$F22),0) -> 0.77634409 | Y22: =IFERROR((VLOOKUP($A22,'Dados StatusInvest'!$A:$AZ,COLUMN(Y22)-$A$5,0)/VLOOKUP($A22,'Dados StatusInvest'!$A:$AZ,2,0)*$F22),0) -> 21.941935 | Z22: =IFERROR((VLOOKUP($A22,'Dados StatusInvest'!$A:$AZ,COLUMN(Z22)-$A$5,0)),0) -> 0.14 | AA22: =IFERROR((VLOOKUP($A22,'Dados StatusInvest'!$A:$AZ,COLUMN(AA22)-$A$5,0)),0) -> 0.86 | AB22: =IFERROR((VLOOKUP($A22,'Dados StatusInvest'!$A:$AZ,COLUMN(AB22)-$A$5,0)),0) -> 0.7 | AC22: =IFERROR((VLOOKUP($A22,'Dados StatusInvest'!$A:$AZ,COLUMN(AC22)-$A$5,0)),0) -> -13.55 | AD22: =IFERROR((VLOOKUP($A22,'Dados StatusInvest'!$A:$AZ,COLUMN(AD22)-$A$5,0)),0) -> 0 | AE22: =IFERROR((VLOOKUP($A22,'Dados StatusInvest'!$A:$AZ,COLUMN(AE22)-$A$5,0)),0) -> 289427.5 | AF22: =IFERROR((VLOOKUP($A22,'Dados StatusInvest'!$A:$AZ,COLUMN(AF22)-$A$5,0)),0) -> 0.58 | AG22: =IFERROR((VLOOKUP($A22,'Dados StatusInvest'!$A:$AZ,COLUMN(AG22)-$A$5,0)),0) -> 0.03 | ... AJ22: =IFERROR((VLOOKUP($A22,'Dados StatusInvest'!$A:$AZ,COLUMN(AJ22)-$A$5,0)),0) | AK22: =IFERROR(__xludf.DUMMYFUNCTION("IFERROR(GOOGLEFINANCE($A22,""high""),"""")"),0.95) -> 0.95 | AL22: =IFERROR(__xludf.DUMMYFUNCTION("IFERROR(GOOGLEFINANCE($A22,""low""),"""")"),0.93) -> 0.93 | AM22: =IFERROR(((AK22-AL22)/AL22),0) -> 0.021505376 | AN22: =IFERROR(__xludf.DUMMYFUNCTION("IFERROR((GOOGLEFINANCE($A22,""volume"")),0)"),6900.0) -> 6900 | AO22: =IFERROR(__xludf.DUMMYFUNCTION("IFERROR((GOOGLEFINANCE($A22,""closeyest"")),"""")"),0.93) -> 0.93 | AP22: =IFERROR(__xludf.DUMMYFUNCTION("IFERROR((GOOGLEFINANCE($A22,""shares"")),"""")"),5.13516302E8) -> 513516302
A23: ='Dados StatusInvest'!A18:A637 -> AMBP3 | B23: =IFERROR(__xludf.DUMMYFUNCTION("IFERROR((GOOGLEFINANCE(A23,""name"")),"""")"),"Ambipar Participacoes e Empreendmnts SA") -> Ambipar Participacoes e Empreendmnts SA | C23: =IFERROR((VLOOKUP(LEFT($A23,4),Setor!$A:$E,3,0)),"") -> Bens Industriais | D23: =IFERROR((VLOOKUP(LEFT($A23,4),Setor!$A:$E,4,0)),"") -> Serviços Diversos | E23: =IFERROR((VLOOKUP(LEFT($A23,4),Setor!$A:$E,5,0)),"") -> Serviços Diversos | F23: =IFERROR(__xludf.DUMMYFUNCTION("IFERROR((GOOGLEFINANCE(A23)),"""")"),0.26) -> 0.26 | G23: =IFERROR(__xludf.DUMMYFUNCTION("IFERROR((sparkline(GOOGLEFINANCE($A23,""price"",TODAY()-30,TODAY(),""DAILY""),{""charttype"",""line"";""linewidth"",1;""color"",""#5f88cc""})),"""")"),"") | H23: =IFERROR(__xludf.DUMMYFUNCTION("IFERROR((((GOOGLEFINANCE(A23))-(INDEX(GoogleFinance(A23,""PRICE"",$AQ$1),2,2)))/(INDEX(GoogleFinance(A23,""PRICE"",$AQ$1),2,2))),"""")"),-0.10344827586206887) -> -0.10344828 | I23: =IFERROR(__xludf.DUMMYFUNCTION("IFERROR((GOOGLEFINANCE($A23,""high52"")),"""")"),20.5) -> 20.5 | J23: =IFERROR(__xludf.DUMMYFUNCTION("IFERROR((sparkline(GOOGLEFINANCE($A23,""price"",TODAY()-365,TODAY(),""DAILY""),{""charttype"",""line"";""linewidth"",1;""color"",""#5f88cc""})),"""")"),"") | K23: =IFERROR(__xludf.DUMMYFUNCTION("IFERROR((((GOOGLEFINANCE(A23))-(INDEX(GoogleFinance(A23,""PRICE"",$AP$1),2,2)))/(INDEX(GoogleFinance(A23,""PRICE"",$AP$1),2,2))),"""")"),-0.978369384359401) -> -0.97836938 | L23: =IFERROR(((F23-I23)/I23),0) -> -0.98731707 | M23: =IFERROR((VLOOKUP($A23,'Dados StatusInvest'!$A:$AZ,COLUMN(M23)-$A$5,0)*VLOOKUP($A23,'Dados StatusInvest'!$A:$AZ,2,0)/$F23/100),0) -> 0.1736 | N23: =IFERROR((VLOOKUP($A23,'Dados StatusInvest'!$A:$AZ,COLUMN(N23)-$A$5,0)/VLOOKUP($A23,'Dados StatusInvest'!$A:$AZ,2,0)*$F23),"") -> -3.54 | O23: =IFERROR((VLOOKUP($A23,'Dados StatusInvest'!$A:$AZ,COLUMN(O23)-$A$5,0)/VLOOKUP($A23,'Dados StatusInvest'!$A:$AZ,2,0)*$F23),0) -> 0.35 | P23: =IFERROR((VLOOKUP($A23,'Dados StatusInvest'!$A:$AZ,COLUMN(P23)-$A$5,0)/VLOOKUP($A23,'Dados StatusInvest'!$A:$AZ,2,0)*$F23),0) -> 5.4 | Q23: =IFERROR((VLOOKUP($A23,'Dados StatusInvest'!$A:$AZ,COLUMN(Q23)-$A$5,0)/100),0) -> 0.0506 | R23: =VLOOKUP($A23,'Dados StatusInvest'!$A:$AZ,COLUMN(R23)-$A$5,0) -> 5.81 | S23: =IFERROR((VLOOKUP($A23,'Dados StatusInvest'!$A:$AZ,COLUMN(S23)-$A$5,0)),0) -> 0.06 | T23: =IFERROR((VLOOKUP($A23,'Dados StatusInvest'!$A:$AZ,COLUMN(T23)-$A$5,0)/VLOOKUP($A23,'Dados StatusInvest'!$A:$AZ,2,0)*$F23),0) -> 0.09 | U23: =IFERROR((VLOOKUP($A23,'Dados StatusInvest'!$A:$AZ,COLUMN(U23)-$A$5,0)-VLOOKUP($A23,'Dados StatusInvest'!$A:$AZ,COLUMN(U23)-$A$5-1,0)+T23),0) -> -0.05 | V23: =IFERROR((VLOOKUP($A23,'Dados StatusInvest'!$A:$AZ,COLUMN(V23)-$A$5,0)),0) -> 2.72 | W23: =IFERROR((VLOOKUP($A23,'Dados StatusInvest'!$A:$AZ,COLUMN(W23)-$A$5,0)),0) -> -23.47 | X23: =IFERROR((VLOOKUP($A23,'Dados StatusInvest'!$A:$AZ,COLUMN(X23)-$A$5,0)/VLOOKUP($A23,'Dados StatusInvest'!$A:$AZ,2,0)*$F23),0) -> -1.52 | Y23: =IFERROR((VLOOKUP($A23,'Dados StatusInvest'!$A:$AZ,COLUMN(Y23)-$A$5,0)/VLOOKUP($A23,'Dados StatusInvest'!$A:$AZ,2,0)*$F23),0) -> 8.91 | Z23: =IFERROR((VLOOKUP($A23,'Dados StatusInvest'!$A:$AZ,COLUMN(Z23)-$A$5,0)),0) -> 0.06 | AA23: =IFERROR((VLOOKUP($A23,'Dados StatusInvest'!$A:$AZ,COLUMN(AA23)-$A$5,0)),0) -> 0.87 | AB23: =IFERROR((VLOOKUP($A23,'Dados StatusInvest'!$A:$AZ,COLUMN(AB23)-$A$5,0)),0) -> 0.43 | AC23: =IFERROR((VLOOKUP($A23,'Dados StatusInvest'!$A:$AZ,COLUMN(AC23)-$A$5,0)),0) -> 67.64 | AD23: =IFERROR((VLOOKUP($A23,'Dados StatusInvest'!$A:$AZ,COLUMN(AD23)-$A$5,0)),0) -> 0 | AE23: =IFERROR((VLOOKUP($A23,'Dados StatusInvest'!$A:$AZ,COLUMN(AE23)-$A$5,0)),0) -> 2280300 | AF23: =IFERROR((VLOOKUP($A23,'Dados StatusInvest'!$A:$AZ,COLUMN(AF23)-$A$5,0)),0) -> 0.65 | AG23: =IFERROR((VLOOKUP($A23,'Dados StatusInvest'!$A:$AZ,COLUMN(AG23)-$A$5,0)),0) -> -0.15 | ... AJ23: =IFERROR((VLOOKUP($A23,'Dados StatusInvest'!$A:$AZ,COLUMN(AJ23)-$A$5,0)),0) | AK23: =IFERROR(__xludf.DUMMYFUNCTION("IFERROR(GOOGLEFINANCE($A23,""high""),"""")"),0.26) -> 0.26 | AL23: =IFERROR(__xludf.DUMMYFUNCTION("IFERROR(GOOGLEFINANCE($A23,""low""),"""")"),0.25) -> 0.25 | AM23: =IFERROR(((AK23-AL23)/AL23),0) -> 0.04 | AN23: =IFERROR(__xludf.DUMMYFUNCTION("IFERROR((GOOGLEFINANCE($A23,""volume"")),0)"),864100.0) -> 864100 | AO23: =IFERROR(__xludf.DUMMYFUNCTION("IFERROR((GOOGLEFINANCE($A23,""closeyest"")),"""")"),0.26) -> 0.26 | AP23: =IFERROR(__xludf.DUMMYFUNCTION("IFERROR((GOOGLEFINANCE($A23,""shares"")),"""")"),1.67041869E9) -> 1670418690
A24: ='Dados StatusInvest'!A19:A638 -> AMER3 | B24: =IFERROR(__xludf.DUMMYFUNCTION("IFERROR((GOOGLEFINANCE(A24,""name"")),"""")"),"Americanas SA - Em Recuperacao Judicial") -> Americanas SA - Em Recuperacao Judicial | C24: =IFERROR((VLOOKUP(LEFT($A24,4),Setor!$A:$E,3,0)),"") | D24: =IFERROR((VLOOKUP(LEFT($A24,4),Setor!$A:$E,4,0)),"") | E24: =IFERROR((VLOOKUP(LEFT($A24,4),Setor!$A:$E,5,0)),"") | F24: =IFERROR(__xludf.DUMMYFUNCTION("IFERROR((GOOGLEFINANCE(A24)),"""")"),5.61) -> 5.61 | G24: =IFERROR(__xludf.DUMMYFUNCTION("IFERROR((sparkline(GOOGLEFINANCE($A24,""price"",TODAY()-30,TODAY(),""DAILY""),{""charttype"",""line"";""linewidth"",1;""color"",""#5f88cc""})),"""")"),"") | H24: =IFERROR(__xludf.DUMMYFUNCTION("IFERROR((((GOOGLEFINANCE(A24))-(INDEX(GoogleFinance(A24,""PRICE"",$AQ$1),2,2)))/(INDEX(GoogleFinance(A24,""PRICE"",$AQ$1),2,2))),"""")"),0.1785714285714287) -> 0.17857143 | I24: =IFERROR(__xludf.DUMMYFUNCTION("IFERROR((GOOGLEFINANCE($A24,""high52"")),"""")"),9.5) -> 9.5 | J24: =IFERROR(__xludf.DUMMYFUNCTION("IFERROR((sparkline(GOOGLEFINANCE($A24,""price"",TODAY()-365,TODAY(),""DAILY""),{""charttype"",""line"";""linewidth"",1;""color"",""#5f88cc""})),"""")"),"") | K24: =IFERROR(__xludf.DUMMYFUNCTION("IFERROR((((GOOGLEFINANCE(A24))-(INDEX(GoogleFinance(A24,""PRICE"",$AP$1),2,2)))/(INDEX(GoogleFinance(A24,""PRICE"",$AP$1),2,2))),"""")"),-0.02264808362369336) -> -0.022648084 | L24: =IFERROR(((F24-I24)/I24),0) -> -0.40947368 | M24: =IFERROR((VLOOKUP($A24,'Dados StatusInvest'!$A:$AZ,COLUMN(M24)-$A$5,0)*VLOOKUP($A24,'Dados StatusInvest'!$A:$AZ,2,0)/$F24/100),0) -> -0.024805704 | N24: =IFERROR((VLOOKUP($A24,'Dados StatusInvest'!$A:$AZ,COLUMN(N24)-$A$5,0)/VLOOKUP($A24,'Dados StatusInvest'!$A:$AZ,2,0)*$F24),"") -> -5.7779049 | O24: =IFERROR((VLOOKUP($A24,'Dados StatusInvest'!$A:$AZ,COLUMN(O24)-$A$5,0)/VLOOKUP($A24,'Dados StatusInvest'!$A:$AZ,2,0)*$F24),0) -> -3.298838 | P24: =IFERROR((VLOOKUP($A24,'Dados StatusInvest'!$A:$AZ,COLUMN(P24)-$A$5,0)/VLOOKUP($A24,'Dados StatusInvest'!$A:$AZ,2,0)*$F24),0) -> -7.1507746 | Q24: =IFERROR((VLOOKUP($A24,'Dados StatusInvest'!$A:$AZ,COLUMN(Q24)-$A$5,0)/100),0) -> -0.0391 | R24: =VLOOKUP($A24,'Dados StatusInvest'!$A:$AZ,COLUMN(R24)-$A$5,0) -> 0.28 | S24: =IFERROR((VLOOKUP($A24,'Dados StatusInvest'!$A:$AZ,COLUMN(S24)-$A$5,0)),0) -> 0.08 | T24: =IFERROR((VLOOKUP($A24,'Dados StatusInvest'!$A:$AZ,COLUMN(T24)-$A$5,0)/VLOOKUP($A24,'Dados StatusInvest'!$A:$AZ,2,0)*$F24),0) -> 0.38519366 | U24: =IFERROR((VLOOKUP($A24,'Dados StatusInvest'!$A:$AZ,COLUMN(U24)-$A$5,0)-VLOOKUP($A24,'Dados StatusInvest'!$A:$AZ,COLUMN(U24)-$A$5-1,0)+T24),0) -> -0.13480634 | V24: =IFERROR((VLOOKUP($A24,'Dados StatusInvest'!$A:$AZ,COLUMN(V24)-$A$5,0)),0) -> 1.63 | W24: =IFERROR((VLOOKUP($A24,'Dados StatusInvest'!$A:$AZ,COLUMN(W24)-$A$5,0)),0) -> -17.16 | X24: =IFERROR((VLOOKUP($A24,'Dados StatusInvest'!$A:$AZ,COLUMN(X24)-$A$5,0)/VLOOKUP($A24,'Dados StatusInvest'!$A:$AZ,2,0)*$F24),0) -> -4.9680106 | Y24: =IFERROR((VLOOKUP($A24,'Dados StatusInvest'!$A:$AZ,COLUMN(Y24)-$A$5,0)/VLOOKUP($A24,'Dados StatusInvest'!$A:$AZ,2,0)*$F24),0) -> -7.3483099 | Z24: =IFERROR((VLOOKUP($A24,'Dados StatusInvest'!$A:$AZ,COLUMN(Z24)-$A$5,0)),0) -> 0.29 | AA24: =IFERROR((VLOOKUP($A24,'Dados StatusInvest'!$A:$AZ,COLUMN(AA24)-$A$5,0)),0) -> 0.71 | AB24: =IFERROR((VLOOKUP($A24,'Dados StatusInvest'!$A:$AZ,COLUMN(AB24)-$A$5,0)),0) -> 0.86 | AC24: =IFERROR((VLOOKUP($A24,'Dados StatusInvest'!$A:$AZ,COLUMN(AC24)-$A$5,0)),0) -> 16.22 | AD24: =IFERROR((VLOOKUP($A24,'Dados StatusInvest'!$A:$AZ,COLUMN(AD24)-$A$5,0)),0) -> 0 | AE24: =IFERROR((VLOOKUP($A24,'Dados StatusInvest'!$A:$AZ,COLUMN(AE24)-$A$5,0)),0) -> 11446965 | AF24: =IFERROR((VLOOKUP($A24,'Dados StatusInvest'!$A:$AZ,COLUMN(AF24)-$A$5,0)),0) -> 23.66 | AG24: =IFERROR((VLOOKUP($A24,'Dados StatusInvest'!$A:$AZ,COLUMN(AG24)-$A$5,0)),0) -> -4.06 | ... AJ24: =IFERROR((VLOOKUP($A24,'Dados StatusInvest'!$A:$AZ,COLUMN(AJ24)-$A$5,0)),0) | AK24: =IFERROR(__xludf.DUMMYFUNCTION("IFERROR(GOOGLEFINANCE($A24,""high""),"""")"),5.64) -> 5.64 | AL24: =IFERROR(__xludf.DUMMYFUNCTION("IFERROR(GOOGLEFINANCE($A24,""low""),"""")"),5.58) -> 5.58 | AM24: =IFERROR(((AK24-AL24)/AL24),0) -> 0.010752688 | AN24: =IFERROR(__xludf.DUMMYFUNCTION("IFERROR((GOOGLEFINANCE($A24,""volume"")),0)"),119200.0) -> 119200 | AO24: =IFERROR(__xludf.DUMMYFUNCTION("IFERROR((GOOGLEFINANCE($A24,""closeyest"")),"""")"),5.68) -> 5.68 | AP24: =IFERROR(__xludf.DUMMYFUNCTION("IFERROR((GOOGLEFINANCE($A24,""shares"")),"""")"),2.00244999E8) -> 200244999
A25: ='Dados StatusInvest'!A20:A639 -> AMOB3 | B25: =IFERROR(__xludf.DUMMYFUNCTION("IFERROR((GOOGLEFINANCE(A25,""name"")),"""")"),"Automob Participacoes SA") -> Automob Participacoes SA | C25: =IFERROR((VLOOKUP(LEFT($A25,4),Setor!$A:$E,3,0)),"") | D25: =IFERROR((VLOOKUP(LEFT($A25,4),Setor!$A:$E,4,0)),"") | E25: =IFERROR((VLOOKUP(LEFT($A25,4),Setor!$A:$E,5,0)),"") | F25: =IFERROR(__xludf.DUMMYFUNCTION("IFERROR((GOOGLEFINANCE(A25)),"""")"),13.3) -> 13.3 | G25: =IFERROR(__xludf.DUMMYFUNCTION("IFERROR((sparkline(GOOGLEFINANCE($A25,""price"",TODAY()-30,TODAY(),""DAILY""),{""charttype"",""line"";""linewidth"",1;""color"",""#5f88cc""})),"""")"),"") | H25: =IFERROR(__xludf.DUMMYFUNCTION("IFERROR((((GOOGLEFINANCE(A25))-(INDEX(GoogleFinance(A25,""PRICE"",$AQ$1),2,2)))/(INDEX(GoogleFinance(A25,""PRICE"",$AQ$1),2,2))),"""")"),0.0075757575757576835) -> 0.0075757576 | I25: =IFERROR(__xludf.DUMMYFUNCTION("IFERROR((GOOGLEFINANCE($A25,""high52"")),"""")"),15.5) -> 15.5 | J25: =IFERROR(__xludf.DUMMYFUNCTION("IFERROR((sparkline(GOOGLEFINANCE($A25,""price"",TODAY()-365,TODAY(),""DAILY""),{""charttype"",""line"";""linewidth"",1;""color"",""#5f88cc""})),"""")"),"") | K25: =IFERROR(__xludf.DUMMYFUNCTION("IFERROR((((GOOGLEFINANCE(A25))-(INDEX(GoogleFinance(A25,""PRICE"",$AP$1),2,2)))/(INDEX(GoogleFinance(A25,""PRICE"",$AP$1),2,2))),"""")"),0.02307692307692313) -> 0.023076923 | L25: =IFERROR(((F25-I25)/I25),0) -> -0.14193548 | M25: =IFERROR((VLOOKUP($A25,'Dados StatusInvest'!$A:$AZ,COLUMN(M25)-$A$5,0)*VLOOKUP($A25,'Dados StatusInvest'!$A:$AZ,2,0)/$F25/100),0) -> -0.46573579 | N25: =IFERROR((VLOOKUP($A25,'Dados StatusInvest'!$A:$AZ,COLUMN(N25)-$A$5,0)/VLOOKUP($A25,'Dados StatusInvest'!$A:$AZ,2,0)*$F25),"") -> -57.884656 | O25: =IFERROR((VLOOKUP($A25,'Dados StatusInvest'!$A:$AZ,COLUMN(O25)-$A$5,0)/VLOOKUP($A25,'Dados StatusInvest'!$A:$AZ,2,0)*$F25),0) -> 0 | P25: =IFERROR((VLOOKUP($A25,'Dados StatusInvest'!$A:$AZ,COLUMN(P25)-$A$5,0)/VLOOKUP($A25,'Dados StatusInvest'!$A:$AZ,2,0)*$F25),0) -> 0 | Q25: =IFERROR((VLOOKUP($A25,'Dados StatusInvest'!$A:$AZ,COLUMN(Q25)-$A$5,0)/100),0) -> -0.0001 | R25: =VLOOKUP($A25,'Dados StatusInvest'!$A:$AZ,COLUMN(R25)-$A$5,0) -> 0 | S25: =IFERROR((VLOOKUP($A25,'Dados StatusInvest'!$A:$AZ,COLUMN(S25)-$A$5,0)),0) -> 0 | T25: =IFERROR((VLOOKUP($A25,'Dados StatusInvest'!$A:$AZ,COLUMN(T25)-$A$5,0)/VLOOKUP($A25,'Dados StatusInvest'!$A:$AZ,2,0)*$F25),0) -> 0 | U25: =IFERROR((VLOOKUP($A25,'Dados StatusInvest'!$A:$AZ,COLUMN(U25)-$A$5,0)-VLOOKUP($A25,'Dados StatusInvest'!$A:$AZ,COLUMN(U25)-$A$5-1,0)+T25),0) -> 0 | V25: =IFERROR((VLOOKUP($A25,'Dados StatusInvest'!$A:$AZ,COLUMN(V25)-$A$5,0)),0) -> 0.19 | W25: =IFERROR((VLOOKUP($A25,'Dados StatusInvest'!$A:$AZ,COLUMN(W25)-$A$5,0)),0) -> -2595.29 | X25: =IFERROR((VLOOKUP($A25,'Dados StatusInvest'!$A:$AZ,COLUMN(X25)-$A$5,0)/VLOOKUP($A25,'Dados StatusInvest'!$A:$AZ,2,0)*$F25),0) -> -6062.1661 | Y25: =IFERROR((VLOOKUP($A25,'Dados StatusInvest'!$A:$AZ,COLUMN(Y25)-$A$5,0)/VLOOKUP($A25,'Dados StatusInvest'!$A:$AZ,2,0)*$F25),0) -> 2674.436 | Z25: =IFERROR((VLOOKUP($A25,'Dados StatusInvest'!$A:$AZ,COLUMN(Z25)-$A$5,0)),0) -> -2.32 | AA25: =IFERROR((VLOOKUP($A25,'Dados StatusInvest'!$A:$AZ,COLUMN(AA25)-$A$5,0)),0) -> 3.32 | AB25: =IFERROR((VLOOKUP($A25,'Dados StatusInvest'!$A:$AZ,COLUMN(AB25)-$A$5,0)),0) -> 104.73 | AC25: =IFERROR((VLOOKUP($A25,'Dados StatusInvest'!$A:$AZ,COLUMN(AC25)-$A$5,0)),0) -> 0 | AD25: =IFERROR((VLOOKUP($A25,'Dados StatusInvest'!$A:$AZ,COLUMN(AD25)-$A$5,0)),0) -> 0 | AE25: =IFERROR((VLOOKUP($A25,'Dados StatusInvest'!$A:$AZ,COLUMN(AE25)-$A$5,0)),0) -> 547696.1 | AF25: =IFERROR((VLOOKUP($A25,'Dados StatusInvest'!$A:$AZ,COLUMN(AF25)-$A$5,0)),0) -> 0 | AG25: =IFERROR((VLOOKUP($A25,'Dados StatusInvest'!$A:$AZ,COLUMN(AG25)-$A$5,0)),0) -> 0 | ... AJ25: =IFERROR((VLOOKUP($A25,'Dados StatusInvest'!$A:$AZ,COLUMN(AJ25)-$A$5,0)),0) | AK25: =IFERROR(__xludf.DUMMYFUNCTION("IFERROR(GOOGLEFINANCE($A25,""high""),"""")"),13.37) -> 13.37 | AL25: =IFERROR(__xludf.DUMMYFUNCTION("IFERROR(GOOGLEFINANCE($A25,""low""),"""")"),13.1) -> 13.1 | AM25: =IFERROR(((AK25-AL25)/AL25),0) -> 0.020610687 | AN25: =IFERROR(__xludf.DUMMYFUNCTION("IFERROR((GOOGLEFINANCE($A25,""volume"")),0)"),2300.0) -> 2300 | AO25: =IFERROR(__xludf.DUMMYFUNCTION("IFERROR((GOOGLEFINANCE($A25,""closeyest"")),"""")"),13.23) -> 13.23 | AP25: =IFERROR(__xludf.DUMMYFUNCTION("IFERROR((GOOGLEFINANCE($A25,""shares"")),"""")"),3.7886057E7) -> 37886057
A26: ='Dados StatusInvest'!A21:A640 -> ANIM3 | B26: =IFERROR(__xludf.DUMMYFUNCTION("IFERROR((GOOGLEFINANCE(A26,""name"")),"""")"),"Anima Holding SA") -> Anima Holding SA | C26: =IFERROR((VLOOKUP(LEFT($A26,4),Setor!$A:$E,3,0)),"") -> Consumo Cíclico | D26: =IFERROR((VLOOKUP(LEFT($A26,4),Setor!$A:$E,4,0)),"") -> Diversos | E26: =IFERROR((VLOOKUP(LEFT($A26,4),Setor!$A:$E,5,0)),"") -> Serviços Educacionais | F26: =IFERROR(__xludf.DUMMYFUNCTION("IFERROR((GOOGLEFINANCE(A26)),"""")"),4.87) -> 4.87 | G26: =IFERROR(__xludf.DUMMYFUNCTION("IFERROR((sparkline(GOOGLEFINANCE($A26,""price"",TODAY()-30,TODAY(),""DAILY""),{""charttype"",""line"";""linewidth"",1;""color"",""#5f88cc""})),"""")"),"") | H26: =IFERROR(__xludf.DUMMYFUNCTION("IFERROR((((GOOGLEFINANCE(A26))-(INDEX(GoogleFinance(A26,""PRICE"",$AQ$1),2,2)))/(INDEX(GoogleFinance(A26,""PRICE"",$AQ$1),2,2))),"""")"),0.10180995475113126) -> 0.10180995 | I26: =IFERROR(__xludf.DUMMYFUNCTION("IFERROR((GOOGLEFINANCE($A26,""high52"")),"""")"),5.39) -> 5.39 | J26: =IFERROR(__xludf.DUMMYFUNCTION("IFERROR((sparkline(GOOGLEFINANCE($A26,""price"",TODAY()-365,TODAY(),""DAILY""),{""charttype"",""line"";""linewidth"",1;""color"",""#5f88cc""})),"""")"),"") | K26: =IFERROR(__xludf.DUMMYFUNCTION("IFERROR((((GOOGLEFINANCE(A26))-(INDEX(GoogleFinance(A26,""PRICE"",$AP$1),2,2)))/(INDEX(GoogleFinance(A26,""PRICE"",$AP$1),2,2))),"""")"),1.2339449541284402) -> 1.233945 | L26: =IFERROR(((F26-I26)/I26),0) -> -0.096474954 | M26: =IFERROR((VLOOKUP($A26,'Dados StatusInvest'!$A:$AZ,COLUMN(M26)-$A$5,0)*VLOOKUP($A26,'Dados StatusInvest'!$A:$AZ,2,0)/$F26/100),0) -> 0.25513347 | N26: =IFERROR((VLOOKUP($A26,'Dados StatusInvest'!$A:$AZ,COLUMN(N26)-$A$5,0)/VLOOKUP($A26,'Dados StatusInvest'!$A:$AZ,2,0)*$F26),"") -> 3.88626 | O26: =IFERROR((VLOOKUP($A26,'Dados StatusInvest'!$A:$AZ,COLUMN(O26)-$A$5,0)/VLOOKUP($A26,'Dados StatusInvest'!$A:$AZ,2,0)*$F26),0) -> 2.00644 | P26: =IFERROR((VLOOKUP($A26,'Dados StatusInvest'!$A:$AZ,COLUMN(P26)-$A$5,0)/VLOOKUP($A26,'Dados StatusInvest'!$A:$AZ,2,0)*$F26),0) -> 5.81478 | Q26: =IFERROR((VLOOKUP($A26,'Dados StatusInvest'!$A:$AZ,COLUMN(Q26)-$A$5,0)/100),0) -> 0.0391 | R26: =VLOOKUP($A26,'Dados StatusInvest'!$A:$AZ,COLUMN(R26)-$A$5,0) -> 1.63 | S26: =IFERROR((VLOOKUP($A26,'Dados StatusInvest'!$A:$AZ,COLUMN(S26)-$A$5,0)),0) -> 0.51 | T26: =IFERROR((VLOOKUP($A26,'Dados StatusInvest'!$A:$AZ,COLUMN(T26)-$A$5,0)/VLOOKUP($A26,'Dados StatusInvest'!$A:$AZ,2,0)*$F26),0) -> 1.61684 | U26: =IFERROR((VLOOKUP($A26,'Dados StatusInvest'!$A:$AZ,COLUMN(U26)-$A$5,0)-VLOOKUP($A26,'Dados StatusInvest'!$A:$AZ,COLUMN(U26)-$A$5-1,0)+T26),0) -> -0.31316 | V26: =IFERROR((VLOOKUP($A26,'Dados StatusInvest'!$A:$AZ,COLUMN(V26)-$A$5,0)),0) -> 1.92 | W26: =IFERROR((VLOOKUP($A26,'Dados StatusInvest'!$A:$AZ,COLUMN(W26)-$A$5,0)),0) -> 6.7 | X26: =IFERROR((VLOOKUP($A26,'Dados StatusInvest'!$A:$AZ,COLUMN(X26)-$A$5,0)/VLOOKUP($A26,'Dados StatusInvest'!$A:$AZ,2,0)*$F26),0) -> 1.51944 | Y26: =IFERROR((VLOOKUP($A26,'Dados StatusInvest'!$A:$AZ,COLUMN(Y26)-$A$5,0)/VLOOKUP($A26,'Dados StatusInvest'!$A:$AZ,2,0)*$F26),0) -> 11.30814 | Z26: =IFERROR((VLOOKUP($A26,'Dados StatusInvest'!$A:$AZ,COLUMN(Z26)-$A$5,0)),0) -> 0.23 | AA26: =IFERROR((VLOOKUP($A26,'Dados StatusInvest'!$A:$AZ,COLUMN(AA26)-$A$5,0)),0) -> 0.71 | AB26: =IFERROR((VLOOKUP($A26,'Dados StatusInvest'!$A:$AZ,COLUMN(AB26)-$A$5,0)),0) -> 0.39 | AC26: =IFERROR((VLOOKUP($A26,'Dados StatusInvest'!$A:$AZ,COLUMN(AC26)-$A$5,0)),0) -> 26.33 | AD26: =IFERROR((VLOOKUP($A26,'Dados StatusInvest'!$A:$AZ,COLUMN(AD26)-$A$5,0)),0) -> 0 | AE26: =IFERROR((VLOOKUP($A26,'Dados StatusInvest'!$A:$AZ,COLUMN(AE26)-$A$5,0)),0) -> 45686853 | AF26: =IFERROR((VLOOKUP($A26,'Dados StatusInvest'!$A:$AZ,COLUMN(AF26)-$A$5,0)),0) -> 5.83 | AG26: =IFERROR((VLOOKUP($A26,'Dados StatusInvest'!$A:$AZ,COLUMN(AG26)-$A$5,0)),0) -> 0.39 | ... AJ26: =IFERROR((VLOOKUP($A26,'Dados StatusInvest'!$A:$AZ,COLUMN(AJ26)-$A$5,0)),0) | AK26: =IFERROR(__xludf.DUMMYFUNCTION("IFERROR(GOOGLEFINANCE($A26,""high""),"""")"),4.99) -> 4.99 | AL26: =IFERROR(__xludf.DUMMYFUNCTION("IFERROR(GOOGLEFINANCE($A26,""low""),"""")"),4.82) -> 4.82 | AM26: =IFERROR(((AK26-AL26)/AL26),0) -> 0.03526971 | AN26: =IFERROR(__xludf.DUMMYFUNCTION("IFERROR((GOOGLEFINANCE($A26,""volume"")),0)"),707000.0) -> 707000 | AO26: =IFERROR(__xludf.DUMMYFUNCTION("IFERROR((GOOGLEFINANCE($A26,""closeyest"")),"""")"),5.0) -> 5 | AP26: =IFERROR(__xludf.DUMMYFUNCTION("IFERROR((GOOGLEFINANCE($A26,""shares"")),"""")"),4.03868805E8) -> 403868805
A27: ='Dados StatusInvest'!A22:A641 -> APER3 | B27: =IFERROR(__xludf.DUMMYFUNCTION("IFERROR((GOOGLEFINANCE(A27,""name"")),"""")"),"") | C27: =IFERROR((VLOOKUP(LEFT($A27,4),Setor!$A:$E,3,0)),"") -> Financeiro | D27: =IFERROR((VLOOKUP(LEFT($A27,4),Setor!$A:$E,4,0)),"") -> Previdência e Seguros | E27: =IFERROR((VLOOKUP(LEFT($A27,4),Setor!$A:$E,5,0)),"") -> Corretoras de Seguros | F27: =IFERROR(__xludf.DUMMYFUNCTION("IFERROR((GOOGLEFINANCE(A27)),"""")"),"") | G27: =IFERROR(__xludf.DUMMYFUNCTION("IFERROR((sparkline(GOOGLEFINANCE($A27,""price"",TODAY()-30,TODAY(),""DAILY""),{""charttype"",""line"";""linewidth"",1;""color"",""#5f88cc""})),"""")"),"") | H27: =IFERROR(__xludf.DUMMYFUNCTION("IFERROR((((GOOGLEFINANCE(A27))-(INDEX(GoogleFinance(A27,""PRICE"",$AQ$1),2,2)))/(INDEX(GoogleFinance(A27,""PRICE"",$AQ$1),2,2))),"""")"),"") | I27: =IFERROR(__xludf.DUMMYFUNCTION("IFERROR((GOOGLEFINANCE($A27,""high52"")),"""")"),"") | J27: =IFERROR(__xludf.DUMMYFUNCTION("IFERROR((sparkline(GOOGLEFINANCE($A27,""price"",TODAY()-365,TODAY(),""DAILY""),{""charttype"",""line"";""linewidth"",1;""color"",""#5f88cc""})),"""")"),"") | K27: =IFERROR(__xludf.DUMMYFUNCTION("IFERROR((((GOOGLEFINANCE(A27))-(INDEX(GoogleFinance(A27,""PRICE"",$AP$1),2,2)))/(INDEX(GoogleFinance(A27,""PRICE"",$AP$1),2,2))),"""")"),"") | L27: =IFERROR(((F27-I27)/I27),0) -> 0 | M27: =IFERROR((VLOOKUP($A27,'Dados StatusInvest'!$A:$AZ,COLUMN(M27)-$A$5,0)*VLOOKUP($A27,'Dados StatusInvest'!$A:$AZ,2,0)/$F27/100),0) -> 0 | N27: =IFERROR((VLOOKUP($A27,'Dados StatusInvest'!$A:$AZ,COLUMN(N27)-$A$5,0)/VLOOKUP($A27,'Dados StatusInvest'!$A:$AZ,2,0)*$F27),"") -> 0 | O27: =IFERROR((VLOOKUP($A27,'Dados StatusInvest'!$A:$AZ,COLUMN(O27)-$A$5,0)/VLOOKUP($A27,'Dados StatusInvest'!$A:$AZ,2,0)*$F27),0) -> 0 | P27: =IFERROR((VLOOKUP($A27,'Dados StatusInvest'!$A:$AZ,COLUMN(P27)-$A$5,0)/VLOOKUP($A27,'Dados StatusInvest'!$A:$AZ,2,0)*$F27),0) -> 0 | Q27: =IFERROR((VLOOKUP($A27,'Dados StatusInvest'!$A:$AZ,COLUMN(Q27)-$A$5,0)/100),0) -> 0.0274 | R27: =VLOOKUP($A27,'Dados StatusInvest'!$A:$AZ,COLUMN(R27)-$A$5,0) -> 0.14 | S27: =IFERROR((VLOOKUP($A27,'Dados StatusInvest'!$A:$AZ,COLUMN(S27)-$A$5,0)),0) -> 2.68 | T27: =IFERROR((VLOOKUP($A27,'Dados StatusInvest'!$A:$AZ,COLUMN(T27)-$A$5,0)/VLOOKUP($A27,'Dados StatusInvest'!$A:$AZ,2,0)*$F27),0) -> 0 | U27: =IFERROR((VLOOKUP($A27,'Dados StatusInvest'!$A:$AZ,COLUMN(U27)-$A$5,0)-VLOOKUP($A27,'Dados StatusInvest'!$A:$AZ,COLUMN(U27)-$A$5-1,0)+T27),0) -> -116.66 | V27: =IFERROR((VLOOKUP($A27,'Dados StatusInvest'!$A:$AZ,COLUMN(V27)-$A$5,0)),0) -> 1.03 | W27: =IFERROR((VLOOKUP($A27,'Dados StatusInvest'!$A:$AZ,COLUMN(W27)-$A$5,0)),0) -> -6.15 | X27: =IFERROR((VLOOKUP($A27,'Dados StatusInvest'!$A:$AZ,COLUMN(X27)-$A$5,0)/VLOOKUP($A27,'Dados StatusInvest'!$A:$AZ,2,0)*$F27),0) -> 0 | Y27: =IFERROR((VLOOKUP($A27,'Dados StatusInvest'!$A:$AZ,COLUMN(Y27)-$A$5,0)/VLOOKUP($A27,'Dados StatusInvest'!$A:$AZ,2,0)*$F27),0) -> 0 | Z27: =IFERROR((VLOOKUP($A27,'Dados StatusInvest'!$A:$AZ,COLUMN(Z27)-$A$5,0)),0) -> 0.5 | AA27: =IFERROR((VLOOKUP($A27,'Dados StatusInvest'!$A:$AZ,COLUMN(AA27)-$A$5,0)),0) -> 0.5 | AB27: =IFERROR((VLOOKUP($A27,'Dados StatusInvest'!$A:$AZ,COLUMN(AB27)-$A$5,0)),0) -> 0.38 | AC27: =IFERROR((VLOOKUP($A27,'Dados StatusInvest'!$A:$AZ,COLUMN(AC27)-$A$5,0)),0) -> 29.52 | AD27: =IFERROR((VLOOKUP($A27,'Dados StatusInvest'!$A:$AZ,COLUMN(AD27)-$A$5,0)),0) -> 0 | AE27: =IFERROR((VLOOKUP($A27,'Dados StatusInvest'!$A:$AZ,COLUMN(AE27)-$A$5,0)),0) -> 51166 | AF27: =IFERROR((VLOOKUP($A27,'Dados StatusInvest'!$A:$AZ,COLUMN(AF27)-$A$5,0)),0) -> 23.16 | AG27: =IFERROR((VLOOKUP($A27,'Dados StatusInvest'!$A:$AZ,COLUMN(AG27)-$A$5,0)),0) -> -1.42 | ... AJ27: =IFERROR((VLOOKUP($A27,'Dados StatusInvest'!$A:$AZ,COLUMN(AJ27)-$A$5,0)),0) | AK27: =IFERROR(__xludf.DUMMYFUNCTION("IFERROR(GOOGLEFINANCE($A27,""high""),"""")"),"") | AL27: =IFERROR(__xludf.DUMMYFUNCTION("IFERROR(GOOGLEFINANCE($A27,""low""),"""")"),"") | AM27: =IFERROR(((AK27-AL27)/AL27),0) -> 0 | AN27: =IFERROR(__xludf.DUMMYFUNCTION("IFERROR((GOOGLEFINANCE($A27,""volume"")),0)"),0.0) -> 0 | AO27: =IFERROR(__xludf.DUMMYFUNCTION("IFERROR((GOOGLEFINANCE($A27,""closeyest"")),"""")"),"") | AP27: =IFERROR(__xludf.DUMMYFUNCTION("IFERROR((GOOGLEFINANCE($A27,""shares"")),"""")"),"")
A28: ='Dados StatusInvest'!A23:A642 -> APTI3 | B28: =IFERROR(__xludf.DUMMYFUNCTION("IFERROR((GOOGLEFINANCE(A28,""name"")),"""")"),"Siderurgica JL Aliperti SA") -> Siderurgica JL Aliperti SA | C28: =IFERROR((VLOOKUP(LEFT($A28,4),Setor!$A:$E,3,0)),"") -> Consumo não Cíclico | D28: =IFERROR((VLOOKUP(LEFT($A28,4),Setor!$A:$E,4,0)),"") -> Agropecuária | E28: =IFERROR((VLOOKUP(LEFT($A28,4),Setor!$A:$E,5,0)),"") -> Agricultura | F28: =IFERROR(__xludf.DUMMYFUNCTION("IFERROR((GOOGLEFINANCE(A28)),"""")"),0.0) -> 0 | G28: =IFERROR(__xludf.DUMMYFUNCTION("IFERROR((sparkline(GOOGLEFINANCE($A28,""price"",TODAY()-30,TODAY(),""DAILY""),{""charttype"",""line"";""linewidth"",1;""color"",""#5f88cc""})),"""")"),"") | H28: =IFERROR(__xludf.DUMMYFUNCTION("IFERROR((((GOOGLEFINANCE(A28))-(INDEX(GoogleFinance(A28,""PRICE"",$AQ$1),2,2)))/(INDEX(GoogleFinance(A28,""PRICE"",$AQ$1),2,2))),"""")"),"") | I28: =IFERROR(__xludf.DUMMYFUNCTION("IFERROR((GOOGLEFINANCE($A28,""high52"")),"""")"),320.0) -> 320 | J28: =IFERROR(__xludf.DUMMYFUNCTION("IFERROR((sparkline(GOOGLEFINANCE($A28,""price"",TODAY()-365,TODAY(),""DAILY""),{""charttype"",""line"";""linewidth"",1;""color"",""#5f88cc""})),"""")"),"") | K28: =IFERROR(__xludf.DUMMYFUNCTION("IFERROR((((GOOGLEFINANCE(A28))-(INDEX(GoogleFinance(A28,""PRICE"",$AP$1),2,2)))/(INDEX(GoogleFinance(A28,""PRICE"",$AP$1),2,2))),"""")"),"") | L28: =IFERROR(((F28-I28)/I28),0) -> -1 | M28: =IFERROR((VLOOKUP($A28,'Dados StatusInvest'!$A:$AZ,COLUMN(M28)-$A$5,0)*VLOOKUP($A28,'Dados StatusInvest'!$A:$AZ,2,0)/$F28/100),0) -> 0 | N28: =IFERROR((VLOOKUP($A28,'Dados StatusInvest'!$A:$AZ,COLUMN(N28)-$A$5,0)/VLOOKUP($A28,'Dados StatusInvest'!$A:$AZ,2,0)*$F28),"") -> 0 | O28: =IFERROR((VLOOKUP($A28,'Dados StatusInvest'!$A:$AZ,COLUMN(O28)-$A$5,0)/VLOOKUP($A28,'Dados StatusInvest'!$A:$AZ,2,0)*$F28),0) -> 0 | P28: =IFERROR((VLOOKUP($A28,'Dados StatusInvest'!$A:$AZ,COLUMN(P28)-$A$5,0)/VLOOKUP($A28,'Dados StatusInvest'!$A:$AZ,2,0)*$F28),0) -> 0 | Q28: =IFERROR((VLOOKUP($A28,'Dados StatusInvest'!$A:$AZ,COLUMN(Q28)-$A$5,0)/100),0) -> -0.0142 | R28: =VLOOKUP($A28,'Dados StatusInvest'!$A:$AZ,COLUMN(R28)-$A$5,0) -> -0.09 | S28: =IFERROR((VLOOKUP($A28,'Dados StatusInvest'!$A:$AZ,COLUMN(S28)-$A$5,0)),0) -> 0.1 | T28: =IFERROR((VLOOKUP($A28,'Dados StatusInvest'!$A:$AZ,COLUMN(T28)-$A$5,0)/VLOOKUP($A28,'Dados StatusInvest'!$A:$AZ,2,0)*$F28),0) -> 0 | U28: =IFERROR((VLOOKUP($A28,'Dados StatusInvest'!$A:$AZ,COLUMN(U28)-$A$5,0)-VLOOKUP($A28,'Dados StatusInvest'!$A:$AZ,COLUMN(U28)-$A$5-1,0)+T28),0) -> -0.03 | V28: =IFERROR((VLOOKUP($A28,'Dados StatusInvest'!$A:$AZ,COLUMN(V28)-$A$5,0)),0) -> 10.57 | W28: =IFERROR((VLOOKUP($A28,'Dados StatusInvest'!$A:$AZ,COLUMN(W28)-$A$5,0)),0) -> 10.94 | X28: =IFERROR((VLOOKUP($A28,'Dados StatusInvest'!$A:$AZ,COLUMN(X28)-$A$5,0)/VLOOKUP($A28,'Dados StatusInvest'!$A:$AZ,2,0)*$F28),0) -> 0 | Y28: =IFERROR((VLOOKUP($A28,'Dados StatusInvest'!$A:$AZ,COLUMN(Y28)-$A$5,0)/VLOOKUP($A28,'Dados StatusInvest'!$A:$AZ,2,0)*$F28),0) -> 0 | Z28: =IFERROR((VLOOKUP($A28,'Dados StatusInvest'!$A:$AZ,COLUMN(Z28)-$A$5,0)),0) -> 0.54 | AA28: =IFERROR((VLOOKUP($A28,'Dados StatusInvest'!$A:$AZ,COLUMN(AA28)-$A$5,0)),0) -> 0.46 | AB28: =IFERROR((VLOOKUP($A28,'Dados StatusInvest'!$A:$AZ,COLUMN(AB28)-$A$5,0)),0) -> 0.07 | AC28: =IFERROR((VLOOKUP($A28,'Dados StatusInvest'!$A:$AZ,COLUMN(AC28)-$A$5,0)),0) -> -2.98 | AD28: =IFERROR((VLOOKUP($A28,'Dados StatusInvest'!$A:$AZ,COLUMN(AD28)-$A$5,0)),0) -> 0 | AE28: =IFERROR((VLOOKUP($A28,'Dados StatusInvest'!$A:$AZ,COLUMN(AE28)-$A$5,0)),0) -> 0 | AF28: =IFERROR((VLOOKUP($A28,'Dados StatusInvest'!$A:$AZ,COLUMN(AF28)-$A$5,0)),0) -> 14822.32 | AG28: =IFERROR((VLOOKUP($A28,'Dados StatusInvest'!$A:$AZ,COLUMN(AG28)-$A$5,0)),0) -> 1621.94 | ... AJ28: =IFERROR((VLOOKUP($A28,'Dados StatusInvest'!$A:$AZ,COLUMN(AJ28)-$A$5,0)),0) | AK28: =IFERROR(__xludf.DUMMYFUNCTION("IFERROR(GOOGLEFINANCE($A28,""high""),"""")"),"") | AL28: =IFERROR(__xludf.DUMMYFUNCTION("IFERROR(GOOGLEFINANCE($A28,""low""),"""")"),"") | AM28: =IFERROR(((AK28-AL28)/AL28),0) -> 0 | AN28: =IFERROR(__xludf.DUMMYFUNCTION("IFERROR((GOOGLEFINANCE($A28,""volume"")),0)"),0.0) -> 0 | AO28: =IFERROR(__xludf.DUMMYFUNCTION("IFERROR((GOOGLEFINANCE($A28,""closeyest"")),"""")"),"") | AP28: =IFERROR(__xludf.DUMMYFUNCTION("IFERROR((GOOGLEFINANCE($A28,""shares"")),"""")"),6250.0) -> 6250
A29: ='Dados StatusInvest'!A24:A643 -> APTI4 | B29: =IFERROR(__xludf.DUMMYFUNCTION("IFERROR((GOOGLEFINANCE(A29,""name"")),"""")"),"Siderurgica JL Aliperti SA Preference Shares") -> Siderurgica JL Aliperti SA Preference Shares | C29: =IFERROR((VLOOKUP(LEFT($A29,4),Setor!$A:$E,3,0)),"") -> Consumo não Cíclico | D29: =IFERROR((VLOOKUP(LEFT($A29,4),Setor!$A:$E,4,0)),"") -> Agropecuária | E29: =IFERROR((VLOOKUP(LEFT($A29,4),Setor!$A:$E,5,0)),"") -> Agricultura | F29: =IFERROR(__xludf.DUMMYFUNCTION("IFERROR((GOOGLEFINANCE(A29)),"""")"),0.0) -> 0 | G29: =IFERROR(__xludf.DUMMYFUNCTION("IFERROR((sparkline(GOOGLEFINANCE($A29,""price"",TODAY()-30,TODAY(),""DAILY""),{""charttype"",""line"";""linewidth"",1;""color"",""#5f88cc""})),"""")"),"") | H29: =IFERROR(__xludf.DUMMYFUNCTION("IFERROR((((GOOGLEFINANCE(A29))-(INDEX(GoogleFinance(A29,""PRICE"",$AQ$1),2,2)))/(INDEX(GoogleFinance(A29,""PRICE"",$AQ$1),2,2))),"""")"),"") | I29: =IFERROR(__xludf.DUMMYFUNCTION("IFERROR((GOOGLEFINANCE($A29,""high52"")),"""")"),3500.0) -> 3500 | J29: =IFERROR(__xludf.DUMMYFUNCTION("IFERROR((sparkline(GOOGLEFINANCE($A29,""price"",TODAY()-365,TODAY(),""DAILY""),{""charttype"",""line"";""linewidth"",1;""color"",""#5f88cc""})),"""")"),"") | K29: =IFERROR(__xludf.DUMMYFUNCTION("IFERROR((((GOOGLEFINANCE(A29))-(INDEX(GoogleFinance(A29,""PRICE"",$AP$1),2,2)))/(INDEX(GoogleFinance(A29,""PRICE"",$AP$1),2,2))),"""")"),"") | L29: =IFERROR(((F29-I29)/I29),0) -> -1 | M29: =IFERROR((VLOOKUP($A29,'Dados StatusInvest'!$A:$AZ,COLUMN(M29)-$A$5,0)*VLOOKUP($A29,'Dados StatusInvest'!$A:$AZ,2,0)/$F29/100),0) -> 0 | N29: =IFERROR((VLOOKUP($A29,'Dados StatusInvest'!$A:$AZ,COLUMN(N29)-$A$5,0)/VLOOKUP($A29,'Dados StatusInvest'!$A:$AZ,2,0)*$F29),"") -> 0 | O29: =IFERROR((VLOOKUP($A29,'Dados StatusInvest'!$A:$AZ,COLUMN(O29)-$A$5,0)/VLOOKUP($A29,'Dados StatusInvest'!$A:$AZ,2,0)*$F29),0) -> 0 | P29: =IFERROR((VLOOKUP($A29,'Dados StatusInvest'!$A:$AZ,COLUMN(P29)-$A$5,0)/VLOOKUP($A29,'Dados StatusInvest'!$A:$AZ,2,0)*$F29),0) -> 0 | Q29: =IFERROR((VLOOKUP($A29,'Dados StatusInvest'!$A:$AZ,COLUMN(Q29)-$A$5,0)/100),0) -> -0.0142 | R29: =VLOOKUP($A29,'Dados StatusInvest'!$A:$AZ,COLUMN(R29)-$A$5,0) -> -0.09 | S29: =IFERROR((VLOOKUP($A29,'Dados StatusInvest'!$A:$AZ,COLUMN(S29)-$A$5,0)),0) -> 1.47 | T29: =IFERROR((VLOOKUP($A29,'Dados StatusInvest'!$A:$AZ,COLUMN(T29)-$A$5,0)/VLOOKUP($A29,'Dados StatusInvest'!$A:$AZ,2,0)*$F29),0) -> 0 | U29: =IFERROR((VLOOKUP($A29,'Dados StatusInvest'!$A:$AZ,COLUMN(U29)-$A$5,0)-VLOOKUP($A29,'Dados StatusInvest'!$A:$AZ,COLUMN(U29)-$A$5-1,0)+T29),0) -> -0.45 | V29: =IFERROR((VLOOKUP($A29,'Dados StatusInvest'!$A:$AZ,COLUMN(V29)-$A$5,0)),0) -> 10.57 | W29: =IFERROR((VLOOKUP($A29,'Dados StatusInvest'!$A:$AZ,COLUMN(W29)-$A$5,0)),0) -> 10.94 | X29: =IFERROR((VLOOKUP($A29,'Dados StatusInvest'!$A:$AZ,COLUMN(X29)-$A$5,0)/VLOOKUP($A29,'Dados StatusInvest'!$A:$AZ,2,0)*$F29),0) -> 0 | Y29: =IFERROR((VLOOKUP($A29,'Dados StatusInvest'!$A:$AZ,COLUMN(Y29)-$A$5,0)/VLOOKUP($A29,'Dados StatusInvest'!$A:$AZ,2,0)*$F29),0) -> 0 | Z29: =IFERROR((VLOOKUP($A29,'Dados StatusInvest'!$A:$AZ,COLUMN(Z29)-$A$5,0)),0) -> 0.54 | AA29: =IFERROR((VLOOKUP($A29,'Dados StatusInvest'!$A:$AZ,COLUMN(AA29)-$A$5,0)),0) -> 0.46 | AB29: =IFERROR((VLOOKUP($A29,'Dados StatusInvest'!$A:$AZ,COLUMN(AB29)-$A$5,0)),0) -> 0.07 | AC29: =IFERROR((VLOOKUP($A29,'Dados StatusInvest'!$A:$AZ,COLUMN(AC29)-$A$5,0)),0) -> -2.98 | AD29: =IFERROR((VLOOKUP($A29,'Dados StatusInvest'!$A:$AZ,COLUMN(AD29)-$A$5,0)),0) -> 0 | AE29: =IFERROR((VLOOKUP($A29,'Dados StatusInvest'!$A:$AZ,COLUMN(AE29)-$A$5,0)),0) -> 0 | AF29: =IFERROR((VLOOKUP($A29,'Dados StatusInvest'!$A:$AZ,COLUMN(AF29)-$A$5,0)),0) -> 14822.32 | AG29: =IFERROR((VLOOKUP($A29,'Dados StatusInvest'!$A:$AZ,COLUMN(AG29)-$A$5,0)),0) -> 1621.94 | ... AJ29: =IFERROR((VLOOKUP($A29,'Dados StatusInvest'!$A:$AZ,COLUMN(AJ29)-$A$5,0)),0) | AK29: =IFERROR(__xludf.DUMMYFUNCTION("IFERROR(GOOGLEFINANCE($A29,""high""),"""")"),"") | AL29: =IFERROR(__xludf.DUMMYFUNCTION("IFERROR(GOOGLEFINANCE($A29,""low""),"""")"),"") | AM29: =IFERROR(((AK29-AL29)/AL29),0) -> 0 | AN29: =IFERROR(__xludf.DUMMYFUNCTION("IFERROR((GOOGLEFINANCE($A29,""volume"")),0)"),0.0) -> 0 | AO29: =IFERROR(__xludf.DUMMYFUNCTION("IFERROR((GOOGLEFINANCE($A29,""closeyest"")),"""")"),140.22) -> 140.22 | AP29: =IFERROR(__xludf.DUMMYFUNCTION("IFERROR((GOOGLEFINANCE($A29,""shares"")),"""")"),12345.0) -> 12345
A30: ='Dados StatusInvest'!A25:A644 -> ARML3 | B30: =IFERROR(__xludf.DUMMYFUNCTION("IFERROR((GOOGLEFINANCE(A30,""name"")),"""")"),"Armac Locacao Logistica e Servicos SA") -> Armac Locacao Logistica e Servicos SA | C30: =IFERROR((VLOOKUP(LEFT($A30,4),Setor!$A:$E,3,0)),"") -> Outros | D30: =IFERROR((VLOOKUP(LEFT($A30,4),Setor!$A:$E,4,0)),"") -> Transporte | E30: =IFERROR((VLOOKUP(LEFT($A30,4),Setor!$A:$E,5,0)),"") -> Exploração de Rodovias | F30: =IFERROR(__xludf.DUMMYFUNCTION("IFERROR((GOOGLEFINANCE(A30)),"""")"),5.52) -> 5.52 | G30: =IFERROR(__xludf.DUMMYFUNCTION("IFERROR((sparkline(GOOGLEFINANCE($A30,""price"",TODAY()-30,TODAY(),""DAILY""),{""charttype"",""line"";""linewidth"",1;""color"",""#5f88cc""})),"""")"),"") | H30: =IFERROR(__xludf.DUMMYFUNCTION("IFERROR((((GOOGLEFINANCE(A30))-(INDEX(GoogleFinance(A30,""PRICE"",$AQ$1),2,2)))/(INDEX(GoogleFinance(A30,""PRICE"",$AQ$1),2,2))),"""")"),0.2748267898383371) -> 0.27482679 | I30: =IFERROR(__xludf.DUMMYFUNCTION("IFERROR((GOOGLEFINANCE($A30,""high52"")),"""")"),5.66) -> 5.66 | J30: =IFERROR(__xludf.DUMMYFUNCTION("IFERROR((sparkline(GOOGLEFINANCE($A30,""price"",TODAY()-365,TODAY(),""DAILY""),{""charttype"",""line"";""linewidth"",1;""color"",""#5f88cc""})),"""")"),"") | K30: =IFERROR(__xludf.DUMMYFUNCTION("IFERROR((((GOOGLEFINANCE(A30))-(INDEX(GoogleFinance(A30,""PRICE"",$AP$1),2,2)))/(INDEX(GoogleFinance(A30,""PRICE"",$AP$1),2,2))),"""")"),0.21318681318681315) -> 0.21318681 | L30: =IFERROR(((F30-I30)/I30),0) -> -0.024734982 | M30: =IFERROR((VLOOKUP($A30,'Dados StatusInvest'!$A:$AZ,COLUMN(M30)-$A$5,0)*VLOOKUP($A30,'Dados StatusInvest'!$A:$AZ,2,0)/$F30/100),0) -> 0.22421268 | N30: =IFERROR((VLOOKUP($A30,'Dados StatusInvest'!$A:$AZ,COLUMN(N30)-$A$5,0)/VLOOKUP($A30,'Dados StatusInvest'!$A:$AZ,2,0)*$F30),"") -> 2.8838779 | O30: =IFERROR((VLOOKUP($A30,'Dados StatusInvest'!$A:$AZ,COLUMN(O30)-$A$5,0)/VLOOKUP($A30,'Dados StatusInvest'!$A:$AZ,2,0)*$F30),0) -> 4.628079 | P30: =IFERROR((VLOOKUP($A30,'Dados StatusInvest'!$A:$AZ,COLUMN(P30)-$A$5,0)/VLOOKUP($A30,'Dados StatusInvest'!$A:$AZ,2,0)*$F30),0) -> 9.1174147 | Q30: =IFERROR((VLOOKUP($A30,'Dados StatusInvest'!$A:$AZ,COLUMN(Q30)-$A$5,0)/100),0) -> 0.0453 | R30: =VLOOKUP($A30,'Dados StatusInvest'!$A:$AZ,COLUMN(R30)-$A$5,0) -> 1.47 | S30: =IFERROR((VLOOKUP($A30,'Dados StatusInvest'!$A:$AZ,COLUMN(S30)-$A$5,0)),0) -> 1.04 | T30: =IFERROR((VLOOKUP($A30,'Dados StatusInvest'!$A:$AZ,COLUMN(T30)-$A$5,0)/VLOOKUP($A30,'Dados StatusInvest'!$A:$AZ,2,0)*$F30),0) -> 2.5171993 | U30: =IFERROR((VLOOKUP($A30,'Dados StatusInvest'!$A:$AZ,COLUMN(U30)-$A$5,0)-VLOOKUP($A30,'Dados StatusInvest'!$A:$AZ,COLUMN(U30)-$A$5-1,0)+T30),0) -> -0.61280072 | V30: =IFERROR((VLOOKUP($A30,'Dados StatusInvest'!$A:$AZ,COLUMN(V30)-$A$5,0)),0) -> 2.21 | W30: =IFERROR((VLOOKUP($A30,'Dados StatusInvest'!$A:$AZ,COLUMN(W30)-$A$5,0)),0) -> 4.26 | X30: =IFERROR((VLOOKUP($A30,'Dados StatusInvest'!$A:$AZ,COLUMN(X30)-$A$5,0)/VLOOKUP($A30,'Dados StatusInvest'!$A:$AZ,2,0)*$F30),0) -> 1.1594973 | Y30: =IFERROR((VLOOKUP($A30,'Dados StatusInvest'!$A:$AZ,COLUMN(Y30)-$A$5,0)/VLOOKUP($A30,'Dados StatusInvest'!$A:$AZ,2,0)*$F30),0) -> 10.356194 | Z30: =IFERROR((VLOOKUP($A30,'Dados StatusInvest'!$A:$AZ,COLUMN(Z30)-$A$5,0)),0) -> 0.27 | AA30: =IFERROR((VLOOKUP($A30,'Dados StatusInvest'!$A:$AZ,COLUMN(AA30)-$A$5,0)),0) -> 0.72 | AB30: =IFERROR((VLOOKUP($A30,'Dados StatusInvest'!$A:$AZ,COLUMN(AB30)-$A$5,0)),0) -> 0.4 | AC30: =IFERROR((VLOOKUP($A30,'Dados StatusInvest'!$A:$AZ,COLUMN(AC30)-$A$5,0)),0) -> 95.79 | AD30: =IFERROR((VLOOKUP($A30,'Dados StatusInvest'!$A:$AZ,COLUMN(AD30)-$A$5,0)),0) -> 42.68 | AE30: =IFERROR((VLOOKUP($A30,'Dados StatusInvest'!$A:$AZ,COLUMN(AE30)-$A$5,0)),0) -> 4126765 | AF30: =IFERROR((VLOOKUP($A30,'Dados StatusInvest'!$A:$AZ,COLUMN(AF30)-$A$5,0)),0) -> 3.67 | AG30: =IFERROR((VLOOKUP($A30,'Dados StatusInvest'!$A:$AZ,COLUMN(AG30)-$A$5,0)),0) -> 0.16 | ... AJ30: =IFERROR((VLOOKUP($A30,'Dados StatusInvest'!$A:$AZ,COLUMN(AJ30)-$A$5,0)),0) | AK30: =IFERROR(__xludf.DUMMYFUNCTION("IFERROR(GOOGLEFINANCE($A30,""high""),"""")"),5.56) -> 5.56 | AL30: =IFERROR(__xludf.DUMMYFUNCTION("IFERROR(GOOGLEFINANCE($A30,""low""),"""")"),5.49) -> 5.49 | AM30: =IFERROR(((AK30-AL30)/AL30),0) -> 0.012750455 | AN30: =IFERROR(__xludf.DUMMYFUNCTION("IFERROR((GOOGLEFINANCE($A30,""volume"")),0)"),13400.0) -> 13400 | AO30: =IFERROR(__xludf.DUMMYFUNCTION("IFERROR((GOOGLEFINANCE($A30,""closeyest"")),"""")"),5.57) -> 5.57 | AP30: =IFERROR(__xludf.DUMMYFUNCTION("IFERROR((GOOGLEFINANCE($A30,""shares"")),"""")"),3.46494097E8) -> 346494097
A31: ='Dados StatusInvest'!A26:A645 -> ARND3 | B31: =IFERROR(__xludf.DUMMYFUNCTION("IFERROR((GOOGLEFINANCE(A31,""name"")),"""")"),"Arandu Investimentos SA") -> Arandu Investimentos SA | C31: =IFERROR((VLOOKUP(LEFT($A31,4),Setor!$A:$E,3,0)),"") | D31: =IFERROR((VLOOKUP(LEFT($A31,4),Setor!$A:$E,4,0)),"") | E31: =IFERROR((VLOOKUP(LEFT($A31,4),Setor!$A:$E,5,0)),"") | F31: =IFERROR(__xludf.DUMMYFUNCTION("IFERROR((GOOGLEFINANCE(A31)),"""")"),0.8) -> 0.8 | G31: =IFERROR(__xludf.DUMMYFUNCTION("IFERROR((sparkline(GOOGLEFINANCE($A31,""price"",TODAY()-30,TODAY(),""DAILY""),{""charttype"",""line"";""linewidth"",1;""color"",""#5f88cc""})),"""")"),"") | H31: =IFERROR(__xludf.DUMMYFUNCTION("IFERROR((((GOOGLEFINANCE(A31))-(INDEX(GoogleFinance(A31,""PRICE"",$AQ$1),2,2)))/(INDEX(GoogleFinance(A31,""PRICE"",$AQ$1),2,2))),"""")"),-0.08045977011494247) -> -0.08045977 | I31: =IFERROR(__xludf.DUMMYFUNCTION("IFERROR((GOOGLEFINANCE($A31,""high52"")),"""")"),1.58) -> 1.58 | J31: =IFERROR(__xludf.DUMMYFUNCTION("IFERROR((sparkline(GOOGLEFINANCE($A31,""price"",TODAY()-365,TODAY(),""DAILY""),{""charttype"",""line"";""linewidth"",1;""color"",""#5f88cc""})),"""")"),"") | K31: =IFERROR(__xludf.DUMMYFUNCTION("IFERROR((((GOOGLEFINANCE(A31))-(INDEX(GoogleFinance(A31,""PRICE"",$AP$1),2,2)))/(INDEX(GoogleFinance(A31,""PRICE"",$AP$1),2,2))),"""")"),-0.8545454545454546) -> -0.85454545 | L31: =IFERROR(((F31-I31)/I31),0) -> -0.49367089 | M31: =IFERROR((VLOOKUP($A31,'Dados StatusInvest'!$A:$AZ,COLUMN(M31)-$A$5,0)*VLOOKUP($A31,'Dados StatusInvest'!$A:$AZ,2,0)/$F31/100),0) -> -0.6173 | N31: =IFERROR((VLOOKUP($A31,'Dados StatusInvest'!$A:$AZ,COLUMN(N31)-$A$5,0)/VLOOKUP($A31,'Dados StatusInvest'!$A:$AZ,2,0)*$F31),"") -> 56.03 | O31: =IFERROR((VLOOKUP($A31,'Dados StatusInvest'!$A:$AZ,COLUMN(O31)-$A$5,0)/VLOOKUP($A31,'Dados StatusInvest'!$A:$AZ,2,0)*$F31),0) -> -3.04 | P31: =IFERROR((VLOOKUP($A31,'Dados StatusInvest'!$A:$AZ,COLUMN(P31)-$A$5,0)/VLOOKUP($A31,'Dados StatusInvest'!$A:$AZ,2,0)*$F31),0) -> 2.5 | Q31: =IFERROR((VLOOKUP($A31,'Dados StatusInvest'!$A:$AZ,COLUMN(Q31)-$A$5,0)/100),0) -> 0.0554 | R31: =VLOOKUP($A31,'Dados StatusInvest'!$A:$AZ,COLUMN(R31)-$A$5,0) -> -0.67 | S31: =IFERROR((VLOOKUP($A31,'Dados StatusInvest'!$A:$AZ,COLUMN(S31)-$A$5,0)),0) -> 1.88 | T31: =IFERROR((VLOOKUP($A31,'Dados StatusInvest'!$A:$AZ,COLUMN(T31)-$A$5,0)/VLOOKUP($A31,'Dados StatusInvest'!$A:$AZ,2,0)*$F31),0) -> 0.41 | U31: =IFERROR((VLOOKUP($A31,'Dados StatusInvest'!$A:$AZ,COLUMN(U31)-$A$5,0)-VLOOKUP($A31,'Dados StatusInvest'!$A:$AZ,COLUMN(U31)-$A$5-1,0)+T31),0) -> -3.27 | V31: =IFERROR((VLOOKUP($A31,'Dados StatusInvest'!$A:$AZ,COLUMN(V31)-$A$5,0)),0) -> 1.34 | W31: =IFERROR((VLOOKUP($A31,'Dados StatusInvest'!$A:$AZ,COLUMN(W31)-$A$5,0)),0) -> 10.95 | X31: =IFERROR((VLOOKUP($A31,'Dados StatusInvest'!$A:$AZ,COLUMN(X31)-$A$5,0)/VLOOKUP($A31,'Dados StatusInvest'!$A:$AZ,2,0)*$F31),0) -> 3.02 | Y31: =IFERROR((VLOOKUP($A31,'Dados StatusInvest'!$A:$AZ,COLUMN(Y31)-$A$5,0)/VLOOKUP($A31,'Dados StatusInvest'!$A:$AZ,2,0)*$F31),0) -> -17.48 | Z31: =IFERROR((VLOOKUP($A31,'Dados StatusInvest'!$A:$AZ,COLUMN(Z31)-$A$5,0)),0) -> 0.28 | AA31: =IFERROR((VLOOKUP($A31,'Dados StatusInvest'!$A:$AZ,COLUMN(AA31)-$A$5,0)),0) -> 0.72 | AB31: =IFERROR((VLOOKUP($A31,'Dados StatusInvest'!$A:$AZ,COLUMN(AB31)-$A$5,0)),0) -> 0.05 | AC31: =IFERROR((VLOOKUP($A31,'Dados StatusInvest'!$A:$AZ,COLUMN(AC31)-$A$5,0)),0) -> 22.22 | AD31: =IFERROR((VLOOKUP($A31,'Dados StatusInvest'!$A:$AZ,COLUMN(AD31)-$A$5,0)),0) -> 0 | AE31: =IFERROR((VLOOKUP($A31,'Dados StatusInvest'!$A:$AZ,COLUMN(AE31)-$A$5,0)),0) -> 956.45 | AF31: =IFERROR((VLOOKUP($A31,'Dados StatusInvest'!$A:$AZ,COLUMN(AF31)-$A$5,0)),0) -> 2.18 | AG31: =IFERROR((VLOOKUP($A31,'Dados StatusInvest'!$A:$AZ,COLUMN(AG31)-$A$5,0)),0) -> 0.24 | ... AJ31: =IFERROR((VLOOKUP($A31,'Dados StatusInvest'!$A:$AZ,COLUMN(AJ31)-$A$5,0)),0) | AK31: =IFERROR(__xludf.DUMMYFUNCTION("IFERROR(GOOGLEFINANCE($A31,""high""),"""")"),"") | AL31: =IFERROR(__xludf.DUMMYFUNCTION("IFERROR(GOOGLEFINANCE($A31,""low""),"""")"),"") | AM31: =IFERROR(((AK31-AL31)/AL31),0) -> 0 | AN31: =IFERROR(__xludf.DUMMYFUNCTION("IFERROR((GOOGLEFINANCE($A31,""volume"")),0)"),0.0) -> 0 | AO31: =IFERROR(__xludf.DUMMYFUNCTION("IFERROR((GOOGLEFINANCE($A31,""closeyest"")),"""")"),0.8) -> 0.8 | AP31: =IFERROR(__xludf.DUMMYFUNCTION("IFERROR((GOOGLEFINANCE($A31,""shares"")),"""")"),1.40991806E8) -> 140991806
A32: ='Dados StatusInvest'!A27:A646 -> ASAI3 | B32: =IFERROR(__xludf.DUMMYFUNCTION("IFERROR((GOOGLEFINANCE(A32,""name"")),"""")"),"Sendas Distribuidora SA") -> Sendas Distribuidora SA | C32: =IFERROR((VLOOKUP(LEFT($A32,4),Setor!$A:$E,3,0)),"") -> Consumo Cíclico | D32: =IFERROR((VLOOKUP(LEFT($A32,4),Setor!$A:$E,4,0)),"") -> Comércio | E32: =IFERROR((VLOOKUP(LEFT($A32,4),Setor!$A:$E,5,0)),"") -> Alimentos | F32: =IFERROR(__xludf.DUMMYFUNCTION("IFERROR((GOOGLEFINANCE(A32)),"""")"),9.48) -> 9.48 | G32: =IFERROR(__xludf.DUMMYFUNCTION("IFERROR((sparkline(GOOGLEFINANCE($A32,""price"",TODAY()-30,TODAY(),""DAILY""),{""charttype"",""line"";""linewidth"",1;""color"",""#5f88cc""})),"""")"),"") | H32: =IFERROR(__xludf.DUMMYFUNCTION("IFERROR((((GOOGLEFINANCE(A32))-(INDEX(GoogleFinance(A32,""PRICE"",$AQ$1),2,2)))/(INDEX(GoogleFinance(A32,""PRICE"",$AQ$1),2,2))),"""")"),0.22797927461139905) -> 0.22797927 | I32: =IFERROR(__xludf.DUMMYFUNCTION("IFERROR((GOOGLEFINANCE($A32,""high52"")),"""")"),11.88) -> 11.88 | J32: =IFERROR(__xludf.DUMMYFUNCTION("IFERROR((sparkline(GOOGLEFINANCE($A32,""price"",TODAY()-365,TODAY(),""DAILY""),{""charttype"",""line"";""linewidth"",1;""color"",""#5f88cc""})),"""")"),"") | K32: =IFERROR(__xludf.DUMMYFUNCTION("IFERROR((((GOOGLEFINANCE(A32))-(INDEX(GoogleFinance(A32,""PRICE"",$AP$1),2,2)))/(INDEX(GoogleFinance(A32,""PRICE"",$AP$1),2,2))),"""")"),0.3581661891117478) -> 0.35816619 | L32: =IFERROR(((F32-I32)/I32),0) -> -0.2020202 | M32: =IFERROR((VLOOKUP($A32,'Dados StatusInvest'!$A:$AZ,COLUMN(M32)-$A$5,0)*VLOOKUP($A32,'Dados StatusInvest'!$A:$AZ,2,0)/$F32/100),0) -> 0.053786287 | N32: =IFERROR((VLOOKUP($A32,'Dados StatusInvest'!$A:$AZ,COLUMN(N32)-$A$5,0)/VLOOKUP($A32,'Dados StatusInvest'!$A:$AZ,2,0)*$F32),"") -> 1.202537 | O32: =IFERROR((VLOOKUP($A32,'Dados StatusInvest'!$A:$AZ,COLUMN(O32)-$A$5,0)/VLOOKUP($A32,'Dados StatusInvest'!$A:$AZ,2,0)*$F32),0) -> 3.1065539 | P32: =IFERROR((VLOOKUP($A32,'Dados StatusInvest'!$A:$AZ,COLUMN(P32)-$A$5,0)/VLOOKUP($A32,'Dados StatusInvest'!$A:$AZ,2,0)*$F32),0) -> 5.9726004 | Q32: =IFERROR((VLOOKUP($A32,'Dados StatusInvest'!$A:$AZ,COLUMN(Q32)-$A$5,0)/100),0) -> 0.0286 | R32: =VLOOKUP($A32,'Dados StatusInvest'!$A:$AZ,COLUMN(R32)-$A$5,0) -> 2.07 | S32: =IFERROR((VLOOKUP($A32,'Dados StatusInvest'!$A:$AZ,COLUMN(S32)-$A$5,0)),0) -> 0.17 | T32: =IFERROR((VLOOKUP($A32,'Dados StatusInvest'!$A:$AZ,COLUMN(T32)-$A$5,0)/VLOOKUP($A32,'Dados StatusInvest'!$A:$AZ,2,0)*$F32),0) -> 7.7864271 | U32: =IFERROR((VLOOKUP($A32,'Dados StatusInvest'!$A:$AZ,COLUMN(U32)-$A$5,0)-VLOOKUP($A32,'Dados StatusInvest'!$A:$AZ,COLUMN(U32)-$A$5-1,0)+T32),0) -> -0.42357294 | V32: =IFERROR((VLOOKUP($A32,'Dados StatusInvest'!$A:$AZ,COLUMN(V32)-$A$5,0)),0) -> 1.12 | W32: =IFERROR((VLOOKUP($A32,'Dados StatusInvest'!$A:$AZ,COLUMN(W32)-$A$5,0)),0) -> 16.05 | X32: =IFERROR((VLOOKUP($A32,'Dados StatusInvest'!$A:$AZ,COLUMN(X32)-$A$5,0)/VLOOKUP($A32,'Dados StatusInvest'!$A:$AZ,2,0)*$F32),0) -> 2.0342918 | Y32: =IFERROR((VLOOKUP($A32,'Dados StatusInvest'!$A:$AZ,COLUMN(Y32)-$A$5,0)/VLOOKUP($A32,'Dados StatusInvest'!$A:$AZ,2,0)*$F32),0) -> 18.619281 | Z32: =IFERROR((VLOOKUP($A32,'Dados StatusInvest'!$A:$AZ,COLUMN(Z32)-$A$5,0)),0) -> 0.13 | AA32: =IFERROR((VLOOKUP($A32,'Dados StatusInvest'!$A:$AZ,COLUMN(AA32)-$A$5,0)),0) -> 0.87 | AB32: =IFERROR((VLOOKUP($A32,'Dados StatusInvest'!$A:$AZ,COLUMN(AB32)-$A$5,0)),0) -> 1.7 | AC32: =IFERROR((VLOOKUP($A32,'Dados StatusInvest'!$A:$AZ,COLUMN(AC32)-$A$5,0)),0) -> 21.32 | AD32: =IFERROR((VLOOKUP($A32,'Dados StatusInvest'!$A:$AZ,COLUMN(AD32)-$A$5,0)),0) -> -2.6 | AE32: =IFERROR((VLOOKUP($A32,'Dados StatusInvest'!$A:$AZ,COLUMN(AE32)-$A$5,0)),0) -> 179000000 | AF32: =IFERROR((VLOOKUP($A32,'Dados StatusInvest'!$A:$AZ,COLUMN(AF32)-$A$5,0)),0) -> 4.23 | AG32: =IFERROR((VLOOKUP($A32,'Dados StatusInvest'!$A:$AZ,COLUMN(AG32)-$A$5,0)),0) -> 0.68 | ... AJ32: =IFERROR((VLOOKUP($A32,'Dados StatusInvest'!$A:$AZ,COLUMN(AJ32)-$A$5,0)),0) | AK32: =IFERROR(__xludf.DUMMYFUNCTION("IFERROR(GOOGLEFINANCE($A32,""high""),"""")"),9.54) -> 9.54 | AL32: =IFERROR(__xludf.DUMMYFUNCTION("IFERROR(GOOGLEFINANCE($A32,""low""),"""")"),9.28) -> 9.28 | AM32: =IFERROR(((AK32-AL32)/AL32),0) -> 0.028017241 | AN32: =IFERROR(__xludf.DUMMYFUNCTION("IFERROR((GOOGLEFINANCE($A32,""volume"")),0)"),736700.0) -> 736700 | AO32: =IFERROR(__xludf.DUMMYFUNCTION("IFERROR((GOOGLEFINANCE($A32,""closeyest"")),"""")"),9.46) -> 9.46 | AP32: =IFERROR(__xludf.DUMMYFUNCTION("IFERROR((GOOGLEFINANCE($A32,""shares"")),"""")"),1.35349695E9) -> 1353496950
A33: ='Dados StatusInvest'!A28:A647 -> AUAU3 | B33: =IFERROR(__xludf.DUMMYFUNCTION("IFERROR((GOOGLEFINANCE(A33,""name"")),"""")"),"Uniao Pet Participacoes SA") -> Uniao Pet Participacoes SA | C33: =IFERROR((VLOOKUP(LEFT($A33,4),Setor!$A:$E,3,0)),"") | D33: =IFERROR((VLOOKUP(LEFT($A33,4),Setor!$A:$E,4,0)),"") | E33: =IFERROR((VLOOKUP(LEFT($A33,4),Setor!$A:$E,5,0)),"") | F33: =IFERROR(__xludf.DUMMYFUNCTION("IFERROR((GOOGLEFINANCE(A33)),"""")"),3.09) -> 3.09 | G33: =IFERROR(__xludf.DUMMYFUNCTION("IFERROR((sparkline(GOOGLEFINANCE($A33,""price"",TODAY()-30,TODAY(),""DAILY""),{""charttype"",""line"";""linewidth"",1;""color"",""#5f88cc""})),"""")"),"") | H33: =IFERROR(__xludf.DUMMYFUNCTION("IFERROR((((GOOGLEFINANCE(A33))-(INDEX(GoogleFinance(A33,""PRICE"",$AQ$1),2,2)))/(INDEX(GoogleFinance(A33,""PRICE"",$AQ$1),2,2))),"""")"),-0.04923076923076927) -> -0.049230769 | I33: =IFERROR(__xludf.DUMMYFUNCTION("IFERROR((GOOGLEFINANCE($A33,""high52"")),"""")"),4.04) -> 4.04 | J33: =IFERROR(__xludf.DUMMYFUNCTION("IFERROR((sparkline(GOOGLEFINANCE($A33,""price"",TODAY()-365,TODAY(),""DAILY""),{""charttype"",""line"";""linewidth"",1;""color"",""#5f88cc""})),"""")"),"") | K33: =IFERROR(__xludf.DUMMYFUNCTION("IFERROR((((GOOGLEFINANCE(A33))-(INDEX(GoogleFinance(A33,""PRICE"",$AP$1),2,2)))/(INDEX(GoogleFinance(A33,""PRICE"",$AP$1),2,2))),"""")"),"") | L33: =IFERROR(((F33-I33)/I33),0) -> -0.23514851 | M33: =IFERROR((VLOOKUP($A33,'Dados StatusInvest'!$A:$AZ,COLUMN(M33)-$A$5,0)*VLOOKUP($A33,'Dados StatusInvest'!$A:$AZ,2,0)/$F33/100),0) -> 0 | N33: =IFERROR((VLOOKUP($A33,'Dados StatusInvest'!$A:$AZ,COLUMN(N33)-$A$5,0)/VLOOKUP($A33,'Dados StatusInvest'!$A:$AZ,2,0)*$F33),"") -> 0 | O33: =IFERROR((VLOOKUP($A33,'Dados StatusInvest'!$A:$AZ,COLUMN(O33)-$A$5,0)/VLOOKUP($A33,'Dados StatusInvest'!$A:$AZ,2,0)*$F33),0) -> 0 | P33: =IFERROR((VLOOKUP($A33,'Dados StatusInvest'!$A:$AZ,COLUMN(P33)-$A$5,0)/VLOOKUP($A33,'Dados StatusInvest'!$A:$AZ,2,0)*$F33),0) -> 0 | Q33: =IFERROR((VLOOKUP($A33,'Dados StatusInvest'!$A:$AZ,COLUMN(Q33)-$A$5,0)/100),0) -> 0 | R33: =VLOOKUP($A33,'Dados StatusInvest'!$A:$AZ,COLUMN(R33)-$A$5,0) -> 0 | S33: =IFERROR((VLOOKUP($A33,'Dados StatusInvest'!$A:$AZ,COLUMN(S33)-$A$5,0)),0) -> 0 | T33: =IFERROR((VLOOKUP($A33,'Dados StatusInvest'!$A:$AZ,COLUMN(T33)-$A$5,0)/VLOOKUP($A33,'Dados StatusInvest'!$A:$AZ,2,0)*$F33),0) -> 0 | U33: =IFERROR((VLOOKUP($A33,'Dados StatusInvest'!$A:$AZ,COLUMN(U33)-$A$5,0)-VLOOKUP($A33,'Dados StatusInvest'!$A:$AZ,COLUMN(U33)-$A$5-1,0)+T33),0) -> 0 | V33: =IFERROR((VLOOKUP($A33,'Dados StatusInvest'!$A:$AZ,COLUMN(V33)-$A$5,0)),0) -> 0 | W33: =IFERROR((VLOOKUP($A33,'Dados StatusInvest'!$A:$AZ,COLUMN(W33)-$A$5,0)),0) -> 0 | X33: =IFERROR((VLOOKUP($A33,'Dados StatusInvest'!$A:$AZ,COLUMN(X33)-$A$5,0)/VLOOKUP($A33,'Dados StatusInvest'!$A:$AZ,2,0)*$F33),0) -> 0 | Y33: =IFERROR((VLOOKUP($A33,'Dados StatusInvest'!$A:$AZ,COLUMN(Y33)-$A$5,0)/VLOOKUP($A33,'Dados StatusInvest'!$A:$AZ,2,0)*$F33),0) -> 0 | Z33: =IFERROR((VLOOKUP($A33,'Dados StatusInvest'!$A:$AZ,COLUMN(Z33)-$A$5,0)),0) -> 0 | AA33: =IFERROR((VLOOKUP($A33,'Dados StatusInvest'!$A:$AZ,COLUMN(AA33)-$A$5,0)),0) -> 0 | AB33: =IFERROR((VLOOKUP($A33,'Dados StatusInvest'!$A:$AZ,COLUMN(AB33)-$A$5,0)),0) -> 0 | AC33: =IFERROR((VLOOKUP($A33,'Dados StatusInvest'!$A:$AZ,COLUMN(AC33)-$A$5,0)),0) -> 0 | AD33: =IFERROR((VLOOKUP($A33,'Dados StatusInvest'!$A:$AZ,COLUMN(AD33)-$A$5,0)),0) -> 0 | AE33: =IFERROR((VLOOKUP($A33,'Dados StatusInvest'!$A:$AZ,COLUMN(AE33)-$A$5,0)),0) -> 14782120 | AF33: =IFERROR((VLOOKUP($A33,'Dados StatusInvest'!$A:$AZ,COLUMN(AF33)-$A$5,0)),0) -> 0 | AG33: =IFERROR((VLOOKUP($A33,'Dados StatusInvest'!$A:$AZ,COLUMN(AG33)-$A$5,0)),0) -> 0 | ... AJ33: =IFERROR((VLOOKUP($A33,'Dados StatusInvest'!$A:$AZ,COLUMN(AJ33)-$A$5,0)),0) | AK33: =IFERROR(__xludf.DUMMYFUNCTION("IFERROR(GOOGLEFINANCE($A33,""high""),"""")"),3.1) -> 3.1 | AL33: =IFERROR(__xludf.DUMMYFUNCTION("IFERROR(GOOGLEFINANCE($A33,""low""),"""")"),3.01) -> 3.01 | AM33: =IFERROR(((AK33-AL33)/AL33),0) -> 0.029900332 | AN33: =IFERROR(__xludf.DUMMYFUNCTION("IFERROR((GOOGLEFINANCE($A33,""volume"")),0)"),621000.0) -> 621000 | AO33: =IFERROR(__xludf.DUMMYFUNCTION("IFERROR((GOOGLEFINANCE($A33,""closeyest"")),"""")"),3.05) -> 3.05 | AP33: =IFERROR(__xludf.DUMMYFUNCTION("IFERROR((GOOGLEFINANCE($A33,""shares"")),"""")"),8.60793811E8) -> 860793811
A34: ='Dados StatusInvest'!A29:A648 -> AURA33 | B34: =IFERROR(__xludf.DUMMYFUNCTION("IFERROR((GOOGLEFINANCE(A34,""name"")),"""")"),"Aura Minerals Bdr") -> Aura Minerals Bdr | C34: =IFERROR((VLOOKUP(LEFT($A34,4),Setor!$A:$E,3,0)),"") -> Outros | D34: =IFERROR((VLOOKUP(LEFT($A34,4),Setor!$A:$E,4,0)),"") -> Mineração | E34: =IFERROR((VLOOKUP(LEFT($A34,4),Setor!$A:$E,5,0)),"") -> Minerais Metálicos | F34: =IFERROR(__xludf.DUMMYFUNCTION("IFERROR((GOOGLEFINANCE(A34)),"""")"),123.55) -> 123.55 | G34: =IFERROR(__xludf.DUMMYFUNCTION("IFERROR((sparkline(GOOGLEFINANCE($A34,""price"",TODAY()-30,TODAY(),""DAILY""),{""charttype"",""line"";""linewidth"",1;""color"",""#5f88cc""})),"""")"),"") | H34: =IFERROR(__xludf.DUMMYFUNCTION("IFERROR((((GOOGLEFINANCE(A34))-(INDEX(GoogleFinance(A34,""PRICE"",$AQ$1),2,2)))/(INDEX(GoogleFinance(A34,""PRICE"",$AQ$1),2,2))),"""")"),0.07025294525294525) -> 0.070252945 | I34: =IFERROR(__xludf.DUMMYFUNCTION("IFERROR((GOOGLEFINANCE($A34,""high52"")),"""")"),131.79) -> 131.79 | J34: =IFERROR(__xludf.DUMMYFUNCTION("IFERROR((sparkline(GOOGLEFINANCE($A34,""price"",TODAY()-365,TODAY(),""DAILY""),{""charttype"",""line"";""linewidth"",1;""color"",""#5f88cc""})),"""")"),"") | K34: =IFERROR(__xludf.DUMMYFUNCTION("IFERROR((((GOOGLEFINANCE(A34))-(INDEX(GoogleFinance(A34,""PRICE"",$AP$1),2,2)))/(INDEX(GoogleFinance(A34,""PRICE"",$AP$1),2,2))),"""")"),3.06280828674778) -> 3.0628083 | L34: =IFERROR(((F34-I34)/I34),0) -> -0.062523712 | M34: =IFERROR((VLOOKUP($A34,'Dados StatusInvest'!$A:$AZ,COLUMN(M34)-$A$5,0)*VLOOKUP($A34,'Dados StatusInvest'!$A:$AZ,2,0)/$F34/100),0) -> 0.45981028 | N34: =IFERROR((VLOOKUP($A34,'Dados StatusInvest'!$A:$AZ,COLUMN(N34)-$A$5,0)/VLOOKUP($A34,'Dados StatusInvest'!$A:$AZ,2,0)*$F34),"") -> -5.9084717 | O34: =IFERROR((VLOOKUP($A34,'Dados StatusInvest'!$A:$AZ,COLUMN(O34)-$A$5,0)/VLOOKUP($A34,'Dados StatusInvest'!$A:$AZ,2,0)*$F34),0) -> 13.126553 | P34: =IFERROR((VLOOKUP($A34,'Dados StatusInvest'!$A:$AZ,COLUMN(P34)-$A$5,0)/VLOOKUP($A34,'Dados StatusInvest'!$A:$AZ,2,0)*$F34),0) -> 13.339745 | Q34: =IFERROR((VLOOKUP($A34,'Dados StatusInvest'!$A:$AZ,COLUMN(Q34)-$A$5,0)/100),0) -> 0.002 | R34: =VLOOKUP($A34,'Dados StatusInvest'!$A:$AZ,COLUMN(R34)-$A$5,0) -> 0.24 | S34: =IFERROR((VLOOKUP($A34,'Dados StatusInvest'!$A:$AZ,COLUMN(S34)-$A$5,0)),0) -> 6.04 | T34: =IFERROR((VLOOKUP($A34,'Dados StatusInvest'!$A:$AZ,COLUMN(T34)-$A$5,0)/VLOOKUP($A34,'Dados StatusInvest'!$A:$AZ,2,0)*$F34),0) -> 26.039914 | U34: =IFERROR((VLOOKUP($A34,'Dados StatusInvest'!$A:$AZ,COLUMN(U34)-$A$5,0)-VLOOKUP($A34,'Dados StatusInvest'!$A:$AZ,COLUMN(U34)-$A$5-1,0)+T34),0) -> -5.0100863 | V34: =IFERROR((VLOOKUP($A34,'Dados StatusInvest'!$A:$AZ,COLUMN(V34)-$A$5,0)),0) -> 1.62 | W34: =IFERROR((VLOOKUP($A34,'Dados StatusInvest'!$A:$AZ,COLUMN(W34)-$A$5,0)),0) -> -14.87 | X34: =IFERROR((VLOOKUP($A34,'Dados StatusInvest'!$A:$AZ,COLUMN(X34)-$A$5,0)/VLOOKUP($A34,'Dados StatusInvest'!$A:$AZ,2,0)*$F34),0) -> -3.4009244 | Y34: =IFERROR((VLOOKUP($A34,'Dados StatusInvest'!$A:$AZ,COLUMN(Y34)-$A$5,0)/VLOOKUP($A34,'Dados StatusInvest'!$A:$AZ,2,0)*$F34),0) -> 35.968583 | Z34: =IFERROR((VLOOKUP($A34,'Dados StatusInvest'!$A:$AZ,COLUMN(Z34)-$A$5,0)),0) -> 0.23 | AA34: =IFERROR((VLOOKUP($A34,'Dados StatusInvest'!$A:$AZ,COLUMN(AA34)-$A$5,0)),0) -> 0.77 | AB34: =IFERROR((VLOOKUP($A34,'Dados StatusInvest'!$A:$AZ,COLUMN(AB34)-$A$5,0)),0) -> 0.58 | AC34: =IFERROR((VLOOKUP($A34,'Dados StatusInvest'!$A:$AZ,COLUMN(AC34)-$A$5,0)),0) -> 29.1 | AD34: =IFERROR((VLOOKUP($A34,'Dados StatusInvest'!$A:$AZ,COLUMN(AD34)-$A$5,0)),0) -> 0 | AE34: =IFERROR((VLOOKUP($A34,'Dados StatusInvest'!$A:$AZ,COLUMN(AE34)-$A$5,0)),0) -> 159000000 | AF34: =IFERROR((VLOOKUP($A34,'Dados StatusInvest'!$A:$AZ,COLUMN(AF34)-$A$5,0)),0) -> 7.9 | AG34: =IFERROR((VLOOKUP($A34,'Dados StatusInvest'!$A:$AZ,COLUMN(AG34)-$A$5,0)),0) -> -1.17 | ... AJ34: =IFERROR((VLOOKUP($A34,'Dados StatusInvest'!$A:$AZ,COLUMN(AJ34)-$A$5,0)),0) | AK34: =IFERROR(__xludf.DUMMYFUNCTION("IFERROR(GOOGLEFINANCE($A34,""high""),"""")"),124.98) -> 124.98 | AL34: =IFERROR(__xludf.DUMMYFUNCTION("IFERROR(GOOGLEFINANCE($A34,""low""),"""")"),122.24) -> 122.24 | AM34: =IFERROR(((AK34-AL34)/AL34),0) -> 0.022414921 | AN34: =IFERROR(__xludf.DUMMYFUNCTION("IFERROR((GOOGLEFINANCE($A34,""volume"")),0)"),63423.0) -> 63423 | AO34: =IFERROR(__xludf.DUMMYFUNCTION("IFERROR((GOOGLEFINANCE($A34,""closeyest"")),"""")"),121.7) -> 121.7 | AP34: =IFERROR(__xludf.DUMMYFUNCTION("IFERROR((GOOGLEFINANCE($A34,""shares"")),"""")"),8.3534506E7) -> 83534506
A35: ='Dados StatusInvest'!A30:A649 -> AURE3 | B35: =IFERROR(__xludf.DUMMYFUNCTION("IFERROR((GOOGLEFINANCE(A35,""name"")),"""")"),"Auren Energia SA") -> Auren Energia SA | C35: =IFERROR((VLOOKUP(LEFT($A35,4),Setor!$A:$E,3,0)),"") | D35: =IFERROR((VLOOKUP(LEFT($A35,4),Setor!$A:$E,4,0)),"") | E35: =IFERROR((VLOOKUP(LEFT($A35,4),Setor!$A:$E,5,0)),"") | F35: =IFERROR(__xludf.DUMMYFUNCTION("IFERROR((GOOGLEFINANCE(A35)),"""")"),11.56) -> 11.56 | G35: =IFERROR(__xludf.DUMMYFUNCTION("IFERROR((sparkline(GOOGLEFINANCE($A35,""price"",TODAY()-30,TODAY(),""DAILY""),{""charttype"",""line"";""linewidth"",1;""color"",""#5f88cc""})),"""")"),"") | H35: =IFERROR(__xludf.DUMMYFUNCTION("IFERROR((((GOOGLEFINANCE(A35))-(INDEX(GoogleFinance(A35,""PRICE"",$AQ$1),2,2)))/(INDEX(GoogleFinance(A35,""PRICE"",$AQ$1),2,2))),"""")"),-0.016170212765957405) -> -0.016170213 | I35: =IFERROR(__xludf.DUMMYFUNCTION("IFERROR((GOOGLEFINANCE($A35,""high52"")),"""")"),12.99) -> 12.99 | J35: =IFERROR(__xludf.DUMMYFUNCTION("IFERROR((sparkline(GOOGLEFINANCE($A35,""price"",TODAY()-365,TODAY(),""DAILY""),{""charttype"",""line"";""linewidth"",1;""color"",""#5f88cc""})),"""")"),"") | K35: =IFERROR(__xludf.DUMMYFUNCTION("IFERROR((((GOOGLEFINANCE(A35))-(INDEX(GoogleFinance(A35,""PRICE"",$AP$1),2,2)))/(INDEX(GoogleFinance(A35,""PRICE"",$AP$1),2,2))),"""")"),0.30621468926553685) -> 0.30621469 | L35: =IFERROR(((F35-I35)/I35),0) -> -0.11008468 | M35: =IFERROR((VLOOKUP($A35,'Dados StatusInvest'!$A:$AZ,COLUMN(M35)-$A$5,0)*VLOOKUP($A35,'Dados StatusInvest'!$A:$AZ,2,0)/$F35/100),0) -> 0.10263114 | N35: =IFERROR((VLOOKUP($A35,'Dados StatusInvest'!$A:$AZ,COLUMN(N35)-$A$5,0)/VLOOKUP($A35,'Dados StatusInvest'!$A:$AZ,2,0)*$F35),"") -> -10.715344 | O35: =IFERROR((VLOOKUP($A35,'Dados StatusInvest'!$A:$AZ,COLUMN(O35)-$A$5,0)/VLOOKUP($A35,'Dados StatusInvest'!$A:$AZ,2,0)*$F35),0) -> 9.6055055 | P35: =IFERROR((VLOOKUP($A35,'Dados StatusInvest'!$A:$AZ,COLUMN(P35)-$A$5,0)/VLOOKUP($A35,'Dados StatusInvest'!$A:$AZ,2,0)*$F35),0) -> 25.074494 | Q35: =IFERROR((VLOOKUP($A35,'Dados StatusInvest'!$A:$AZ,COLUMN(Q35)-$A$5,0)/100),0) -> 0.1575 | R35: =VLOOKUP($A35,'Dados StatusInvest'!$A:$AZ,COLUMN(R35)-$A$5,0) -> 1.62 | S35: =IFERROR((VLOOKUP($A35,'Dados StatusInvest'!$A:$AZ,COLUMN(S35)-$A$5,0)),0) -> 0.99 | T35: =IFERROR((VLOOKUP($A35,'Dados StatusInvest'!$A:$AZ,COLUMN(T35)-$A$5,0)/VLOOKUP($A35,'Dados StatusInvest'!$A:$AZ,2,0)*$F35),0) -> 5.9518777 | U35: =IFERROR((VLOOKUP($A35,'Dados StatusInvest'!$A:$AZ,COLUMN(U35)-$A$5,0)-VLOOKUP($A35,'Dados StatusInvest'!$A:$AZ,COLUMN(U35)-$A$5-1,0)+T35),0) -> -0.41812234 | V35: =IFERROR((VLOOKUP($A35,'Dados StatusInvest'!$A:$AZ,COLUMN(V35)-$A$5,0)),0) -> 1.3 | W35: =IFERROR((VLOOKUP($A35,'Dados StatusInvest'!$A:$AZ,COLUMN(W35)-$A$5,0)),0) -> -11.15 | X35: =IFERROR((VLOOKUP($A35,'Dados StatusInvest'!$A:$AZ,COLUMN(X35)-$A$5,0)/VLOOKUP($A35,'Dados StatusInvest'!$A:$AZ,2,0)*$F35),0) -> -2.7500425 | Y35: =IFERROR((VLOOKUP($A35,'Dados StatusInvest'!$A:$AZ,COLUMN(Y35)-$A$5,0)/VLOOKUP($A35,'Dados StatusInvest'!$A:$AZ,2,0)*$F35),0) -> 3.1625489 | Z35: =IFERROR((VLOOKUP($A35,'Dados StatusInvest'!$A:$AZ,COLUMN(Z35)-$A$5,0)),0) -> 0.25 | AA35: =IFERROR((VLOOKUP($A35,'Dados StatusInvest'!$A:$AZ,COLUMN(AA35)-$A$5,0)),0) -> 0.72 | AB35: =IFERROR((VLOOKUP($A35,'Dados StatusInvest'!$A:$AZ,COLUMN(AB35)-$A$5,0)),0) -> 0.26 | AC35: =IFERROR((VLOOKUP($A35,'Dados StatusInvest'!$A:$AZ,COLUMN(AC35)-$A$5,0)),0) -> 0 | AD35: =IFERROR((VLOOKUP($A35,'Dados StatusInvest'!$A:$AZ,COLUMN(AD35)-$A$5,0)),0) -> 0 | AE35: =IFERROR((VLOOKUP($A35,'Dados StatusInvest'!$A:$AZ,COLUMN(AE35)-$A$5,0)),0) -> 58479399 | AF35: =IFERROR((VLOOKUP($A35,'Dados StatusInvest'!$A:$AZ,COLUMN(AF35)-$A$5,0)),0) -> 11.69 | AG35: =IFERROR((VLOOKUP($A35,'Dados StatusInvest'!$A:$AZ,COLUMN(AG35)-$A$5,0)),0) -> -1.3 | ... AJ35: =IFERROR((VLOOKUP($A35,'Dados StatusInvest'!$A:$AZ,COLUMN(AJ35)-$A$5,0)),0) | AK35: =IFERROR(__xludf.DUMMYFUNCTION("IFERROR(GOOGLEFINANCE($A35,""high""),"""")"),11.76) -> 11.76 | AL35: =IFERROR(__xludf.DUMMYFUNCTION("IFERROR(GOOGLEFINANCE($A35,""low""),"""")"),11.45) -> 11.45 | AM35: =IFERROR(((AK35-AL35)/AL35),0) -> 0.027074236 | AN35: =IFERROR(__xludf.DUMMYFUNCTION("IFERROR((GOOGLEFINANCE($A35,""volume"")),0)"),333300.0) -> 333300 | AO35: =IFERROR(__xludf.DUMMYFUNCTION("IFERROR((GOOGLEFINANCE($A35,""closeyest"")),"""")"),11.77) -> 11.77 | AP35: =IFERROR(__xludf.DUMMYFUNCTION("IFERROR((GOOGLEFINANCE($A35,""shares"")),"""")"),1.050377974E9) -> 1050377974
A36: ='Dados StatusInvest'!A31:A650 -> AVLL3 | B36: =IFERROR(__xludf.DUMMYFUNCTION("IFERROR((GOOGLEFINANCE(A36,""name"")),"""")"),"Alphaville SA") -> Alphaville SA | C36: =IFERROR((VLOOKUP(LEFT($A36,4),Setor!$A:$E,3,0)),"") | D36: =IFERROR((VLOOKUP(LEFT($A36,4),Setor!$A:$E,4,0)),"") | E36: =IFERROR((VLOOKUP(LEFT($A36,4),Setor!$A:$E,5,0)),"") | F36: =IFERROR(__xludf.DUMMYFUNCTION("IFERROR((GOOGLEFINANCE(A36)),"""")"),0.85) -> 0.85 | G36: =IFERROR(__xludf.DUMMYFUNCTION("IFERROR((sparkline(GOOGLEFINANCE($A36,""price"",TODAY()-30,TODAY(),""DAILY""),{""charttype"",""line"";""linewidth"",1;""color"",""#5f88cc""})),"""")"),"") | H36: =IFERROR(__xludf.DUMMYFUNCTION("IFERROR((((GOOGLEFINANCE(A36))-(INDEX(GoogleFinance(A36,""PRICE"",$AQ$1),2,2)))/(INDEX(GoogleFinance(A36,""PRICE"",$AQ$1),2,2))),"""")"),-0.011627906976744196) -> -0.011627907 | I36: =IFERROR(__xludf.DUMMYFUNCTION("IFERROR((GOOGLEFINANCE($A36,""high52"")),"""")"),2.65) -> 2.65 | J36: =IFERROR(__xludf.DUMMYFUNCTION("IFERROR((sparkline(GOOGLEFINANCE($A36,""price"",TODAY()-365,TODAY(),""DAILY""),{""charttype"",""line"";""linewidth"",1;""color"",""#5f88cc""})),"""")"),"") | K36: =IFERROR(__xludf.DUMMYFUNCTION("IFERROR((((GOOGLEFINANCE(A36))-(INDEX(GoogleFinance(A36,""PRICE"",$AP$1),2,2)))/(INDEX(GoogleFinance(A36,""PRICE"",$AP$1),2,2))),"""")"),-0.6271929824561403) -> -0.62719298 | L36: =IFERROR(((F36-I36)/I36),0) -> -0.67924528 | M36: =IFERROR((VLOOKUP($A36,'Dados StatusInvest'!$A:$AZ,COLUMN(M36)-$A$5,0)*VLOOKUP($A36,'Dados StatusInvest'!$A:$AZ,2,0)/$F36/100),0) -> 0.18845882 | N36: =IFERROR((VLOOKUP($A36,'Dados StatusInvest'!$A:$AZ,COLUMN(N36)-$A$5,0)/VLOOKUP($A36,'Dados StatusInvest'!$A:$AZ,2,0)*$F36),"") -> -18.689759 | O36: =IFERROR((VLOOKUP($A36,'Dados StatusInvest'!$A:$AZ,COLUMN(O36)-$A$5,0)/VLOOKUP($A36,'Dados StatusInvest'!$A:$AZ,2,0)*$F36),0) -> 1.3210843 | P36: =IFERROR((VLOOKUP($A36,'Dados StatusInvest'!$A:$AZ,COLUMN(P36)-$A$5,0)/VLOOKUP($A36,'Dados StatusInvest'!$A:$AZ,2,0)*$F36),0) -> 5.7349398 | Q36: =IFERROR((VLOOKUP($A36,'Dados StatusInvest'!$A:$AZ,COLUMN(Q36)-$A$5,0)/100),0) -> 0.0431 | R36: =VLOOKUP($A36,'Dados StatusInvest'!$A:$AZ,COLUMN(R36)-$A$5,0) -> 0 | S36: =IFERROR((VLOOKUP($A36,'Dados StatusInvest'!$A:$AZ,COLUMN(S36)-$A$5,0)),0) -> 0.25 | T36: =IFERROR((VLOOKUP($A36,'Dados StatusInvest'!$A:$AZ,COLUMN(T36)-$A$5,0)/VLOOKUP($A36,'Dados StatusInvest'!$A:$AZ,2,0)*$F36),0) -> -3.1337349 | U36: =IFERROR((VLOOKUP($A36,'Dados StatusInvest'!$A:$AZ,COLUMN(U36)-$A$5,0)-VLOOKUP($A36,'Dados StatusInvest'!$A:$AZ,COLUMN(U36)-$A$5-1,0)+T36),0) -> -0.27373494 | V36: =IFERROR((VLOOKUP($A36,'Dados StatusInvest'!$A:$AZ,COLUMN(V36)-$A$5,0)),0) -> 0.91 | W36: =IFERROR((VLOOKUP($A36,'Dados StatusInvest'!$A:$AZ,COLUMN(W36)-$A$5,0)),0) -> -62.83 | X36: =IFERROR((VLOOKUP($A36,'Dados StatusInvest'!$A:$AZ,COLUMN(X36)-$A$5,0)/VLOOKUP($A36,'Dados StatusInvest'!$A:$AZ,2,0)*$F36),0) -> -9.073494 | Y36: =IFERROR((VLOOKUP($A36,'Dados StatusInvest'!$A:$AZ,COLUMN(Y36)-$A$5,0)/VLOOKUP($A36,'Dados StatusInvest'!$A:$AZ,2,0)*$F36),0) -> 22.007831 | Z36: =IFERROR((VLOOKUP($A36,'Dados StatusInvest'!$A:$AZ,COLUMN(Z36)-$A$5,0)),0) -> -0.14 | AA36: =IFERROR((VLOOKUP($A36,'Dados StatusInvest'!$A:$AZ,COLUMN(AA36)-$A$5,0)),0) -> 1.11 | AB36: =IFERROR((VLOOKUP($A36,'Dados StatusInvest'!$A:$AZ,COLUMN(AB36)-$A$5,0)),0) -> 0.49 | AC36: =IFERROR((VLOOKUP($A36,'Dados StatusInvest'!$A:$AZ,COLUMN(AC36)-$A$5,0)),0) -> 32.82 | AD36: =IFERROR((VLOOKUP($A36,'Dados StatusInvest'!$A:$AZ,COLUMN(AD36)-$A$5,0)),0) -> 0 | AE36: =IFERROR((VLOOKUP($A36,'Dados StatusInvest'!$A:$AZ,COLUMN(AE36)-$A$5,0)),0) -> 11173.05 | AF36: =IFERROR((VLOOKUP($A36,'Dados StatusInvest'!$A:$AZ,COLUMN(AF36)-$A$5,0)),0) -> -0.97 | AG36: =IFERROR((VLOOKUP($A36,'Dados StatusInvest'!$A:$AZ,COLUMN(AG36)-$A$5,0)),0) -> -0.61 | ... AJ36: =IFERROR((VLOOKUP($A36,'Dados StatusInvest'!$A:$AZ,COLUMN(AJ36)-$A$5,0)),0) | AK36: =IFERROR(__xludf.DUMMYFUNCTION("IFERROR(GOOGLEFINANCE($A36,""high""),"""")"),0.85) -> 0.85 | AL36: =IFERROR(__xludf.DUMMYFUNCTION("IFERROR(GOOGLEFINANCE($A36,""low""),"""")"),0.81) -> 0.81 | AM36: =IFERROR(((AK36-AL36)/AL36),0) -> 0.049382716 | AN36: =IFERROR(__xludf.DUMMYFUNCTION("IFERROR((GOOGLEFINANCE($A36,""volume"")),0)"),1200.0) -> 1200 | AO36: =IFERROR(__xludf.DUMMYFUNCTION("IFERROR((GOOGLEFINANCE($A36,""closeyest"")),"""")"),0.83) -> 0.83 | AP36: =IFERROR(__xludf.DUMMYFUNCTION("IFERROR((GOOGLEFINANCE($A36,""shares"")),"""")"),1.95330061E8) -> 195330061
A37: ='Dados StatusInvest'!A32:A651 -> AXIA3 | B37: =IFERROR(__xludf.DUMMYFUNCTION("IFERROR((GOOGLEFINANCE(A37,""name"")),"""")"),"Centrais Eletricas Brasilrs SA - Eltrbrs") -> Centrais Eletricas Brasilrs SA - Eltrbrs | C37: =IFERROR((VLOOKUP(LEFT($A37,4),Setor!$A:$E,3,0)),"") | D37: =IFERROR((VLOOKUP(LEFT($A37,4),Setor!$A:$E,4,0)),"") | E37: =IFERROR((VLOOKUP(LEFT($A37,4),Setor!$A:$E,5,0)),"") | F37: =IFERROR(__xludf.DUMMYFUNCTION("IFERROR((GOOGLEFINANCE(A37)),"""")"),60.91) -> 60.91 | G37: =IFERROR(__xludf.DUMMYFUNCTION("IFERROR((sparkline(GOOGLEFINANCE($A37,""price"",TODAY()-30,TODAY(),""DAILY""),{""charttype"",""line"";""linewidth"",1;""color"",""#5f88cc""})),"""")"),"") | H37: =IFERROR(__xludf.DUMMYFUNCTION("IFERROR((((GOOGLEFINANCE(A37))-(INDEX(GoogleFinance(A37,""PRICE"",$AQ$1),2,2)))/(INDEX(GoogleFinance(A37,""PRICE"",$AQ$1),2,2))),"""")"),0.1529434033692977) -> 0.1529434 | I37: =IFERROR(__xludf.DUMMYFUNCTION("IFERROR((GOOGLEFINANCE($A37,""high52"")),"""")"),67.84) -> 67.84 | J37: =IFERROR(__xludf.DUMMYFUNCTION("IFERROR((sparkline(GOOGLEFINANCE($A37,""price"",TODAY()-365,TODAY(),""DAILY""),{""charttype"",""line"";""linewidth"",1;""color"",""#5f88cc""})),"""")"),"") | K37: =IFERROR(__xludf.DUMMYFUNCTION("IFERROR((((GOOGLEFINANCE(A37))-(INDEX(GoogleFinance(A37,""PRICE"",$AP$1),2,2)))/(INDEX(GoogleFinance(A37,""PRICE"",$AP$1),2,2))),"""")"),1.0425888665325285) -> 1.0425889 | L37: =IFERROR(((F37-I37)/I37),0) -> -0.10215212 | M37: =IFERROR((VLOOKUP($A37,'Dados StatusInvest'!$A:$AZ,COLUMN(M37)-$A$5,0)*VLOOKUP($A37,'Dados StatusInvest'!$A:$AZ,2,0)/$F37/100),0) -> 0.11018627 | N37: =IFERROR((VLOOKUP($A37,'Dados StatusInvest'!$A:$AZ,COLUMN(N37)-$A$5,0)/VLOOKUP($A37,'Dados StatusInvest'!$A:$AZ,2,0)*$F37),"") -> -14.037774 | O37: =IFERROR((VLOOKUP($A37,'Dados StatusInvest'!$A:$AZ,COLUMN(O37)-$A$5,0)/VLOOKUP($A37,'Dados StatusInvest'!$A:$AZ,2,0)*$F37),0) -> 37.97168 | P37: =IFERROR((VLOOKUP($A37,'Dados StatusInvest'!$A:$AZ,COLUMN(P37)-$A$5,0)/VLOOKUP($A37,'Dados StatusInvest'!$A:$AZ,2,0)*$F37),0) -> 48.047019 | Q37: =IFERROR((VLOOKUP($A37,'Dados StatusInvest'!$A:$AZ,COLUMN(Q37)-$A$5,0)/100),0) -> 0.0911 | R37: =VLOOKUP($A37,'Dados StatusInvest'!$A:$AZ,COLUMN(R37)-$A$5,0) -> 0.39 | S37: =IFERROR((VLOOKUP($A37,'Dados StatusInvest'!$A:$AZ,COLUMN(S37)-$A$5,0)),0) -> 4.18 | T37: =IFERROR((VLOOKUP($A37,'Dados StatusInvest'!$A:$AZ,COLUMN(T37)-$A$5,0)/VLOOKUP($A37,'Dados StatusInvest'!$A:$AZ,2,0)*$F37),0) -> 7.088578 | U37: =IFERROR((VLOOKUP($A37,'Dados StatusInvest'!$A:$AZ,COLUMN(U37)-$A$5,0)-VLOOKUP($A37,'Dados StatusInvest'!$A:$AZ,COLUMN(U37)-$A$5-1,0)+T37),0) -> -0.86142203 | V37: =IFERROR((VLOOKUP($A37,'Dados StatusInvest'!$A:$AZ,COLUMN(V37)-$A$5,0)),0) -> 1.92 | W37: =IFERROR((VLOOKUP($A37,'Dados StatusInvest'!$A:$AZ,COLUMN(W37)-$A$5,0)),0) -> -5.5 | X37: =IFERROR((VLOOKUP($A37,'Dados StatusInvest'!$A:$AZ,COLUMN(X37)-$A$5,0)/VLOOKUP($A37,'Dados StatusInvest'!$A:$AZ,2,0)*$F37),0) -> -2.2500262 | Y37: =IFERROR((VLOOKUP($A37,'Dados StatusInvest'!$A:$AZ,COLUMN(Y37)-$A$5,0)/VLOOKUP($A37,'Dados StatusInvest'!$A:$AZ,2,0)*$F37),0) -> 1.6427182 | Z37: =IFERROR((VLOOKUP($A37,'Dados StatusInvest'!$A:$AZ,COLUMN(Z37)-$A$5,0)),0) -> 0.41 | AA37: =IFERROR((VLOOKUP($A37,'Dados StatusInvest'!$A:$AZ,COLUMN(AA37)-$A$5,0)),0) -> 0.59 | AB37: =IFERROR((VLOOKUP($A37,'Dados StatusInvest'!$A:$AZ,COLUMN(AB37)-$A$5,0)),0) -> 0.16 | AC37: =IFERROR((VLOOKUP($A37,'Dados StatusInvest'!$A:$AZ,COLUMN(AC37)-$A$5,0)),0) -> 7.7 | AD37: =IFERROR((VLOOKUP($A37,'Dados StatusInvest'!$A:$AZ,COLUMN(AD37)-$A$5,0)),0) -> 0 | AE37: =IFERROR((VLOOKUP($A37,'Dados StatusInvest'!$A:$AZ,COLUMN(AE37)-$A$5,0)),0) -> 687000000 | AF37: =IFERROR((VLOOKUP($A37,'Dados StatusInvest'!$A:$AZ,COLUMN(AF37)-$A$5,0)),0) -> 37.49 | AG37: =IFERROR((VLOOKUP($A37,'Dados StatusInvest'!$A:$AZ,COLUMN(AG37)-$A$5,0)),0) -> -2.06 | ... AJ37: =IFERROR((VLOOKUP($A37,'Dados StatusInvest'!$A:$AZ,COLUMN(AJ37)-$A$5,0)),0) | AK37: =IFERROR(__xludf.DUMMYFUNCTION("IFERROR(GOOGLEFINANCE($A37,""high""),"""")"),60.98) -> 60.98 | AL37: =IFERROR(__xludf.DUMMYFUNCTION("IFERROR(GOOGLEFINANCE($A37,""low""),"""")"),60.27) -> 60.27 | AM37: =IFERROR(((AK37-AL37)/AL37),0) -> 0.011780322 | AN37: =IFERROR(__xludf.DUMMYFUNCTION("IFERROR((GOOGLEFINANCE($A37,""volume"")),0)"),393400.0) -> 393400 | AO37: =IFERROR(__xludf.DUMMYFUNCTION("IFERROR((GOOGLEFINANCE($A37,""closeyest"")),"""")"),61.18) -> 61.18 | AP37: =IFERROR(__xludf.DUMMYFUNCTION("IFERROR((GOOGLEFINANCE($A37,""shares"")),"""")"),2.028544286E9) -> 2028544286
A38: ='Dados StatusInvest'!A33:A652 -> AXIA5 | B38: =IFERROR(__xludf.DUMMYFUNCTION("IFERROR((GOOGLEFINANCE(A38,""name"")),"""")"),"Centrais Eletricas Brasilrs SA - Eltrbrs Preference Shares Class A") -> Centrais Eletricas Brasilrs SA - Eltrbrs Preference Shares Class A | C38: =IFERROR((VLOOKUP(LEFT($A38,4),Setor!$A:$E,3,0)),"") | D38: =IFERROR((VLOOKUP(LEFT($A38,4),Setor!$A:$E,4,0)),"") | E38: =IFERROR((VLOOKUP(LEFT($A38,4),Setor!$A:$E,5,0)),"") | F38: =IFERROR(__xludf.DUMMYFUNCTION("IFERROR((GOOGLEFINANCE(A38)),"""")"),79.0) -> 79 | G38: =IFERROR(__xludf.DUMMYFUNCTION("IFERROR((sparkline(GOOGLEFINANCE($A38,""price"",TODAY()-30,TODAY(),""DAILY""),{""charttype"",""line"";""linewidth"",1;""color"",""#5f88cc""})),"""")"),"") | H38: =IFERROR(__xludf.DUMMYFUNCTION("IFERROR((((GOOGLEFINANCE(A38))-(INDEX(GoogleFinance(A38,""PRICE"",$AQ$1),2,2)))/(INDEX(GoogleFinance(A38,""PRICE"",$AQ$1),2,2))),"""")"),"") | I38: =IFERROR(__xludf.DUMMYFUNCTION("IFERROR((GOOGLEFINANCE($A38,""high52"")),"""")"),79.0) -> 79 | J38: =IFERROR(__xludf.DUMMYFUNCTION("IFERROR((sparkline(GOOGLEFINANCE($A38,""price"",TODAY()-365,TODAY(),""DAILY""),{""charttype"",""line"";""linewidth"",1;""color"",""#5f88cc""})),"""")"),"") | K38: =IFERROR(__xludf.DUMMYFUNCTION("IFERROR((((GOOGLEFINANCE(A38))-(INDEX(GoogleFinance(A38,""PRICE"",$AP$1),2,2)))/(INDEX(GoogleFinance(A38,""PRICE"",$AP$1),2,2))),"""")"),"") | L38: =IFERROR(((F38-I38)/I38),0) -> 0 | M38: =IFERROR((VLOOKUP($A38,'Dados StatusInvest'!$A:$AZ,COLUMN(M38)-$A$5,0)*VLOOKUP($A38,'Dados StatusInvest'!$A:$AZ,2,0)/$F38/100),0) -> 0.1097 | N38: =IFERROR((VLOOKUP($A38,'Dados StatusInvest'!$A:$AZ,COLUMN(N38)-$A$5,0)/VLOOKUP($A38,'Dados StatusInvest'!$A:$AZ,2,0)*$F38),"") -> -14.1 | O38: =IFERROR((VLOOKUP($A38,'Dados StatusInvest'!$A:$AZ,COLUMN(O38)-$A$5,0)/VLOOKUP($A38,'Dados StatusInvest'!$A:$AZ,2,0)*$F38),0) -> 49.25 | P38: =IFERROR((VLOOKUP($A38,'Dados StatusInvest'!$A:$AZ,COLUMN(P38)-$A$5,0)/VLOOKUP($A38,'Dados StatusInvest'!$A:$AZ,2,0)*$F38),0) -> 48.26 | Q38: =IFERROR((VLOOKUP($A38,'Dados StatusInvest'!$A:$AZ,COLUMN(Q38)-$A$5,0)/100),0) -> 0.0911 | R38: =VLOOKUP($A38,'Dados StatusInvest'!$A:$AZ,COLUMN(R38)-$A$5,0) -> 0.39 | S38: =IFERROR((VLOOKUP($A38,'Dados StatusInvest'!$A:$AZ,COLUMN(S38)-$A$5,0)),0) -> 5.4 | T38: =IFERROR((VLOOKUP($A38,'Dados StatusInvest'!$A:$AZ,COLUMN(T38)-$A$5,0)/VLOOKUP($A38,'Dados StatusInvest'!$A:$AZ,2,0)*$F38),0) -> 9.19 | U38: =IFERROR((VLOOKUP($A38,'Dados StatusInvest'!$A:$AZ,COLUMN(U38)-$A$5,0)-VLOOKUP($A38,'Dados StatusInvest'!$A:$AZ,COLUMN(U38)-$A$5-1,0)+T38),0) -> -1.08 | V38: =IFERROR((VLOOKUP($A38,'Dados StatusInvest'!$A:$AZ,COLUMN(V38)-$A$5,0)),0) -> 1.92 | W38: =IFERROR((VLOOKUP($A38,'Dados StatusInvest'!$A:$AZ,COLUMN(W38)-$A$5,0)),0) -> -5.5 | X38: =IFERROR((VLOOKUP($A38,'Dados StatusInvest'!$A:$AZ,COLUMN(X38)-$A$5,0)/VLOOKUP($A38,'Dados StatusInvest'!$A:$AZ,2,0)*$F38),0) -> -2.26 | Y38: =IFERROR((VLOOKUP($A38,'Dados StatusInvest'!$A:$AZ,COLUMN(Y38)-$A$5,0)/VLOOKUP($A38,'Dados StatusInvest'!$A:$AZ,2,0)*$F38),0) -> 1.65 | Z38: =IFERROR((VLOOKUP($A38,'Dados StatusInvest'!$A:$AZ,COLUMN(Z38)-$A$5,0)),0) -> 0.41 | AA38: =IFERROR((VLOOKUP($A38,'Dados StatusInvest'!$A:$AZ,COLUMN(AA38)-$A$5,0)),0) -> 0.59 | AB38: =IFERROR((VLOOKUP($A38,'Dados StatusInvest'!$A:$AZ,COLUMN(AB38)-$A$5,0)),0) -> 0.16 | AC38: =IFERROR((VLOOKUP($A38,'Dados StatusInvest'!$A:$AZ,COLUMN(AC38)-$A$5,0)),0) -> 7.7 | AD38: =IFERROR((VLOOKUP($A38,'Dados StatusInvest'!$A:$AZ,COLUMN(AD38)-$A$5,0)),0) -> 0 | AE38: =IFERROR((VLOOKUP($A38,'Dados StatusInvest'!$A:$AZ,COLUMN(AE38)-$A$5,0)),0) -> 31051 | AF38: =IFERROR((VLOOKUP($A38,'Dados StatusInvest'!$A:$AZ,COLUMN(AF38)-$A$5,0)),0) -> 37.49 | AG38: =IFERROR((VLOOKUP($A38,'Dados StatusInvest'!$A:$AZ,COLUMN(AG38)-$A$5,0)),0) -> -2.06 | ... AJ38: =IFERROR((VLOOKUP($A38,'Dados StatusInvest'!$A:$AZ,COLUMN(AJ38)-$A$5,0)),0) | AK38: =IFERROR(__xludf.DUMMYFUNCTION("IFERROR(GOOGLEFINANCE($A38,""high""),"""")"),"") | AL38: =IFERROR(__xludf.DUMMYFUNCTION("IFERROR(GOOGLEFINANCE($A38,""low""),"""")"),"") | AM38: =IFERROR(((AK38-AL38)/AL38),0) -> 0 | AN38: =IFERROR(__xludf.DUMMYFUNCTION("IFERROR((GOOGLEFINANCE($A38,""volume"")),0)"),0.0) -> 0 | AO38: =IFERROR(__xludf.DUMMYFUNCTION("IFERROR((GOOGLEFINANCE($A38,""closeyest"")),"""")"),64.63) -> 64.63 | AP38: =IFERROR(__xludf.DUMMYFUNCTION("IFERROR((GOOGLEFINANCE($A38,""shares"")),"""")"),146920.0) -> 146920
A39: ='Dados StatusInvest'!A34:A653 -> AXIA6 | B39: =IFERROR(__xludf.DUMMYFUNCTION("IFERROR((GOOGLEFINANCE(A39,""name"")),"""")"),"Centrais Eletricas Brasilrs SA - Eltrbrs Preference Shares Class B") -> Centrais Eletricas Brasilrs SA - Eltrbrs Preference Shares Class B | C39: =IFERROR((VLOOKUP(LEFT($A39,4),Setor!$A:$E,3,0)),"") | D39: =IFERROR((VLOOKUP(LEFT($A39,4),Setor!$A:$E,4,0)),"") | E39: =IFERROR((VLOOKUP(LEFT($A39,4),Setor!$A:$E,5,0)),"") | F39: =IFERROR(__xludf.DUMMYFUNCTION("IFERROR((GOOGLEFINANCE(A39)),"""")"),66.18) -> 66.18 | G39: =IFERROR(__xludf.DUMMYFUNCTION("IFERROR((sparkline(GOOGLEFINANCE($A39,""price"",TODAY()-30,TODAY(),""DAILY""),{""charttype"",""line"";""linewidth"",1;""color"",""#5f88cc""})),"""")"),"") | H39: =IFERROR(__xludf.DUMMYFUNCTION("IFERROR((((GOOGLEFINANCE(A39))-(INDEX(GoogleFinance(A39,""PRICE"",$AQ$1),2,2)))/(INDEX(GoogleFinance(A39,""PRICE"",$AQ$1),2,2))),"""")"),0.1725726435152376) -> 0.17257264 | I39: =IFERROR(__xludf.DUMMYFUNCTION("IFERROR((GOOGLEFINANCE($A39,""high52"")),"""")"),71.5) -> 71.5 | J39: =IFERROR(__xludf.DUMMYFUNCTION("IFERROR((sparkline(GOOGLEFINANCE($A39,""price"",TODAY()-365,TODAY(),""DAILY""),{""charttype"",""line"";""linewidth"",1;""color"",""#5f88cc""})),"""")"),"") | K39: =IFERROR(__xludf.DUMMYFUNCTION("IFERROR((((GOOGLEFINANCE(A39))-(INDEX(GoogleFinance(A39,""PRICE"",$AP$1),2,2)))/(INDEX(GoogleFinance(A39,""PRICE"",$AP$1),2,2))),"""")"),0.9873873873873877) -> 0.98738739 | L39: =IFERROR(((F39-I39)/I39),0) -> -0.074405594 | M39: =IFERROR((VLOOKUP($A39,'Dados StatusInvest'!$A:$AZ,COLUMN(M39)-$A$5,0)*VLOOKUP($A39,'Dados StatusInvest'!$A:$AZ,2,0)/$F39/100),0) -> 0.11029674 | N39: =IFERROR((VLOOKUP($A39,'Dados StatusInvest'!$A:$AZ,COLUMN(N39)-$A$5,0)/VLOOKUP($A39,'Dados StatusInvest'!$A:$AZ,2,0)*$F39),"") -> -14.023715 | O39: =IFERROR((VLOOKUP($A39,'Dados StatusInvest'!$A:$AZ,COLUMN(O39)-$A$5,0)/VLOOKUP($A39,'Dados StatusInvest'!$A:$AZ,2,0)*$F39),0) -> 41.255582 | P39: =IFERROR((VLOOKUP($A39,'Dados StatusInvest'!$A:$AZ,COLUMN(P39)-$A$5,0)/VLOOKUP($A39,'Dados StatusInvest'!$A:$AZ,2,0)*$F39),0) -> 47.9989 | Q39: =IFERROR((VLOOKUP($A39,'Dados StatusInvest'!$A:$AZ,COLUMN(Q39)-$A$5,0)/100),0) -> 0.0911 | R39: =VLOOKUP($A39,'Dados StatusInvest'!$A:$AZ,COLUMN(R39)-$A$5,0) -> 0.39 | S39: =IFERROR((VLOOKUP($A39,'Dados StatusInvest'!$A:$AZ,COLUMN(S39)-$A$5,0)),0) -> 4.55 | T39: =IFERROR((VLOOKUP($A39,'Dados StatusInvest'!$A:$AZ,COLUMN(T39)-$A$5,0)/VLOOKUP($A39,'Dados StatusInvest'!$A:$AZ,2,0)*$F39),0) -> 7.6981244 | U39: =IFERROR((VLOOKUP($A39,'Dados StatusInvest'!$A:$AZ,COLUMN(U39)-$A$5,0)-VLOOKUP($A39,'Dados StatusInvest'!$A:$AZ,COLUMN(U39)-$A$5-1,0)+T39),0) -> -0.95187556 | V39: =IFERROR((VLOOKUP($A39,'Dados StatusInvest'!$A:$AZ,COLUMN(V39)-$A$5,0)),0) -> 1.92 | W39: =IFERROR((VLOOKUP($A39,'Dados StatusInvest'!$A:$AZ,COLUMN(W39)-$A$5,0)),0) -> -5.5 | X39: =IFERROR((VLOOKUP($A39,'Dados StatusInvest'!$A:$AZ,COLUMN(X39)-$A$5,0)/VLOOKUP($A39,'Dados StatusInvest'!$A:$AZ,2,0)*$F39),0) -> -2.2477728 | Y39: =IFERROR((VLOOKUP($A39,'Dados StatusInvest'!$A:$AZ,COLUMN(Y39)-$A$5,0)/VLOOKUP($A39,'Dados StatusInvest'!$A:$AZ,2,0)*$F39),0) -> 1.641073 | Z39: =IFERROR((VLOOKUP($A39,'Dados StatusInvest'!$A:$AZ,COLUMN(Z39)-$A$5,0)),0) -> 0.41 | AA39: =IFERROR((VLOOKUP($A39,'Dados StatusInvest'!$A:$AZ,COLUMN(AA39)-$A$5,0)),0) -> 0.59 | AB39: =IFERROR((VLOOKUP($A39,'Dados StatusInvest'!$A:$AZ,COLUMN(AB39)-$A$5,0)),0) -> 0.16 | AC39: =IFERROR((VLOOKUP($A39,'Dados StatusInvest'!$A:$AZ,COLUMN(AC39)-$A$5,0)),0) -> 7.7 | AD39: =IFERROR((VLOOKUP($A39,'Dados StatusInvest'!$A:$AZ,COLUMN(AD39)-$A$5,0)),0) -> 0 | AE39: =IFERROR((VLOOKUP($A39,'Dados StatusInvest'!$A:$AZ,COLUMN(AE39)-$A$5,0)),0) -> 86185274 | AF39: =IFERROR((VLOOKUP($A39,'Dados StatusInvest'!$A:$AZ,COLUMN(AF39)-$A$5,0)),0) -> 37.49 | AG39: =IFERROR((VLOOKUP($A39,'Dados StatusInvest'!$A:$AZ,COLUMN(AG39)-$A$5,0)),0) -> -2.06 | ... AJ39: =IFERROR((VLOOKUP($A39,'Dados StatusInvest'!$A:$AZ,COLUMN(AJ39)-$A$5,0)),0) | AK39: =IFERROR(__xludf.DUMMYFUNCTION("IFERROR(GOOGLEFINANCE($A39,""high""),"""")"),66.25) -> 66.25 | AL39: =IFERROR(__xludf.DUMMYFUNCTION("IFERROR(GOOGLEFINANCE($A39,""low""),"""")"),65.49) -> 65.49 | AM39: =IFERROR(((AK39-AL39)/AL39),0) -> 0.011604825 | AN39: =IFERROR(__xludf.DUMMYFUNCTION("IFERROR((GOOGLEFINANCE($A39,""volume"")),0)"),117000.0) -> 117000 | AO39: =IFERROR(__xludf.DUMMYFUNCTION("IFERROR((GOOGLEFINANCE($A39,""closeyest"")),"""")"),66.54) -> 66.54 | AP39: =IFERROR(__xludf.DUMMYFUNCTION("IFERROR((GOOGLEFINANCE($A39,""shares"")),"""")"),2.79941394E8) -> 279941394
A40: ='Dados StatusInvest'!A35:A654 -> AXIA7 | B40: =IFERROR(__xludf.DUMMYFUNCTION("IFERROR((GOOGLEFINANCE(A40,""name"")),"""")"),"Centrais Elet Bras Prf Shs") -> Centrais Elet Bras Prf Shs | C40: =IFERROR((VLOOKUP(LEFT($A40,4),Setor!$A:$E,3,0)),"") | D40: =IFERROR((VLOOKUP(LEFT($A40,4),Setor!$A:$E,4,0)),"") | E40: =IFERROR((VLOOKUP(LEFT($A40,4),Setor!$A:$E,5,0)),"") | F40: =IFERROR(__xludf.DUMMYFUNCTION("IFERROR((GOOGLEFINANCE(A40)),"""")"),58.82) -> 58.82 | G40: =IFERROR(__xludf.DUMMYFUNCTION("IFERROR((sparkline(GOOGLEFINANCE($A40,""price"",TODAY()-30,TODAY(),""DAILY""),{""charttype"",""line"";""linewidth"",1;""color"",""#5f88cc""})),"""")"),"") | H40: =IFERROR(__xludf.DUMMYFUNCTION("IFERROR((((GOOGLEFINANCE(A40))-(INDEX(GoogleFinance(A40,""PRICE"",$AQ$1),2,2)))/(INDEX(GoogleFinance(A40,""PRICE"",$AQ$1),2,2))),"""")"),0.15107632093933462) -> 0.15107632 | I40: =IFERROR(__xludf.DUMMYFUNCTION("IFERROR((GOOGLEFINANCE($A40,""high52"")),"""")"),58.69) -> 58.69 | J40: =IFERROR(__xludf.DUMMYFUNCTION("IFERROR((sparkline(GOOGLEFINANCE($A40,""price"",TODAY()-365,TODAY(),""DAILY""),{""charttype"",""line"";""linewidth"",1;""color"",""#5f88cc""})),"""")"),"") | K40: =IFERROR(__xludf.DUMMYFUNCTION("IFERROR((((GOOGLEFINANCE(A40))-(INDEX(GoogleFinance(A40,""PRICE"",$AP$1),2,2)))/(INDEX(GoogleFinance(A40,""PRICE"",$AP$1),2,2))),"""")"),"") | L40: =IFERROR(((F40-I40)/I40),0) -> 0.0022150281 | M40: =IFERROR((VLOOKUP($A40,'Dados StatusInvest'!$A:$AZ,COLUMN(M40)-$A$5,0)*VLOOKUP($A40,'Dados StatusInvest'!$A:$AZ,2,0)/$F40/100),0) -> 0.11039005 | N40: =IFERROR((VLOOKUP($A40,'Dados StatusInvest'!$A:$AZ,COLUMN(N40)-$A$5,0)/VLOOKUP($A40,'Dados StatusInvest'!$A:$AZ,2,0)*$F40),"") -> -14.01186 | O40: =IFERROR((VLOOKUP($A40,'Dados StatusInvest'!$A:$AZ,COLUMN(O40)-$A$5,0)/VLOOKUP($A40,'Dados StatusInvest'!$A:$AZ,2,0)*$F40),0) -> 36.669336 | P40: =IFERROR((VLOOKUP($A40,'Dados StatusInvest'!$A:$AZ,COLUMN(P40)-$A$5,0)/VLOOKUP($A40,'Dados StatusInvest'!$A:$AZ,2,0)*$F40),0) -> 47.958324 | Q40: =IFERROR((VLOOKUP($A40,'Dados StatusInvest'!$A:$AZ,COLUMN(Q40)-$A$5,0)/100),0) -> 0.0911 | R40: =VLOOKUP($A40,'Dados StatusInvest'!$A:$AZ,COLUMN(R40)-$A$5,0) -> 0.39 | S40: =IFERROR((VLOOKUP($A40,'Dados StatusInvest'!$A:$AZ,COLUMN(S40)-$A$5,0)),0) -> 4.05 | T40: =IFERROR((VLOOKUP($A40,'Dados StatusInvest'!$A:$AZ,COLUMN(T40)-$A$5,0)/VLOOKUP($A40,'Dados StatusInvest'!$A:$AZ,2,0)*$F40),0) -> 6.8369927 | U40: =IFERROR((VLOOKUP($A40,'Dados StatusInvest'!$A:$AZ,COLUMN(U40)-$A$5,0)-VLOOKUP($A40,'Dados StatusInvest'!$A:$AZ,COLUMN(U40)-$A$5-1,0)+T40),0) -> -0.85300726 | V40: =IFERROR((VLOOKUP($A40,'Dados StatusInvest'!$A:$AZ,COLUMN(V40)-$A$5,0)),0) -> 1.92 | W40: =IFERROR((VLOOKUP($A40,'Dados StatusInvest'!$A:$AZ,COLUMN(W40)-$A$5,0)),0) -> -5.5 | X40: =IFERROR((VLOOKUP($A40,'Dados StatusInvest'!$A:$AZ,COLUMN(X40)-$A$5,0)/VLOOKUP($A40,'Dados StatusInvest'!$A:$AZ,2,0)*$F40),0) -> -2.2458726 | Y40: =IFERROR((VLOOKUP($A40,'Dados StatusInvest'!$A:$AZ,COLUMN(Y40)-$A$5,0)/VLOOKUP($A40,'Dados StatusInvest'!$A:$AZ,2,0)*$F40),0) -> 1.6396858 | Z40: =IFERROR((VLOOKUP($A40,'Dados StatusInvest'!$A:$AZ,COLUMN(Z40)-$A$5,0)),0) -> 0.41 | AA40: =IFERROR((VLOOKUP($A40,'Dados StatusInvest'!$A:$AZ,COLUMN(AA40)-$A$5,0)),0) -> 0.59 | AB40: =IFERROR((VLOOKUP($A40,'Dados StatusInvest'!$A:$AZ,COLUMN(AB40)-$A$5,0)),0) -> 0.16 | AC40: =IFERROR((VLOOKUP($A40,'Dados StatusInvest'!$A:$AZ,COLUMN(AC40)-$A$5,0)),0) -> 7.7 | AD40: =IFERROR((VLOOKUP($A40,'Dados StatusInvest'!$A:$AZ,COLUMN(AD40)-$A$5,0)),0) -> 0 | AE40: =IFERROR((VLOOKUP($A40,'Dados StatusInvest'!$A:$AZ,COLUMN(AE40)-$A$5,0)),0) -> 189000000 | AF40: =IFERROR((VLOOKUP($A40,'Dados StatusInvest'!$A:$AZ,COLUMN(AF40)-$A$5,0)),0) -> 37.49 | AG40: =IFERROR((VLOOKUP($A40,'Dados StatusInvest'!$A:$AZ,COLUMN(AG40)-$A$5,0)),0) -> -2.06 | ... AJ40: =IFERROR((VLOOKUP($A40,'Dados StatusInvest'!$A:$AZ,COLUMN(AJ40)-$A$5,0)),0) | AK40: =IFERROR(__xludf.DUMMYFUNCTION("IFERROR(GOOGLEFINANCE($A40,""high""),"""")"),58.81) -> 58.81 | AL40: =IFERROR(__xludf.DUMMYFUNCTION("IFERROR(GOOGLEFINANCE($A40,""low""),"""")"),58.41) -> 58.41 | AM40: =IFERROR(((AK40-AL40)/AL40),0) -> 0.0068481424 | AN40: =IFERROR(__xludf.DUMMYFUNCTION("IFERROR((GOOGLEFINANCE($A40,""volume"")),0)"),34000.0) -> 34000 | AO40: =IFERROR(__xludf.DUMMYFUNCTION("IFERROR((GOOGLEFINANCE($A40,""closeyest"")),"""")"),59.19) -> 59.19 | AP40: =IFERROR(__xludf.DUMMYFUNCTION("IFERROR((GOOGLEFINANCE($A40,""shares"")),"""")"),6.06796117E8) -> 606796117
A41: ='Dados StatusInvest'!A36:A655 -> AZEV3 | B41: =IFERROR(__xludf.DUMMYFUNCTION("IFERROR((GOOGLEFINANCE(A41,""name"")),"""")"),"Azevedo & Travassos SA") -> Azevedo & Travassos SA | C41: =IFERROR((VLOOKUP(LEFT($A41,4),Setor!$A:$E,3,0)),"") -> Bens Industriais | D41: =IFERROR((VLOOKUP(LEFT($A41,4),Setor!$A:$E,4,0)),"") -> Construção e Engenharia | E41: =IFERROR((VLOOKUP(LEFT($A41,4),Setor!$A:$E,5,0)),"") -> Construção Pesada | F41: =IFERROR(__xludf.DUMMYFUNCTION("IFERROR((GOOGLEFINANCE(A41)),"""")"),0.25) -> 0.25 | G41: =IFERROR(__xludf.DUMMYFUNCTION("IFERROR((sparkline(GOOGLEFINANCE($A41,""price"",TODAY()-30,TODAY(),""DAILY""),{""charttype"",""line"";""linewidth"",1;""color"",""#5f88cc""})),"""")"),"") | H41: =IFERROR(__xludf.DUMMYFUNCTION("IFERROR((((GOOGLEFINANCE(A41))-(INDEX(GoogleFinance(A41,""PRICE"",$AQ$1),2,2)))/(INDEX(GoogleFinance(A41,""PRICE"",$AQ$1),2,2))),"""")"),-0.3055555555555555) -> -0.30555556 | I41: =IFERROR(__xludf.DUMMYFUNCTION("IFERROR((GOOGLEFINANCE($A41,""high52"")),"""")"),1.33) -> 1.33 | J41: =IFERROR(__xludf.DUMMYFUNCTION("IFERROR((sparkline(GOOGLEFINANCE($A41,""price"",TODAY()-365,TODAY(),""DAILY""),{""charttype"",""line"";""linewidth"",1;""color"",""#5f88cc""})),"""")"),"") | K41: =IFERROR(__xludf.DUMMYFUNCTION("IFERROR((((GOOGLEFINANCE(A41))-(INDEX(GoogleFinance(A41,""PRICE"",$AP$1),2,2)))/(INDEX(GoogleFinance(A41,""PRICE"",$AP$1),2,2))),"""")"),-0.6835443037974683) -> -0.6835443 | L41: =IFERROR(((F41-I41)/I41),0) -> -0.81203008 | M41: =IFERROR((VLOOKUP($A41,'Dados StatusInvest'!$A:$AZ,COLUMN(M41)-$A$5,0)*VLOOKUP($A41,'Dados StatusInvest'!$A:$AZ,2,0)/$F41/100),0) -> -1.8196 | N41: =IFERROR((VLOOKUP($A41,'Dados StatusInvest'!$A:$AZ,COLUMN(N41)-$A$5,0)/VLOOKUP($A41,'Dados StatusInvest'!$A:$AZ,2,0)*$F41),"") -> -269.37 | O41: =IFERROR((VLOOKUP($A41,'Dados StatusInvest'!$A:$AZ,COLUMN(O41)-$A$5,0)/VLOOKUP($A41,'Dados StatusInvest'!$A:$AZ,2,0)*$F41),0) -> -0.3 | P41: =IFERROR((VLOOKUP($A41,'Dados StatusInvest'!$A:$AZ,COLUMN(P41)-$A$5,0)/VLOOKUP($A41,'Dados StatusInvest'!$A:$AZ,2,0)*$F41),0) -> -0.37 | Q41: =IFERROR((VLOOKUP($A41,'Dados StatusInvest'!$A:$AZ,COLUMN(Q41)-$A$5,0)/100),0) -> -0.0012 | R41: =VLOOKUP($A41,'Dados StatusInvest'!$A:$AZ,COLUMN(R41)-$A$5,0) -> 0.36 | S41: =IFERROR((VLOOKUP($A41,'Dados StatusInvest'!$A:$AZ,COLUMN(S41)-$A$5,0)),0) -> 0.55 | T41: =IFERROR((VLOOKUP($A41,'Dados StatusInvest'!$A:$AZ,COLUMN(T41)-$A$5,0)/VLOOKUP($A41,'Dados StatusInvest'!$A:$AZ,2,0)*$F41),0) -> -1.27 | U41: =IFERROR((VLOOKUP($A41,'Dados StatusInvest'!$A:$AZ,COLUMN(U41)-$A$5,0)-VLOOKUP($A41,'Dados StatusInvest'!$A:$AZ,COLUMN(U41)-$A$5-1,0)+T41),0) -> -0.18 | V41: =IFERROR((VLOOKUP($A41,'Dados StatusInvest'!$A:$AZ,COLUMN(V41)-$A$5,0)),0) -> 0.65 | W41: =IFERROR((VLOOKUP($A41,'Dados StatusInvest'!$A:$AZ,COLUMN(W41)-$A$5,0)),0) -> -453.29 | X41: =IFERROR((VLOOKUP($A41,'Dados StatusInvest'!$A:$AZ,COLUMN(X41)-$A$5,0)/VLOOKUP($A41,'Dados StatusInvest'!$A:$AZ,2,0)*$F41),0) -> -69.02 | Y41: =IFERROR((VLOOKUP($A41,'Dados StatusInvest'!$A:$AZ,COLUMN(Y41)-$A$5,0)/VLOOKUP($A41,'Dados StatusInvest'!$A:$AZ,2,0)*$F41),0) -> -250.88 | Z41: =IFERROR((VLOOKUP($A41,'Dados StatusInvest'!$A:$AZ,COLUMN(Z41)-$A$5,0)),0) -> 0.15 | AA41: =IFERROR((VLOOKUP($A41,'Dados StatusInvest'!$A:$AZ,COLUMN(AA41)-$A$5,0)),0) -> 0.85 | AB41: =IFERROR((VLOOKUP($A41,'Dados StatusInvest'!$A:$AZ,COLUMN(AB41)-$A$5,0)),0) -> 0.26 | AC41: =IFERROR((VLOOKUP($A41,'Dados StatusInvest'!$A:$AZ,COLUMN(AC41)-$A$5,0)),0) -> 144.07 | AD41: =IFERROR((VLOOKUP($A41,'Dados StatusInvest'!$A:$AZ,COLUMN(AD41)-$A$5,0)),0) -> 0 | AE41: =IFERROR((VLOOKUP($A41,'Dados StatusInvest'!$A:$AZ,COLUMN(AE41)-$A$5,0)),0) -> 483773.5 | AF41: =IFERROR((VLOOKUP($A41,'Dados StatusInvest'!$A:$AZ,COLUMN(AF41)-$A$5,0)),0) -> 0.27 | AG41: =IFERROR((VLOOKUP($A41,'Dados StatusInvest'!$A:$AZ,COLUMN(AG41)-$A$5,0)),0) -> -1.22 | ... AJ41: =IFERROR((VLOOKUP($A41,'Dados StatusInvest'!$A:$AZ,COLUMN(AJ41)-$A$5,0)),0) | AK41: =IFERROR(__xludf.DUMMYFUNCTION("IFERROR(GOOGLEFINANCE($A41,""high""),"""")"),0.26) -> 0.26 | AL41: =IFERROR(__xludf.DUMMYFUNCTION("IFERROR(GOOGLEFINANCE($A41,""low""),"""")"),0.24) -> 0.24 | AM41: =IFERROR(((AK41-AL41)/AL41),0) -> 0.083333333 | AN41: =IFERROR(__xludf.DUMMYFUNCTION("IFERROR((GOOGLEFINANCE($A41,""volume"")),0)"),200800.0) -> 200800 | AO41: =IFERROR(__xludf.DUMMYFUNCTION("IFERROR((GOOGLEFINANCE($A41,""closeyest"")),"""")"),0.25) -> 0.25 | AP41: =IFERROR(__xludf.DUMMYFUNCTION("IFERROR((GOOGLEFINANCE($A41,""shares"")),"""")"),2.01978758E8) -> 201978758
A42: ='Dados StatusInvest'!A37:A656 -> AZEV4 | B42: =IFERROR(__xludf.DUMMYFUNCTION("IFERROR((GOOGLEFINANCE(A42,""name"")),"""")"),"Azevedo & Travassos SA Preference Shares") -> Azevedo & Travassos SA Preference Shares | C42: =IFERROR((VLOOKUP(LEFT($A42,4),Setor!$A:$E,3,0)),"") -> Bens Industriais | D42: =IFERROR((VLOOKUP(LEFT($A42,4),Setor!$A:$E,4,0)),"") -> Construção e Engenharia | E42: =IFERROR((VLOOKUP(LEFT($A42,4),Setor!$A:$E,5,0)),"") -> Construção Pesada | F42: =IFERROR(__xludf.DUMMYFUNCTION("IFERROR((GOOGLEFINANCE(A42)),"""")"),0.19) -> 0.19 | G42: =IFERROR(__xludf.DUMMYFUNCTION("IFERROR((sparkline(GOOGLEFINANCE($A42,""price"",TODAY()-30,TODAY(),""DAILY""),{""charttype"",""line"";""linewidth"",1;""color"",""#5f88cc""})),"""")"),"") | H42: =IFERROR(__xludf.DUMMYFUNCTION("IFERROR((((GOOGLEFINANCE(A42))-(INDEX(GoogleFinance(A42,""PRICE"",$AQ$1),2,2)))/(INDEX(GoogleFinance(A42,""PRICE"",$AQ$1),2,2))),"""")"),-0.09523809523809519) -> -0.095238095 | I42: =IFERROR(__xludf.DUMMYFUNCTION("IFERROR((GOOGLEFINANCE($A42,""high52"")),"""")"),1.41) -> 1.41 | J42: =IFERROR(__xludf.DUMMYFUNCTION("IFERROR((sparkline(GOOGLEFINANCE($A42,""price"",TODAY()-365,TODAY(),""DAILY""),{""charttype"",""line"";""linewidth"",1;""color"",""#5f88cc""})),"""")"),"") | K42: =IFERROR(__xludf.DUMMYFUNCTION("IFERROR((((GOOGLEFINANCE(A42))-(INDEX(GoogleFinance(A42,""PRICE"",$AP$1),2,2)))/(INDEX(GoogleFinance(A42,""PRICE"",$AP$1),2,2))),"""")"),-0.7738095238095237) -> -0.77380952 | L42: =IFERROR(((F42-I42)/I42),0) -> -0.86524823 | M42: =IFERROR((VLOOKUP($A42,'Dados StatusInvest'!$A:$AZ,COLUMN(M42)-$A$5,0)*VLOOKUP($A42,'Dados StatusInvest'!$A:$AZ,2,0)/$F42/100),0) -> -1.8196 | N42: =IFERROR((VLOOKUP($A42,'Dados StatusInvest'!$A:$AZ,COLUMN(N42)-$A$5,0)/VLOOKUP($A42,'Dados StatusInvest'!$A:$AZ,2,0)*$F42),"") -> -269.37 | O42: =IFERROR((VLOOKUP($A42,'Dados StatusInvest'!$A:$AZ,COLUMN(O42)-$A$5,0)/VLOOKUP($A42,'Dados StatusInvest'!$A:$AZ,2,0)*$F42),0) -> -0.23 | P42: =IFERROR((VLOOKUP($A42,'Dados StatusInvest'!$A:$AZ,COLUMN(P42)-$A$5,0)/VLOOKUP($A42,'Dados StatusInvest'!$A:$AZ,2,0)*$F42),0) -> -0.37 | Q42: =IFERROR((VLOOKUP($A42,'Dados StatusInvest'!$A:$AZ,COLUMN(Q42)-$A$5,0)/100),0) -> -0.0012 | R42: =VLOOKUP($A42,'Dados StatusInvest'!$A:$AZ,COLUMN(R42)-$A$5,0) -> 0.36 | S42: =IFERROR((VLOOKUP($A42,'Dados StatusInvest'!$A:$AZ,COLUMN(S42)-$A$5,0)),0) -> 0.42 | T42: =IFERROR((VLOOKUP($A42,'Dados StatusInvest'!$A:$AZ,COLUMN(T42)-$A$5,0)/VLOOKUP($A42,'Dados StatusInvest'!$A:$AZ,2,0)*$F42),0) -> -0.97 | U42: =IFERROR((VLOOKUP($A42,'Dados StatusInvest'!$A:$AZ,COLUMN(U42)-$A$5,0)-VLOOKUP($A42,'Dados StatusInvest'!$A:$AZ,COLUMN(U42)-$A$5-1,0)+T42),0) -> -0.14 | V42: =IFERROR((VLOOKUP($A42,'Dados StatusInvest'!$A:$AZ,COLUMN(V42)-$A$5,0)),0) -> 0.65 | W42: =IFERROR((VLOOKUP($A42,'Dados StatusInvest'!$A:$AZ,COLUMN(W42)-$A$5,0)),0) -> -453.29 | X42: =IFERROR((VLOOKUP($A42,'Dados StatusInvest'!$A:$AZ,COLUMN(X42)-$A$5,0)/VLOOKUP($A42,'Dados StatusInvest'!$A:$AZ,2,0)*$F42),0) -> -69.02 | Y42: =IFERROR((VLOOKUP($A42,'Dados StatusInvest'!$A:$AZ,COLUMN(Y42)-$A$5,0)/VLOOKUP($A42,'Dados StatusInvest'!$A:$AZ,2,0)*$F42),0) -> -250.88 | Z42: =IFERROR((VLOOKUP($A42,'Dados StatusInvest'!$A:$AZ,COLUMN(Z42)-$A$5,0)),0) -> 0.15 | AA42: =IFERROR((VLOOKUP($A42,'Dados StatusInvest'!$A:$AZ,COLUMN(AA42)-$A$5,0)),0) -> 0.85 | AB42: =IFERROR((VLOOKUP($A42,'Dados StatusInvest'!$A:$AZ,COLUMN(AB42)-$A$5,0)),0) -> 0.26 | AC42: =IFERROR((VLOOKUP($A42,'Dados StatusInvest'!$A:$AZ,COLUMN(AC42)-$A$5,0)),0) -> 144.07 | AD42: =IFERROR((VLOOKUP($A42,'Dados StatusInvest'!$A:$AZ,COLUMN(AD42)-$A$5,0)),0) -> 0 | AE42: =IFERROR((VLOOKUP($A42,'Dados StatusInvest'!$A:$AZ,COLUMN(AE42)-$A$5,0)),0) -> 927072.3 | AF42: =IFERROR((VLOOKUP($A42,'Dados StatusInvest'!$A:$AZ,COLUMN(AF42)-$A$5,0)),0) -> 0.27 | AG42: =IFERROR((VLOOKUP($A42,'Dados StatusInvest'!$A:$AZ,COLUMN(AG42)-$A$5,0)),0) -> -1.22 | ... AJ42: =IFERROR((VLOOKUP($A42,'Dados StatusInvest'!$A:$AZ,COLUMN(AJ42)-$A$5,0)),0) | AK42: =IFERROR(__xludf.DUMMYFUNCTION("IFERROR(GOOGLEFINANCE($A42,""high""),"""")"),0.19) -> 0.19 | AL42: =IFERROR(__xludf.DUMMYFUNCTION("IFERROR(GOOGLEFINANCE($A42,""low""),"""")"),0.18) -> 0.18 | AM42: =IFERROR(((AK42-AL42)/AL42),0) -> 0.055555556 | AN42: =IFERROR(__xludf.DUMMYFUNCTION("IFERROR((GOOGLEFINANCE($A42,""volume"")),0)"),203400.0) -> 203400 | AO42: =IFERROR(__xludf.DUMMYFUNCTION("IFERROR((GOOGLEFINANCE($A42,""closeyest"")),"""")"),0.19) -> 0.19 | AP42: =IFERROR(__xludf.DUMMYFUNCTION("IFERROR((GOOGLEFINANCE($A42,""shares"")),"""")"),3.9077684E8) -> 390776840
A43: ='Dados StatusInvest'!A38:A657 -> AZTE3 | B43: =IFERROR(__xludf.DUMMYFUNCTION("IFERROR((GOOGLEFINANCE(A43,""name"")),"""")"),"Azevedo e Travassos Energia Ord Shs") -> Azevedo e Travassos Energia Ord Shs | C43: =IFERROR((VLOOKUP(LEFT($A43,4),Setor!$A:$E,3,0)),"") | D43: =IFERROR((VLOOKUP(LEFT($A43,4),Setor!$A:$E,4,0)),"") | E43: =IFERROR((VLOOKUP(LEFT($A43,4),Setor!$A:$E,5,0)),"") | F43: =IFERROR(__xludf.DUMMYFUNCTION("IFERROR((GOOGLEFINANCE(A43)),"""")"),0.29) -> 0.29 | G43: =IFERROR(__xludf.DUMMYFUNCTION("IFERROR((sparkline(GOOGLEFINANCE($A43,""price"",TODAY()-30,TODAY(),""DAILY""),{""charttype"",""line"";""linewidth"",1;""color"",""#5f88cc""})),"""")"),"") | H43: =IFERROR(__xludf.DUMMYFUNCTION("IFERROR((((GOOGLEFINANCE(A43))-(INDEX(GoogleFinance(A43,""PRICE"",$AQ$1),2,2)))/(INDEX(GoogleFinance(A43,""PRICE"",$AQ$1),2,2))),"""")"),-0.21621621621621626) -> -0.21621622 | I43: =IFERROR(__xludf.DUMMYFUNCTION("IFERROR((GOOGLEFINANCE($A43,""high52"")),"""")"),1.57) -> 1.57 | J43: =IFERROR(__xludf.DUMMYFUNCTION("IFERROR((sparkline(GOOGLEFINANCE($A43,""price"",TODAY()-365,TODAY(),""DAILY""),{""charttype"",""line"";""linewidth"",1;""color"",""#5f88cc""})),"""")"),"") | K43: =IFERROR(__xludf.DUMMYFUNCTION("IFERROR((((GOOGLEFINANCE(A43))-(INDEX(GoogleFinance(A43,""PRICE"",$AP$1),2,2)))/(INDEX(GoogleFinance(A43,""PRICE"",$AP$1),2,2))),"""")"),-0.7211538461538461) -> -0.72115385 | L43: =IFERROR(((F43-I43)/I43),0) -> -0.81528662 | M43: =IFERROR((VLOOKUP($A43,'Dados StatusInvest'!$A:$AZ,COLUMN(M43)-$A$5,0)*VLOOKUP($A43,'Dados StatusInvest'!$A:$AZ,2,0)/$F43/100),0) -> 0 | N43: =IFERROR((VLOOKUP($A43,'Dados StatusInvest'!$A:$AZ,COLUMN(N43)-$A$5,0)/VLOOKUP($A43,'Dados StatusInvest'!$A:$AZ,2,0)*$F43),"") -> 0 | O43: =IFERROR((VLOOKUP($A43,'Dados StatusInvest'!$A:$AZ,COLUMN(O43)-$A$5,0)/VLOOKUP($A43,'Dados StatusInvest'!$A:$AZ,2,0)*$F43),0) -> 0 | P43: =IFERROR((VLOOKUP($A43,'Dados StatusInvest'!$A:$AZ,COLUMN(P43)-$A$5,0)/VLOOKUP($A43,'Dados StatusInvest'!$A:$AZ,2,0)*$F43),0) -> 0 | Q43: =IFERROR((VLOOKUP($A43,'Dados StatusInvest'!$A:$AZ,COLUMN(Q43)-$A$5,0)/100),0) -> 0 | R43: =VLOOKUP($A43,'Dados StatusInvest'!$A:$AZ,COLUMN(R43)-$A$5,0) -> 0 | S43: =IFERROR((VLOOKUP($A43,'Dados StatusInvest'!$A:$AZ,COLUMN(S43)-$A$5,0)),0) -> 0 | T43: =IFERROR((VLOOKUP($A43,'Dados StatusInvest'!$A:$AZ,COLUMN(T43)-$A$5,0)/VLOOKUP($A43,'Dados StatusInvest'!$A:$AZ,2,0)*$F43),0) -> 0 | U43: =IFERROR((VLOOKUP($A43,'Dados StatusInvest'!$A:$AZ,COLUMN(U43)-$A$5,0)-VLOOKUP($A43,'Dados StatusInvest'!$A:$AZ,COLUMN(U43)-$A$5-1,0)+T43),0) -> 0 | V43: =IFERROR((VLOOKUP($A43,'Dados StatusInvest'!$A:$AZ,COLUMN(V43)-$A$5,0)),0) -> 0 | W43: =IFERROR((VLOOKUP($A43,'Dados StatusInvest'!$A:$AZ,COLUMN(W43)-$A$5,0)),0) -> 0 | X43: =IFERROR((VLOOKUP($A43,'Dados StatusInvest'!$A:$AZ,COLUMN(X43)-$A$5,0)/VLOOKUP($A43,'Dados StatusInvest'!$A:$AZ,2,0)*$F43),0) -> 0 | Y43: =IFERROR((VLOOKUP($A43,'Dados StatusInvest'!$A:$AZ,COLUMN(Y43)-$A$5,0)/VLOOKUP($A43,'Dados StatusInvest'!$A:$AZ,2,0)*$F43),0) -> 0 | Z43: =IFERROR((VLOOKUP($A43,'Dados StatusInvest'!$A:$AZ,COLUMN(Z43)-$A$5,0)),0) -> 0 | AA43: =IFERROR((VLOOKUP($A43,'Dados StatusInvest'!$A:$AZ,COLUMN(AA43)-$A$5,0)),0) -> 0 | AB43: =IFERROR((VLOOKUP($A43,'Dados StatusInvest'!$A:$AZ,COLUMN(AB43)-$A$5,0)),0) -> 0 | AC43: =IFERROR((VLOOKUP($A43,'Dados StatusInvest'!$A:$AZ,COLUMN(AC43)-$A$5,0)),0) -> 0 | AD43: =IFERROR((VLOOKUP($A43,'Dados StatusInvest'!$A:$AZ,COLUMN(AD43)-$A$5,0)),0) -> 0 | AE43: =IFERROR((VLOOKUP($A43,'Dados StatusInvest'!$A:$AZ,COLUMN(AE43)-$A$5,0)),0) -> 803727.6 | AF43: =IFERROR((VLOOKUP($A43,'Dados StatusInvest'!$A:$AZ,COLUMN(AF43)-$A$5,0)),0) -> 0 | AG43: =IFERROR((VLOOKUP($A43,'Dados StatusInvest'!$A:$AZ,COLUMN(AG43)-$A$5,0)),0) -> 0 | ... AJ43: =IFERROR((VLOOKUP($A43,'Dados StatusInvest'!$A:$AZ,COLUMN(AJ43)-$A$5,0)),0) | AK43: =IFERROR(__xludf.DUMMYFUNCTION("IFERROR(GOOGLEFINANCE($A43,""high""),"""")"),0.29) -> 0.29 | AL43: =IFERROR(__xludf.DUMMYFUNCTION("IFERROR(GOOGLEFINANCE($A43,""low""),"""")"),0.27) -> 0.27 | AM43: =IFERROR(((AK43-AL43)/AL43),0) -> 0.074074074 | AN43: =IFERROR(__xludf.DUMMYFUNCTION("IFERROR((GOOGLEFINANCE($A43,""volume"")),0)"),1375600.0) -> 1375600 | AO43: =IFERROR(__xludf.DUMMYFUNCTION("IFERROR((GOOGLEFINANCE($A43,""closeyest"")),"""")"),0.27) -> 0.27 | AP43: =IFERROR(__xludf.DUMMYFUNCTION("IFERROR((GOOGLEFINANCE($A43,""shares"")),"""")"),3.39094779E8) -> 339094779
A44: ='Dados StatusInvest'!A39:A658 -> AZUL53 | B44: =IFERROR(__xludf.DUMMYFUNCTION("IFERROR((GOOGLEFINANCE(A44,""name"")),"""")"),"Azul Ord Shs") -> Azul Ord Shs | C44: =IFERROR((VLOOKUP(LEFT($A44,4),Setor!$A:$E,3,0)),"") -> Bens Industriais | D44: =IFERROR((VLOOKUP(LEFT($A44,4),Setor!$A:$E,4,0)),"") -> Transporte | E44: =IFERROR((VLOOKUP(LEFT($A44,4),Setor!$A:$E,5,0)),"") -> Transporte Aéreo | F44: =IFERROR(__xludf.DUMMYFUNCTION("IFERROR((GOOGLEFINANCE(A44)),"""")"),159.6) -> 159.6 | G44: =IFERROR(__xludf.DUMMYFUNCTION("IFERROR((sparkline(GOOGLEFINANCE($A44,""price"",TODAY()-30,TODAY(),""DAILY""),{""charttype"",""line"";""linewidth"",1;""color"",""#5f88cc""})),"""")"),"") | H44: =IFERROR(__xludf.DUMMYFUNCTION("IFERROR((((GOOGLEFINANCE(A44))-(INDEX(GoogleFinance(A44,""PRICE"",$AQ$1),2,2)))/(INDEX(GoogleFinance(A44,""PRICE"",$AQ$1),2,2))),"""")"),-0.8108444444444444) -> -0.81084444 | I44: =IFERROR(__xludf.DUMMYFUNCTION("IFERROR((GOOGLEFINANCE($A44,""high52"")),"""")"),175.0) -> 175 | J44: =IFERROR(__xludf.DUMMYFUNCTION("IFERROR((sparkline(GOOGLEFINANCE($A44,""price"",TODAY()-365,TODAY(),""DAILY""),{""charttype"",""line"";""linewidth"",1;""color"",""#5f88cc""})),"""")"),"") | K44: =IFERROR(__xludf.DUMMYFUNCTION("IFERROR((((GOOGLEFINANCE(A44))-(INDEX(GoogleFinance(A44,""PRICE"",$AP$1),2,2)))/(INDEX(GoogleFinance(A44,""PRICE"",$AP$1),2,2))),"""")"),"") | L44: =IFERROR(((F44-I44)/I44),0) -> -0.088 | M44: =IFERROR((VLOOKUP($A44,'Dados StatusInvest'!$A:$AZ,COLUMN(M44)-$A$5,0)*VLOOKUP($A44,'Dados StatusInvest'!$A:$AZ,2,0)/$F44/100),0) -> 0.15262375 | N44: =IFERROR((VLOOKUP($A44,'Dados StatusInvest'!$A:$AZ,COLUMN(N44)-$A$5,0)/VLOOKUP($A44,'Dados StatusInvest'!$A:$AZ,2,0)*$F44),"") -> 71.255262 | O44: =IFERROR((VLOOKUP($A44,'Dados StatusInvest'!$A:$AZ,COLUMN(O44)-$A$5,0)/VLOOKUP($A44,'Dados StatusInvest'!$A:$AZ,2,0)*$F44),0) -> 2696176.3 | P44: =IFERROR((VLOOKUP($A44,'Dados StatusInvest'!$A:$AZ,COLUMN(P44)-$A$5,0)/VLOOKUP($A44,'Dados StatusInvest'!$A:$AZ,2,0)*$F44),0) -> 16049.582 | Q44: =IFERROR((VLOOKUP($A44,'Dados StatusInvest'!$A:$AZ,COLUMN(Q44)-$A$5,0)/100),0) -> 0.1099 | R44: =VLOOKUP($A44,'Dados StatusInvest'!$A:$AZ,COLUMN(R44)-$A$5,0) -> 0 | S44: =IFERROR((VLOOKUP($A44,'Dados StatusInvest'!$A:$AZ,COLUMN(S44)-$A$5,0)),0) -> 411381.4 | T44: =IFERROR((VLOOKUP($A44,'Dados StatusInvest'!$A:$AZ,COLUMN(T44)-$A$5,0)/VLOOKUP($A44,'Dados StatusInvest'!$A:$AZ,2,0)*$F44),0) -> -447273.84 | U44: =IFERROR((VLOOKUP($A44,'Dados StatusInvest'!$A:$AZ,COLUMN(U44)-$A$5,0)-VLOOKUP($A44,'Dados StatusInvest'!$A:$AZ,COLUMN(U44)-$A$5-1,0)+T44),0) -> -429397.84 | V44: =IFERROR((VLOOKUP($A44,'Dados StatusInvest'!$A:$AZ,COLUMN(V44)-$A$5,0)),0) -> 0.27 | W44: =IFERROR((VLOOKUP($A44,'Dados StatusInvest'!$A:$AZ,COLUMN(W44)-$A$5,0)),0) -> -57.23 | X44: =IFERROR((VLOOKUP($A44,'Dados StatusInvest'!$A:$AZ,COLUMN(X44)-$A$5,0)/VLOOKUP($A44,'Dados StatusInvest'!$A:$AZ,2,0)*$F44),0) -> 55.756874 | Y44: =IFERROR((VLOOKUP($A44,'Dados StatusInvest'!$A:$AZ,COLUMN(Y44)-$A$5,0)/VLOOKUP($A44,'Dados StatusInvest'!$A:$AZ,2,0)*$F44),0) -> 31.939643 | Z44: =IFERROR((VLOOKUP($A44,'Dados StatusInvest'!$A:$AZ,COLUMN(Z44)-$A$5,0)),0) -> -0.99 | AA44: =IFERROR((VLOOKUP($A44,'Dados StatusInvest'!$A:$AZ,COLUMN(AA44)-$A$5,0)),0) -> 1.99 | AB44: =IFERROR((VLOOKUP($A44,'Dados StatusInvest'!$A:$AZ,COLUMN(AB44)-$A$5,0)),0) -> 0.78 | AC44: =IFERROR((VLOOKUP($A44,'Dados StatusInvest'!$A:$AZ,COLUMN(AC44)-$A$5,0)),0) -> 11.28 | AD44: =IFERROR((VLOOKUP($A44,'Dados StatusInvest'!$A:$AZ,COLUMN(AD44)-$A$5,0)),0) -> 0 | AE44: =IFERROR((VLOOKUP($A44,'Dados StatusInvest'!$A:$AZ,COLUMN(AE44)-$A$5,0)),0) -> 3868102 | AF44: =IFERROR((VLOOKUP($A44,'Dados StatusInvest'!$A:$AZ,COLUMN(AF44)-$A$5,0)),0) -> 0 | AG44: =IFERROR((VLOOKUP($A44,'Dados StatusInvest'!$A:$AZ,COLUMN(AG44)-$A$5,0)),0) -> 0 | ... AJ44: =IFERROR((VLOOKUP($A44,'Dados StatusInvest'!$A:$AZ,COLUMN(AJ44)-$A$5,0)),0) | AK44: =IFERROR(__xludf.DUMMYFUNCTION("IFERROR(GOOGLEFINANCE($A44,""high""),"""")"),175.0) -> 175 | AL44: =IFERROR(__xludf.DUMMYFUNCTION("IFERROR(GOOGLEFINANCE($A44,""low""),"""")"),152.01) -> 152.01 | AM44: =IFERROR(((AK44-AL44)/AL44),0) -> 0.15124005 | AN44: =IFERROR(__xludf.DUMMYFUNCTION("IFERROR((GOOGLEFINANCE($A44,""volume"")),0)"),2.328032704E9) -> 2328032704 | AO44: =IFERROR(__xludf.DUMMYFUNCTION("IFERROR((GOOGLEFINANCE($A44,""closeyest"")),"""")"),162.5) -> 162.5 | AP44: =IFERROR(__xludf.DUMMYFUNCTION("IFERROR((GOOGLEFINANCE($A44,""shares"")),"""")"),9.2531440949E12) -> 9253144094900
A45: ='Dados StatusInvest'!A40:A659 -> AZUL54 | B45: =IFERROR(__xludf.DUMMYFUNCTION("IFERROR((GOOGLEFINANCE(A45,""name"")),"""")"),"") | C45: =IFERROR((VLOOKUP(LEFT($A45,4),Setor!$A:$E,3,0)),"") -> Bens Industriais | D45: =IFERROR((VLOOKUP(LEFT($A45,4),Setor!$A:$E,4,0)),"") -> Transporte | E45: =IFERROR((VLOOKUP(LEFT($A45,4),Setor!$A:$E,5,0)),"") -> Transporte Aéreo | F45: =IFERROR(__xludf.DUMMYFUNCTION("IFERROR((GOOGLEFINANCE(A45)),"""")"),"") | G45: =IFERROR(__xludf.DUMMYFUNCTION("IFERROR((sparkline(GOOGLEFINANCE($A45,""price"",TODAY()-30,TODAY(),""DAILY""),{""charttype"",""line"";""linewidth"",1;""color"",""#5f88cc""})),"""")"),"") | H45: =IFERROR(__xludf.DUMMYFUNCTION("IFERROR((((GOOGLEFINANCE(A45))-(INDEX(GoogleFinance(A45,""PRICE"",$AQ$1),2,2)))/(INDEX(GoogleFinance(A45,""PRICE"",$AQ$1),2,2))),"""")"),"") | I45: =IFERROR(__xludf.DUMMYFUNCTION("IFERROR((GOOGLEFINANCE($A45,""high52"")),"""")"),"") | J45: =IFERROR(__xludf.DUMMYFUNCTION("IFERROR((sparkline(GOOGLEFINANCE($A45,""price"",TODAY()-365,TODAY(),""DAILY""),{""charttype"",""line"";""linewidth"",1;""color"",""#5f88cc""})),"""")"),"") | K45: =IFERROR(__xludf.DUMMYFUNCTION("IFERROR((((GOOGLEFINANCE(A45))-(INDEX(GoogleFinance(A45,""PRICE"",$AP$1),2,2)))/(INDEX(GoogleFinance(A45,""PRICE"",$AP$1),2,2))),"""")"),"") | L45: =IFERROR(((F45-I45)/I45),0) -> 0 | M45: =IFERROR((VLOOKUP($A45,'Dados StatusInvest'!$A:$AZ,COLUMN(M45)-$A$5,0)*VLOOKUP($A45,'Dados StatusInvest'!$A:$AZ,2,0)/$F45/100),0) -> 0 | N45: =IFERROR((VLOOKUP($A45,'Dados StatusInvest'!$A:$AZ,COLUMN(N45)-$A$5,0)/VLOOKUP($A45,'Dados StatusInvest'!$A:$AZ,2,0)*$F45),"") -> 0 | O45: =IFERROR((VLOOKUP($A45,'Dados StatusInvest'!$A:$AZ,COLUMN(O45)-$A$5,0)/VLOOKUP($A45,'Dados StatusInvest'!$A:$AZ,2,0)*$F45),0) -> 0 | P45: =IFERROR((VLOOKUP($A45,'Dados StatusInvest'!$A:$AZ,COLUMN(P45)-$A$5,0)/VLOOKUP($A45,'Dados StatusInvest'!$A:$AZ,2,0)*$F45),0) -> 0 | Q45: =IFERROR((VLOOKUP($A45,'Dados StatusInvest'!$A:$AZ,COLUMN(Q45)-$A$5,0)/100),0) -> 0.1099 | R45: =VLOOKUP($A45,'Dados StatusInvest'!$A:$AZ,COLUMN(R45)-$A$5,0) -> 0 | S45: =IFERROR((VLOOKUP($A45,'Dados StatusInvest'!$A:$AZ,COLUMN(S45)-$A$5,0)),0) -> 183539.4 | T45: =IFERROR((VLOOKUP($A45,'Dados StatusInvest'!$A:$AZ,COLUMN(T45)-$A$5,0)/VLOOKUP($A45,'Dados StatusInvest'!$A:$AZ,2,0)*$F45),0) -> 0 | U45: =IFERROR((VLOOKUP($A45,'Dados StatusInvest'!$A:$AZ,COLUMN(U45)-$A$5,0)-VLOOKUP($A45,'Dados StatusInvest'!$A:$AZ,COLUMN(U45)-$A$5-1,0)+T45),0) -> 7975 | V45: =IFERROR((VLOOKUP($A45,'Dados StatusInvest'!$A:$AZ,COLUMN(V45)-$A$5,0)),0) -> 0.27 | W45: =IFERROR((VLOOKUP($A45,'Dados StatusInvest'!$A:$AZ,COLUMN(W45)-$A$5,0)),0) -> -57.23 | X45: =IFERROR((VLOOKUP($A45,'Dados StatusInvest'!$A:$AZ,COLUMN(X45)-$A$5,0)/VLOOKUP($A45,'Dados StatusInvest'!$A:$AZ,2,0)*$F45),0) -> 0 | Y45: =IFERROR((VLOOKUP($A45,'Dados StatusInvest'!$A:$AZ,COLUMN(Y45)-$A$5,0)/VLOOKUP($A45,'Dados StatusInvest'!$A:$AZ,2,0)*$F45),0) -> 0 | Z45: =IFERROR((VLOOKUP($A45,'Dados StatusInvest'!$A:$AZ,COLUMN(Z45)-$A$5,0)),0) -> -0.99 | AA45: =IFERROR((VLOOKUP($A45,'Dados StatusInvest'!$A:$AZ,COLUMN(AA45)-$A$5,0)),0) -> 1.99 | AB45: =IFERROR((VLOOKUP($A45,'Dados StatusInvest'!$A:$AZ,COLUMN(AB45)-$A$5,0)),0) -> 0.78 | AC45: =IFERROR((VLOOKUP($A45,'Dados StatusInvest'!$A:$AZ,COLUMN(AC45)-$A$5,0)),0) -> 11.28 | AD45: =IFERROR((VLOOKUP($A45,'Dados StatusInvest'!$A:$AZ,COLUMN(AD45)-$A$5,0)),0) -> 0 | AE45: =IFERROR((VLOOKUP($A45,'Dados StatusInvest'!$A:$AZ,COLUMN(AE45)-$A$5,0)),0) -> 20945788 | AF45: =IFERROR((VLOOKUP($A45,'Dados StatusInvest'!$A:$AZ,COLUMN(AF45)-$A$5,0)),0) -> 0 | AG45: =IFERROR((VLOOKUP($A45,'Dados StatusInvest'!$A:$AZ,COLUMN(AG45)-$A$5,0)),0) -> 0 | ... AJ45: =IFERROR((VLOOKUP($A45,'Dados StatusInvest'!$A:$AZ,COLUMN(AJ45)-$A$5,0)),0) | AK45: =IFERROR(__xludf.DUMMYFUNCTION("IFERROR(GOOGLEFINANCE($A45,""high""),"""")"),"") | AL45: =IFERROR(__xludf.DUMMYFUNCTION("IFERROR(GOOGLEFINANCE($A45,""low""),"""")"),"") | AM45: =IFERROR(((AK45-AL45)/AL45),0) -> 0 | AN45: =IFERROR(__xludf.DUMMYFUNCTION("IFERROR((GOOGLEFINANCE($A45,""volume"")),0)"),0.0) -> 0 | AO45: =IFERROR(__xludf.DUMMYFUNCTION("IFERROR((GOOGLEFINANCE($A45,""closeyest"")),"""")"),"") | AP45: =IFERROR(__xludf.DUMMYFUNCTION("IFERROR((GOOGLEFINANCE($A45,""shares"")),"""")"),"")
A46: ='Dados StatusInvest'!A41:A660 -> AZZA3 | B46: =IFERROR(__xludf.DUMMYFUNCTION("IFERROR((GOOGLEFINANCE(A46,""name"")),"""")"),"Azzas 2154 SA") -> Azzas 2154 SA | C46: =IFERROR((VLOOKUP(LEFT($A46,4),Setor!$A:$E,3,0)),"") | D46: =IFERROR((VLOOKUP(LEFT($A46,4),Setor!$A:$E,4,0)),"") | E46: =IFERROR((VLOOKUP(LEFT($A46,4),Setor!$A:$E,5,0)),"") | F46: =IFERROR(__xludf.DUMMYFUNCTION("IFERROR((GOOGLEFINANCE(A46)),"""")"),25.11) -> 25.11 | G46: =IFERROR(__xludf.DUMMYFUNCTION("IFERROR((sparkline(GOOGLEFINANCE($A46,""price"",TODAY()-30,TODAY(),""DAILY""),{""charttype"",""line"";""linewidth"",1;""color"",""#5f88cc""})),"""")"),"") | H46: =IFERROR(__xludf.DUMMYFUNCTION("IFERROR((((GOOGLEFINANCE(A46))-(INDEX(GoogleFinance(A46,""PRICE"",$AQ$1),2,2)))/(INDEX(GoogleFinance(A46,""PRICE"",$AQ$1),2,2))),"""")"),0.014545454545454523) -> 0.014545455 | I46: =IFERROR(__xludf.DUMMYFUNCTION("IFERROR((GOOGLEFINANCE($A46,""high52"")),"""")"),41.49) -> 41.49 | J46: =IFERROR(__xludf.DUMMYFUNCTION("IFERROR((sparkline(GOOGLEFINANCE($A46,""price"",TODAY()-365,TODAY(),""DAILY""),{""charttype"",""line"";""linewidth"",1;""color"",""#5f88cc""})),"""")"),"") | K46: =IFERROR(__xludf.DUMMYFUNCTION("IFERROR((((GOOGLEFINANCE(A46))-(INDEX(GoogleFinance(A46,""PRICE"",$AP$1),2,2)))/(INDEX(GoogleFinance(A46,""PRICE"",$AP$1),2,2))),"""")"),-0.21037735849056607) -> -0.21037736 | L46: =IFERROR(((F46-I46)/I46),0) -> -0.39479393 | M46: =IFERROR((VLOOKUP($A46,'Dados StatusInvest'!$A:$AZ,COLUMN(M46)-$A$5,0)*VLOOKUP($A46,'Dados StatusInvest'!$A:$AZ,2,0)/$F46/100),0) -> 0.058311111 | N46: =IFERROR((VLOOKUP($A46,'Dados StatusInvest'!$A:$AZ,COLUMN(N46)-$A$5,0)/VLOOKUP($A46,'Dados StatusInvest'!$A:$AZ,2,0)*$F46),"") -> 6.2231707 | O46: =IFERROR((VLOOKUP($A46,'Dados StatusInvest'!$A:$AZ,COLUMN(O46)-$A$5,0)/VLOOKUP($A46,'Dados StatusInvest'!$A:$AZ,2,0)*$F46),0) -> 7.5171951 | P46: =IFERROR((VLOOKUP($A46,'Dados StatusInvest'!$A:$AZ,COLUMN(P46)-$A$5,0)/VLOOKUP($A46,'Dados StatusInvest'!$A:$AZ,2,0)*$F46),0) -> 10.855976 | Q46: =IFERROR((VLOOKUP($A46,'Dados StatusInvest'!$A:$AZ,COLUMN(Q46)-$A$5,0)/100),0) -> 0.0338 | R46: =VLOOKUP($A46,'Dados StatusInvest'!$A:$AZ,COLUMN(R46)-$A$5,0) -> 0.28 | S46: =IFERROR((VLOOKUP($A46,'Dados StatusInvest'!$A:$AZ,COLUMN(S46)-$A$5,0)),0) -> 0.44 | T46: =IFERROR((VLOOKUP($A46,'Dados StatusInvest'!$A:$AZ,COLUMN(T46)-$A$5,0)/VLOOKUP($A46,'Dados StatusInvest'!$A:$AZ,2,0)*$F46),0) -> 1.6002439 | U46: =IFERROR((VLOOKUP($A46,'Dados StatusInvest'!$A:$AZ,COLUMN(U46)-$A$5,0)-VLOOKUP($A46,'Dados StatusInvest'!$A:$AZ,COLUMN(U46)-$A$5-1,0)+T46),0) -> -0.6297561 | V46: =IFERROR((VLOOKUP($A46,'Dados StatusInvest'!$A:$AZ,COLUMN(V46)-$A$5,0)),0) -> 1.9 | W46: =IFERROR((VLOOKUP($A46,'Dados StatusInvest'!$A:$AZ,COLUMN(W46)-$A$5,0)),0) -> 9.02 | X46: =IFERROR((VLOOKUP($A46,'Dados StatusInvest'!$A:$AZ,COLUMN(X46)-$A$5,0)/VLOOKUP($A46,'Dados StatusInvest'!$A:$AZ,2,0)*$F46),0) -> 4.7908537 | Y46: =IFERROR((VLOOKUP($A46,'Dados StatusInvest'!$A:$AZ,COLUMN(Y46)-$A$5,0)/VLOOKUP($A46,'Dados StatusInvest'!$A:$AZ,2,0)*$F46),0) -> -1.817561 | Z46: =IFERROR((VLOOKUP($A46,'Dados StatusInvest'!$A:$AZ,COLUMN(Z46)-$A$5,0)),0) -> 0.54 | AA46: =IFERROR((VLOOKUP($A46,'Dados StatusInvest'!$A:$AZ,COLUMN(AA46)-$A$5,0)),0) -> 0.46 | AB46: =IFERROR((VLOOKUP($A46,'Dados StatusInvest'!$A:$AZ,COLUMN(AB46)-$A$5,0)),0) -> 0.77 | AC46: =IFERROR((VLOOKUP($A46,'Dados StatusInvest'!$A:$AZ,COLUMN(AC46)-$A$5,0)),0) -> 37.92 | AD46: =IFERROR((VLOOKUP($A46,'Dados StatusInvest'!$A:$AZ,COLUMN(AD46)-$A$5,0)),0) -> 35.96 | AE46: =IFERROR((VLOOKUP($A46,'Dados StatusInvest'!$A:$AZ,COLUMN(AE46)-$A$5,0)),0) -> 70676079 | AF46: =IFERROR((VLOOKUP($A46,'Dados StatusInvest'!$A:$AZ,COLUMN(AF46)-$A$5,0)),0) -> 40.43 | AG46: =IFERROR((VLOOKUP($A46,'Dados StatusInvest'!$A:$AZ,COLUMN(AG46)-$A$5,0)),0) -> 3.65 | ... AJ46: =IFERROR((VLOOKUP($A46,'Dados StatusInvest'!$A:$AZ,COLUMN(AJ46)-$A$5,0)),0) | AK46: =IFERROR(__xludf.DUMMYFUNCTION("IFERROR(GOOGLEFINANCE($A46,""high""),"""")"),25.29) -> 25.29 | AL46: =IFERROR(__xludf.DUMMYFUNCTION("IFERROR(GOOGLEFINANCE($A46,""low""),"""")"),25.02) -> 25.02 | AM46: =IFERROR(((AK46-AL46)/AL46),0) -> 0.010791367 | AN46: =IFERROR(__xludf.DUMMYFUNCTION("IFERROR((GOOGLEFINANCE($A46,""volume"")),0)"),148700.0) -> 148700 | AO46: =IFERROR(__xludf.DUMMYFUNCTION("IFERROR((GOOGLEFINANCE($A46,""closeyest"")),"""")"),25.42) -> 25.42 | AP46: =IFERROR(__xludf.DUMMYFUNCTION("IFERROR((GOOGLEFINANCE($A46,""shares"")),"""")"),2.06489813E8) -> 206489813
A47: ='Dados StatusInvest'!A42:A661 -> B3SA3 | B47: =IFERROR(__xludf.DUMMYFUNCTION("IFERROR((GOOGLEFINANCE(A47,""name"")),"""")"),"B3 SA Brasil Bolsa Balcao") -> B3 SA Brasil Bolsa Balcao | C47: =IFERROR((VLOOKUP(LEFT($A47,4),Setor!$A:$E,3,0)),"") -> Financeiro | D47: =IFERROR((VLOOKUP(LEFT($A47,4),Setor!$A:$E,4,0)),"") -> Serviços Financeiros Diversos | E47: =IFERROR((VLOOKUP(LEFT($A47,4),Setor!$A:$E,5,0)),"") -> Serviços Financeiros Diversos | F47: =IFERROR(__xludf.DUMMYFUNCTION("IFERROR((GOOGLEFINANCE(A47)),"""")"),17.52) -> 17.52 | G47: =IFERROR(__xludf.DUMMYFUNCTION("IFERROR((sparkline(GOOGLEFINANCE($A47,""price"",TODAY()-30,TODAY(),""DAILY""),{""charttype"",""line"";""linewidth"",1;""color"",""#5f88cc""})),"""")"),"") | H47: =IFERROR(__xludf.DUMMYFUNCTION("IFERROR((((GOOGLEFINANCE(A47))-(INDEX(GoogleFinance(A47,""PRICE"",$AQ$1),2,2)))/(INDEX(GoogleFinance(A47,""PRICE"",$AQ$1),2,2))),"""")"),0.13032258064516125) -> 0.13032258 | I47: =IFERROR(__xludf.DUMMYFUNCTION("IFERROR((GOOGLEFINANCE($A47,""high52"")),"""")"),17.75) -> 17.75 | J47: =IFERROR(__xludf.DUMMYFUNCTION("IFERROR((sparkline(GOOGLEFINANCE($A47,""price"",TODAY()-365,TODAY(),""DAILY""),{""charttype"",""line"";""linewidth"",1;""color"",""#5f88cc""})),"""")"),"") | K47: =IFERROR(__xludf.DUMMYFUNCTION("IFERROR((((GOOGLEFINANCE(A47))-(INDEX(GoogleFinance(A47,""PRICE"",$AP$1),2,2)))/(INDEX(GoogleFinance(A47,""PRICE"",$AP$1),2,2))),"""")"),0.5518157661647476) -> 0.55181577 | L47: =IFERROR(((F47-I47)/I47),0) -> -0.012957746 | M47: =IFERROR((VLOOKUP($A47,'Dados StatusInvest'!$A:$AZ,COLUMN(M47)-$A$5,0)*VLOOKUP($A47,'Dados StatusInvest'!$A:$AZ,2,0)/$F47/100),0) -> 0.59774543 | N47: =IFERROR((VLOOKUP($A47,'Dados StatusInvest'!$A:$AZ,COLUMN(N47)-$A$5,0)/VLOOKUP($A47,'Dados StatusInvest'!$A:$AZ,2,0)*$F47),"") -> 44.229363 | O47: =IFERROR((VLOOKUP($A47,'Dados StatusInvest'!$A:$AZ,COLUMN(O47)-$A$5,0)/VLOOKUP($A47,'Dados StatusInvest'!$A:$AZ,2,0)*$F47),0) -> 14.430558 | P47: =IFERROR((VLOOKUP($A47,'Dados StatusInvest'!$A:$AZ,COLUMN(P47)-$A$5,0)/VLOOKUP($A47,'Dados StatusInvest'!$A:$AZ,2,0)*$F47),0) -> 14.25289 | Q47: =IFERROR((VLOOKUP($A47,'Dados StatusInvest'!$A:$AZ,COLUMN(Q47)-$A$5,0)/100),0) -> -0.0018 | R47: =VLOOKUP($A47,'Dados StatusInvest'!$A:$AZ,COLUMN(R47)-$A$5,0) -> -0.06 | S47: =IFERROR((VLOOKUP($A47,'Dados StatusInvest'!$A:$AZ,COLUMN(S47)-$A$5,0)),0) -> 8.63 | T47: =IFERROR((VLOOKUP($A47,'Dados StatusInvest'!$A:$AZ,COLUMN(T47)-$A$5,0)/VLOOKUP($A47,'Dados StatusInvest'!$A:$AZ,2,0)*$F47),0) -> 8.666231 | U47: =IFERROR((VLOOKUP($A47,'Dados StatusInvest'!$A:$AZ,COLUMN(U47)-$A$5,0)-VLOOKUP($A47,'Dados StatusInvest'!$A:$AZ,COLUMN(U47)-$A$5-1,0)+T47),0) -> -3.213769 | V47: =IFERROR((VLOOKUP($A47,'Dados StatusInvest'!$A:$AZ,COLUMN(V47)-$A$5,0)),0) -> 2.62 | W47: =IFERROR((VLOOKUP($A47,'Dados StatusInvest'!$A:$AZ,COLUMN(W47)-$A$5,0)),0) -> 24.55 | X47: =IFERROR((VLOOKUP($A47,'Dados StatusInvest'!$A:$AZ,COLUMN(X47)-$A$5,0)/VLOOKUP($A47,'Dados StatusInvest'!$A:$AZ,2,0)*$F47),0) -> 10.127054 | Y47: =IFERROR((VLOOKUP($A47,'Dados StatusInvest'!$A:$AZ,COLUMN(Y47)-$A$5,0)/VLOOKUP($A47,'Dados StatusInvest'!$A:$AZ,2,0)*$F47),0) -> 9.3472901 | Z47: =IFERROR((VLOOKUP($A47,'Dados StatusInvest'!$A:$AZ,COLUMN(Z47)-$A$5,0)),0) -> 0.42 | AA47: =IFERROR((VLOOKUP($A47,'Dados StatusInvest'!$A:$AZ,COLUMN(AA47)-$A$5,0)),0) -> 0.58 | AB47: =IFERROR((VLOOKUP($A47,'Dados StatusInvest'!$A:$AZ,COLUMN(AB47)-$A$5,0)),0) -> 0.23 | AC47: =IFERROR((VLOOKUP($A47,'Dados StatusInvest'!$A:$AZ,COLUMN(AC47)-$A$5,0)),0) -> 12.34 | AD47: =IFERROR((VLOOKUP($A47,'Dados StatusInvest'!$A:$AZ,COLUMN(AD47)-$A$5,0)),0) -> 12.34 | AE47: =IFERROR((VLOOKUP($A47,'Dados StatusInvest'!$A:$AZ,COLUMN(AE47)-$A$5,0)),0) -> 866000000 | AF47: =IFERROR((VLOOKUP($A47,'Dados StatusInvest'!$A:$AZ,COLUMN(AF47)-$A$5,0)),0) -> 3.76 | AG47: =IFERROR((VLOOKUP($A47,'Dados StatusInvest'!$A:$AZ,COLUMN(AG47)-$A$5,0)),0) -> 0.92 | ... AJ47: =IFERROR((VLOOKUP($A47,'Dados StatusInvest'!$A:$AZ,COLUMN(AJ47)-$A$5,0)),0) | AK47: =IFERROR(__xludf.DUMMYFUNCTION("IFERROR(GOOGLEFINANCE($A47,""high""),"""")"),17.64) -> 17.64 | AL47: =IFERROR(__xludf.DUMMYFUNCTION("IFERROR(GOOGLEFINANCE($A47,""low""),"""")"),17.5) -> 17.5 | AM47: =IFERROR(((AK47-AL47)/AL47),0) -> 0.008 | AN47: =IFERROR(__xludf.DUMMYFUNCTION("IFERROR((GOOGLEFINANCE($A47,""volume"")),0)"),1476100.0) -> 1476100 | AO47: =IFERROR(__xludf.DUMMYFUNCTION("IFERROR((GOOGLEFINANCE($A47,""closeyest"")),"""")"),17.75) -> 17.75 | AP47: =IFERROR(__xludf.DUMMYFUNCTION("IFERROR((GOOGLEFINANCE($A47,""shares"")),"""")"),5.2665E9) -> 5266500000
A48: ='Dados StatusInvest'!A43:A662 -> BAHI3 | B48: =IFERROR(__xludf.DUMMYFUNCTION("IFERROR((GOOGLEFINANCE(A48,""name"")),"""")"),"") | C48: =IFERROR((VLOOKUP(LEFT($A48,4),Setor!$A:$E,3,0)),"") -> Consumo Cíclico | D48: =IFERROR((VLOOKUP(LEFT($A48,4),Setor!$A:$E,4,0)),"") -> Diversos | E48: =IFERROR((VLOOKUP(LEFT($A48,4),Setor!$A:$E,5,0)),"") -> Serviços Educacionais | F48: =IFERROR(__xludf.DUMMYFUNCTION("IFERROR((GOOGLEFINANCE(A48)),"""")"),"") | G48: =IFERROR(__xludf.DUMMYFUNCTION("IFERROR((sparkline(GOOGLEFINANCE($A48,""price"",TODAY()-30,TODAY(),""DAILY""),{""charttype"",""line"";""linewidth"",1;""color"",""#5f88cc""})),"""")"),"") | H48: =IFERROR(__xludf.DUMMYFUNCTION("IFERROR((((GOOGLEFINANCE(A48))-(INDEX(GoogleFinance(A48,""PRICE"",$AQ$1),2,2)))/(INDEX(GoogleFinance(A48,""PRICE"",$AQ$1),2,2))),"""")"),"") | I48: =IFERROR(__xludf.DUMMYFUNCTION("IFERROR((GOOGLEFINANCE($A48,""high52"")),"""")"),"") | J48: =IFERROR(__xludf.DUMMYFUNCTION("IFERROR((sparkline(GOOGLEFINANCE($A48,""price"",TODAY()-365,TODAY(),""DAILY""),{""charttype"",""line"";""linewidth"",1;""color"",""#5f88cc""})),"""")"),"") | K48: =IFERROR(__xludf.DUMMYFUNCTION("IFERROR((((GOOGLEFINANCE(A48))-(INDEX(GoogleFinance(A48,""PRICE"",$AP$1),2,2)))/(INDEX(GoogleFinance(A48,""PRICE"",$AP$1),2,2))),"""")"),"") | L48: =IFERROR(((F48-I48)/I48),0) -> 0 | M48: =IFERROR((VLOOKUP($A48,'Dados StatusInvest'!$A:$AZ,COLUMN(M48)-$A$5,0)*VLOOKUP($A48,'Dados StatusInvest'!$A:$AZ,2,0)/$F48/100),0) -> 0 | N48: =IFERROR((VLOOKUP($A48,'Dados StatusInvest'!$A:$AZ,COLUMN(N48)-$A$5,0)/VLOOKUP($A48,'Dados StatusInvest'!$A:$AZ,2,0)*$F48),"") -> 0 | O48: =IFERROR((VLOOKUP($A48,'Dados StatusInvest'!$A:$AZ,COLUMN(O48)-$A$5,0)/VLOOKUP($A48,'Dados StatusInvest'!$A:$AZ,2,0)*$F48),0) -> 0 | P48: =IFERROR((VLOOKUP($A48,'Dados StatusInvest'!$A:$AZ,COLUMN(P48)-$A$5,0)/VLOOKUP($A48,'Dados StatusInvest'!$A:$AZ,2,0)*$F48),0) -> 0 | Q48: =IFERROR((VLOOKUP($A48,'Dados StatusInvest'!$A:$AZ,COLUMN(Q48)-$A$5,0)/100),0) -> -0.0238 | R48: =VLOOKUP($A48,'Dados StatusInvest'!$A:$AZ,COLUMN(R48)-$A$5,0) -> 0.49 | S48: =IFERROR((VLOOKUP($A48,'Dados StatusInvest'!$A:$AZ,COLUMN(S48)-$A$5,0)),0) -> 0.35 | T48: =IFERROR((VLOOKUP($A48,'Dados StatusInvest'!$A:$AZ,COLUMN(T48)-$A$5,0)/VLOOKUP($A48,'Dados StatusInvest'!$A:$AZ,2,0)*$F48),0) -> 0 | U48: =IFERROR((VLOOKUP($A48,'Dados StatusInvest'!$A:$AZ,COLUMN(U48)-$A$5,0)-VLOOKUP($A48,'Dados StatusInvest'!$A:$AZ,COLUMN(U48)-$A$5-1,0)+T48),0) -> 0.86 | V48: =IFERROR((VLOOKUP($A48,'Dados StatusInvest'!$A:$AZ,COLUMN(V48)-$A$5,0)),0) -> 0.33 | W48: =IFERROR((VLOOKUP($A48,'Dados StatusInvest'!$A:$AZ,COLUMN(W48)-$A$5,0)),0) -> -82.07 | X48: =IFERROR((VLOOKUP($A48,'Dados StatusInvest'!$A:$AZ,COLUMN(X48)-$A$5,0)/VLOOKUP($A48,'Dados StatusInvest'!$A:$AZ,2,0)*$F48),0) -> 0 | Y48: =IFERROR((VLOOKUP($A48,'Dados StatusInvest'!$A:$AZ,COLUMN(Y48)-$A$5,0)/VLOOKUP($A48,'Dados StatusInvest'!$A:$AZ,2,0)*$F48),0) -> 0 | Z48: =IFERROR((VLOOKUP($A48,'Dados StatusInvest'!$A:$AZ,COLUMN(Z48)-$A$5,0)),0) -> 0.15 | AA48: =IFERROR((VLOOKUP($A48,'Dados StatusInvest'!$A:$AZ,COLUMN(AA48)-$A$5,0)),0) -> 0.78 | AB48: =IFERROR((VLOOKUP($A48,'Dados StatusInvest'!$A:$AZ,COLUMN(AB48)-$A$5,0)),0) -> 0.77 | AC48: =IFERROR((VLOOKUP($A48,'Dados StatusInvest'!$A:$AZ,COLUMN(AC48)-$A$5,0)),0) -> 46.22 | AD48: =IFERROR((VLOOKUP($A48,'Dados StatusInvest'!$A:$AZ,COLUMN(AD48)-$A$5,0)),0) -> 0 | AE48: =IFERROR((VLOOKUP($A48,'Dados StatusInvest'!$A:$AZ,COLUMN(AE48)-$A$5,0)),0) -> 16499 | AF48: =IFERROR((VLOOKUP($A48,'Dados StatusInvest'!$A:$AZ,COLUMN(AF48)-$A$5,0)),0) -> 2.53 | AG48: =IFERROR((VLOOKUP($A48,'Dados StatusInvest'!$A:$AZ,COLUMN(AG48)-$A$5,0)),0) -> -2.07 | ... AJ48: =IFERROR((VLOOKUP($A48,'Dados StatusInvest'!$A:$AZ,COLUMN(AJ48)-$A$5,0)),0) | AK48: =IFERROR(__xludf.DUMMYFUNCTION("IFERROR(GOOGLEFINANCE($A48,""high""),"""")"),"") | AL48: =IFERROR(__xludf.DUMMYFUNCTION("IFERROR(GOOGLEFINANCE($A48,""low""),"""")"),"") | AM48: =IFERROR(((AK48-AL48)/AL48),0) -> 0 | AN48: =IFERROR(__xludf.DUMMYFUNCTION("IFERROR((GOOGLEFINANCE($A48,""volume"")),0)"),0.0) -> 0 | AO48: =IFERROR(__xludf.DUMMYFUNCTION("IFERROR((GOOGLEFINANCE($A48,""closeyest"")),"""")"),"") | AP48: =IFERROR(__xludf.DUMMYFUNCTION("IFERROR((GOOGLEFINANCE($A48,""shares"")),"""")"),"")
A49: ='Dados StatusInvest'!A44:A663 -> BALM3 | B49: =IFERROR(__xludf.DUMMYFUNCTION("IFERROR((GOOGLEFINANCE(A49,""name"")),"""")"),"Baumer SA") -> Baumer SA | C49: =IFERROR((VLOOKUP(LEFT($A49,4),Setor!$A:$E,3,0)),"") -> Saúde | D49: =IFERROR((VLOOKUP(LEFT($A49,4),Setor!$A:$E,4,0)),"") -> Equipamentos | E49: =IFERROR((VLOOKUP(LEFT($A49,4),Setor!$A:$E,5,0)),"") -> Equipamentos | F49: =IFERROR(__xludf.DUMMYFUNCTION("IFERROR((GOOGLEFINANCE(A49)),"""")"),26.0) -> 26 | G49: =IFERROR(__xludf.DUMMYFUNCTION("IFERROR((sparkline(GOOGLEFINANCE($A49,""price"",TODAY()-30,TODAY(),""DAILY""),{""charttype"",""line"";""linewidth"",1;""color"",""#5f88cc""})),"""")"),"") | H49: =IFERROR(__xludf.DUMMYFUNCTION("IFERROR((((GOOGLEFINANCE(A49))-(INDEX(GoogleFinance(A49,""PRICE"",$AQ$1),2,2)))/(INDEX(GoogleFinance(A49,""PRICE"",$AQ$1),2,2))),"""")"),-0.13333333333333333) -> -0.13333333 | I49: =IFERROR(__xludf.DUMMYFUNCTION("IFERROR((GOOGLEFINANCE($A49,""high52"")),"""")"),30.0) -> 30 | J49: =IFERROR(__xludf.DUMMYFUNCTION("IFERROR((sparkline(GOOGLEFINANCE($A49,""price"",TODAY()-365,TODAY(),""DAILY""),{""charttype"",""line"";""linewidth"",1;""color"",""#5f88cc""})),"""")"),"") | K49: =IFERROR(__xludf.DUMMYFUNCTION("IFERROR((((GOOGLEFINANCE(A49))-(INDEX(GoogleFinance(A49,""PRICE"",$AP$1),2,2)))/(INDEX(GoogleFinance(A49,""PRICE"",$AP$1),2,2))),"""")"),0.5312131919905771) -> 0.53121319 | L49: =IFERROR(((F49-I49)/I49),0) -> -0.13333333 | M49: =IFERROR((VLOOKUP($A49,'Dados StatusInvest'!$A:$AZ,COLUMN(M49)-$A$5,0)*VLOOKUP($A49,'Dados StatusInvest'!$A:$AZ,2,0)/$F49/100),0) -> 0.2078 | N49: =IFERROR((VLOOKUP($A49,'Dados StatusInvest'!$A:$AZ,COLUMN(N49)-$A$5,0)/VLOOKUP($A49,'Dados StatusInvest'!$A:$AZ,2,0)*$F49),"") -> 11.28 | O49: =IFERROR((VLOOKUP($A49,'Dados StatusInvest'!$A:$AZ,COLUMN(O49)-$A$5,0)/VLOOKUP($A49,'Dados StatusInvest'!$A:$AZ,2,0)*$F49),0) -> 5.59 | P49: =IFERROR((VLOOKUP($A49,'Dados StatusInvest'!$A:$AZ,COLUMN(P49)-$A$5,0)/VLOOKUP($A49,'Dados StatusInvest'!$A:$AZ,2,0)*$F49),0) -> 3.25 | Q49: =IFERROR((VLOOKUP($A49,'Dados StatusInvest'!$A:$AZ,COLUMN(Q49)-$A$5,0)/100),0) -> -0.0156 | R49: =VLOOKUP($A49,'Dados StatusInvest'!$A:$AZ,COLUMN(R49)-$A$5,0) -> -0.39 | S49: =IFERROR((VLOOKUP($A49,'Dados StatusInvest'!$A:$AZ,COLUMN(S49)-$A$5,0)),0) -> 1.16 | T49: =IFERROR((VLOOKUP($A49,'Dados StatusInvest'!$A:$AZ,COLUMN(T49)-$A$5,0)/VLOOKUP($A49,'Dados StatusInvest'!$A:$AZ,2,0)*$F49),0) -> 1.67 | U49: =IFERROR((VLOOKUP($A49,'Dados StatusInvest'!$A:$AZ,COLUMN(U49)-$A$5,0)-VLOOKUP($A49,'Dados StatusInvest'!$A:$AZ,COLUMN(U49)-$A$5-1,0)+T49),0) -> -3.34 | V49: =IFERROR((VLOOKUP($A49,'Dados StatusInvest'!$A:$AZ,COLUMN(V49)-$A$5,0)),0) -> 3.12 | W49: =IFERROR((VLOOKUP($A49,'Dados StatusInvest'!$A:$AZ,COLUMN(W49)-$A$5,0)),0) -> 13.52 | X49: =IFERROR((VLOOKUP($A49,'Dados StatusInvest'!$A:$AZ,COLUMN(X49)-$A$5,0)/VLOOKUP($A49,'Dados StatusInvest'!$A:$AZ,2,0)*$F49),0) -> 8.23 | Y49: =IFERROR((VLOOKUP($A49,'Dados StatusInvest'!$A:$AZ,COLUMN(Y49)-$A$5,0)/VLOOKUP($A49,'Dados StatusInvest'!$A:$AZ,2,0)*$F49),0) -> 19.28 | Z49: =IFERROR((VLOOKUP($A49,'Dados StatusInvest'!$A:$AZ,COLUMN(Z49)-$A$5,0)),0) -> 0.61 | AA49: =IFERROR((VLOOKUP($A49,'Dados StatusInvest'!$A:$AZ,COLUMN(AA49)-$A$5,0)),0) -> 0.39 | AB49: =IFERROR((VLOOKUP($A49,'Dados StatusInvest'!$A:$AZ,COLUMN(AB49)-$A$5,0)),0) -> 0.73 | AC49: =IFERROR((VLOOKUP($A49,'Dados StatusInvest'!$A:$AZ,COLUMN(AC49)-$A$5,0)),0) -> 5.42 | AD49: =IFERROR((VLOOKUP($A49,'Dados StatusInvest'!$A:$AZ,COLUMN(AD49)-$A$5,0)),0) -> 31.66 | AE49: =IFERROR((VLOOKUP($A49,'Dados StatusInvest'!$A:$AZ,COLUMN(AE49)-$A$5,0)),0) -> 7411.71 | AF49: =IFERROR((VLOOKUP($A49,'Dados StatusInvest'!$A:$AZ,COLUMN(AF49)-$A$5,0)),0) -> 18.67 | AG49: =IFERROR((VLOOKUP($A49,'Dados StatusInvest'!$A:$AZ,COLUMN(AG49)-$A$5,0)),0) -> 2.52 | ... AJ49: =IFERROR((VLOOKUP($A49,'Dados StatusInvest'!$A:$AZ,COLUMN(AJ49)-$A$5,0)),0) | AK49: =IFERROR(__xludf.DUMMYFUNCTION("IFERROR(GOOGLEFINANCE($A49,""high""),"""")"),"") | AL49: =IFERROR(__xludf.DUMMYFUNCTION("IFERROR(GOOGLEFINANCE($A49,""low""),"""")"),"") | AM49: =IFERROR(((AK49-AL49)/AL49),0) -> 0 | AN49: =IFERROR(__xludf.DUMMYFUNCTION("IFERROR((GOOGLEFINANCE($A49,""volume"")),0)"),0.0) -> 0 | AO49: =IFERROR(__xludf.DUMMYFUNCTION("IFERROR((GOOGLEFINANCE($A49,""closeyest"")),"""")"),26.0) -> 26 | AP49: =IFERROR(__xludf.DUMMYFUNCTION("IFERROR((GOOGLEFINANCE($A49,""shares"")),"""")"),4900000.0) -> 4900000
A50: ='Dados StatusInvest'!A45:A664 -> BALM4 | B50: =IFERROR(__xludf.DUMMYFUNCTION("IFERROR((GOOGLEFINANCE(A50,""name"")),"""")"),"Baumer SA Preference Shares") -> Baumer SA Preference Shares | C50: =IFERROR((VLOOKUP(LEFT($A50,4),Setor!$A:$E,3,0)),"") -> Saúde | D50: =IFERROR((VLOOKUP(LEFT($A50,4),Setor!$A:$E,4,0)),"") -> Equipamentos | E50: =IFERROR((VLOOKUP(LEFT($A50,4),Setor!$A:$E,5,0)),"") -> Equipamentos | F50: =IFERROR(__xludf.DUMMYFUNCTION("IFERROR((GOOGLEFINANCE(A50)),"""")"),18.51) -> 18.51 | G50: =IFERROR(__xludf.DUMMYFUNCTION("IFERROR((sparkline(GOOGLEFINANCE($A50,""price"",TODAY()-30,TODAY(),""DAILY""),{""charttype"",""line"";""linewidth"",1;""color"",""#5f88cc""})),"""")"),"") | H50: =IFERROR(__xludf.DUMMYFUNCTION("IFERROR((((GOOGLEFINANCE(A50))-(INDEX(GoogleFinance(A50,""PRICE"",$AQ$1),2,2)))/(INDEX(GoogleFinance(A50,""PRICE"",$AQ$1),2,2))),"""")"),0.006525285481239858) -> 0.0065252855 | I50: =IFERROR(__xludf.DUMMYFUNCTION("IFERROR((GOOGLEFINANCE($A50,""high52"")),"""")"),21.8) -> 21.8 | J50: =IFERROR(__xludf.DUMMYFUNCTION("IFERROR((sparkline(GOOGLEFINANCE($A50,""price"",TODAY()-365,TODAY(),""DAILY""),{""charttype"",""line"";""linewidth"",1;""color"",""#5f88cc""})),"""")"),"") | K50: =IFERROR(__xludf.DUMMYFUNCTION("IFERROR((((GOOGLEFINANCE(A50))-(INDEX(GoogleFinance(A50,""PRICE"",$AP$1),2,2)))/(INDEX(GoogleFinance(A50,""PRICE"",$AP$1),2,2))),"""")"),0.698165137614679) -> 0.69816514 | L50: =IFERROR(((F50-I50)/I50),0) -> -0.15091743 | M50: =IFERROR((VLOOKUP($A50,'Dados StatusInvest'!$A:$AZ,COLUMN(M50)-$A$5,0)*VLOOKUP($A50,'Dados StatusInvest'!$A:$AZ,2,0)/$F50/100),0) -> 0.21060659 | N50: =IFERROR((VLOOKUP($A50,'Dados StatusInvest'!$A:$AZ,COLUMN(N50)-$A$5,0)/VLOOKUP($A50,'Dados StatusInvest'!$A:$AZ,2,0)*$F50),"") -> 11.12968 | O50: =IFERROR((VLOOKUP($A50,'Dados StatusInvest'!$A:$AZ,COLUMN(O50)-$A$5,0)/VLOOKUP($A50,'Dados StatusInvest'!$A:$AZ,2,0)*$F50),0) -> 3.9762953 | P50: =IFERROR((VLOOKUP($A50,'Dados StatusInvest'!$A:$AZ,COLUMN(P50)-$A$5,0)/VLOOKUP($A50,'Dados StatusInvest'!$A:$AZ,2,0)*$F50),0) -> 3.2066898 | Q50: =IFERROR((VLOOKUP($A50,'Dados StatusInvest'!$A:$AZ,COLUMN(Q50)-$A$5,0)/100),0) -> -0.0156 | R50: =VLOOKUP($A50,'Dados StatusInvest'!$A:$AZ,COLUMN(R50)-$A$5,0) -> -0.39 | S50: =IFERROR((VLOOKUP($A50,'Dados StatusInvest'!$A:$AZ,COLUMN(S50)-$A$5,0)),0) -> 0.84 | T50: =IFERROR((VLOOKUP($A50,'Dados StatusInvest'!$A:$AZ,COLUMN(T50)-$A$5,0)/VLOOKUP($A50,'Dados StatusInvest'!$A:$AZ,2,0)*$F50),0) -> 1.1938753 | U50: =IFERROR((VLOOKUP($A50,'Dados StatusInvest'!$A:$AZ,COLUMN(U50)-$A$5,0)-VLOOKUP($A50,'Dados StatusInvest'!$A:$AZ,COLUMN(U50)-$A$5-1,0)+T50),0) -> -2.4261247 | V50: =IFERROR((VLOOKUP($A50,'Dados StatusInvest'!$A:$AZ,COLUMN(V50)-$A$5,0)),0) -> 3.12 | W50: =IFERROR((VLOOKUP($A50,'Dados StatusInvest'!$A:$AZ,COLUMN(W50)-$A$5,0)),0) -> 13.52 | X50: =IFERROR((VLOOKUP($A50,'Dados StatusInvest'!$A:$AZ,COLUMN(X50)-$A$5,0)/VLOOKUP($A50,'Dados StatusInvest'!$A:$AZ,2,0)*$F50),0) -> 8.1203252 | Y50: =IFERROR((VLOOKUP($A50,'Dados StatusInvest'!$A:$AZ,COLUMN(Y50)-$A$5,0)/VLOOKUP($A50,'Dados StatusInvest'!$A:$AZ,2,0)*$F50),0) -> 19.02307 | Z50: =IFERROR((VLOOKUP($A50,'Dados StatusInvest'!$A:$AZ,COLUMN(Z50)-$A$5,0)),0) -> 0.61 | AA50: =IFERROR((VLOOKUP($A50,'Dados StatusInvest'!$A:$AZ,COLUMN(AA50)-$A$5,0)),0) -> 0.39 | AB50: =IFERROR((VLOOKUP($A50,'Dados StatusInvest'!$A:$AZ,COLUMN(AB50)-$A$5,0)),0) -> 0.73 | AC50: =IFERROR((VLOOKUP($A50,'Dados StatusInvest'!$A:$AZ,COLUMN(AC50)-$A$5,0)),0) -> 5.42 | AD50: =IFERROR((VLOOKUP($A50,'Dados StatusInvest'!$A:$AZ,COLUMN(AD50)-$A$5,0)),0) -> 31.66 | AE50: =IFERROR((VLOOKUP($A50,'Dados StatusInvest'!$A:$AZ,COLUMN(AE50)-$A$5,0)),0) -> 20127.4 | AF50: =IFERROR((VLOOKUP($A50,'Dados StatusInvest'!$A:$AZ,COLUMN(AF50)-$A$5,0)),0) -> 18.67 | AG50: =IFERROR((VLOOKUP($A50,'Dados StatusInvest'!$A:$AZ,COLUMN(AG50)-$A$5,0)),0) -> 2.52 | ... AJ50: =IFERROR((VLOOKUP($A50,'Dados StatusInvest'!$A:$AZ,COLUMN(AJ50)-$A$5,0)),0) | AK50: =IFERROR(__xludf.DUMMYFUNCTION("IFERROR(GOOGLEFINANCE($A50,""high""),"""")"),18.51) -> 18.51 | AL50: =IFERROR(__xludf.DUMMYFUNCTION("IFERROR(GOOGLEFINANCE($A50,""low""),"""")"),18.51) -> 18.51 | AM50: =IFERROR(((AK50-AL50)/AL50),0) -> 0 | AN50: =IFERROR(__xludf.DUMMYFUNCTION("IFERROR((GOOGLEFINANCE($A50,""volume"")),0)"),500.0) -> 500 | AO50: =IFERROR(__xludf.DUMMYFUNCTION("IFERROR((GOOGLEFINANCE($A50,""closeyest"")),"""")"),18.76) -> 18.76 | AP50: =IFERROR(__xludf.DUMMYFUNCTION("IFERROR((GOOGLEFINANCE($A50,""shares"")),"""")"),4900000.0) -> 4900000
